Workbook

Sheet Generales
A1: 2025 | B1: 5
B2: Período
B3: Fecha de inicio | C3: Fecha final | D3: Días de revisión | E3: Años de revisión
B4: 45909 | C4: 46010 | D4: =_xlfn.DAYS(C4,B4) -> 101 | E4: =D4/365 -> 0.27671233

Sheet Liquidación Laboral
A1: Salario Mensual Base | B1: 1423500 | C1: Año | D1: 2025
A2: Salario Quincenal | B2: =B1/2 -> 711750
A3: Auxilio de transporte | E3: Historico salarios mínimos
A4: Días trabajados en el Semestre | B4: 180 | F4: 2019 | G4: 2020 | H4: 2021 | I4: 2022 | J4: 2023 | K4: 2024 | L4: 2025 | M4: 2026
A5: Días trabajados en el Año | B5: 360 | E5: Salario Mensual | F5: 828211 | G5: 877802 | H5: 908526 | I5: 1000000 | J5: 1160000 | K5: 1300000 | L5: 1423500
A6: Salud Empleado | B6: =B1*0.04 -> 56940 | E6: Auxilio de transporte | F6: 97032 | G6: 102853 | H6: 106454 | I6: 117172 | J6: 140606 | K6: 162000 | L6: 200000
A7: Salud Empleador | B7: =IF(F19<2,B1*0.085,IF(B1/HLOOKUP(D1,F4:M6,2,FALSE)>10,B1*0.085,0)) -> 0 | F7: =F5*2 -> 1656422 | G7: =G5*2 -> 1755604 | H7: =H5*2 -> 1817052 | I7: =I5*2 -> 2000000 | J7: =J5*2 -> 2320000 | K7: =K5*2 -> 2600000 | L7: =L5*2 -> 2847000
A8: Pensión Empleado | B8: =B1*0.04 -> 56940 | E8: Nivel de Riesgo | F8: Porcentaje | G8: Riesgo iv | H8: Riesgo del Empleado
A9: Pensión Empleador | B9: =B1*0.12 -> 170820 | E9: Riesgo I | F9: 0.00522
A10: ARL | B10: =B1*(VLOOKUP(G8,E9:F13,2,FALSE)) -> 61922.25 | E10: Riesgo II | F10: 0.01044
A11: Prima | B11: =((B1+B3)*B4/360) -> 711750 | E11: Riesgo III | F11: 0.02436
A12: Cesantías | B12: =((B1+B3)*B5/360) -> 1423500 | E12: Riesgo IV | F12: 0.0435 | I12: ARTÍCULO 114-1 Estatuto Tributario. Así mismo las personas naturales empleadoras estarán exoneradas de la obligación de pago de los aportes parafiscales al SENA, al ICBF y al Sistema de Seguridad Social en Salud por los empleados que devenguen menos de diez (10) salarios mínimos legales mensuales vigentes. Lo anterior no aplicará para personas naturales que empleen menos de dos trabajadores, los cuales seguirán obligados a efectuar los aportes de que trata este inciso.
A13: Intereses a las Cesantías | B13: =(B12*B5*0.12)/360 -> 170820 | E13: Riesgo V | F13: 0.0696
A14: Cesantías + intereses | B14: =B12+B13 -> 1594320
A15: Vacaciones | B15: =(B1*B5)/720 -> 711750
A16: Fondo de solidaridad pensional | B16: =IF(B1/HLOOKUP(D1,F4:M7,2,FALSE)>4,B1*1%,0) -> 0
A17: Cajas de compensación familiar | B17: =IF(F19<2,B1*0.04,IF(B1/HLOOKUP(D1,F4:M7,2,FALSE)>10,B1*0.04,0)) -> 0 | E17: Total Días | F17: Día inicial | G17: Dia final
A18: I.C.B.F. (3%). | B18: =IF(F19<2,B1*0.03,IF(B1/HLOOKUP(D1,F4:M7,2,FALSE)>10,B1*0.03,0)) -> 0 | E18: =DAYS360(F18,G18) -> 150 | F18: 44774 | G18: 44926
A19: Sena | B19: =IF(F19<2,B1*0.02,IF(B1/HLOOKUP(D1,F4:M7,2,FALSE)>10,B1*0.02,0)) -> 0 | E19: Total empleados | F19: 2

Sheet Calendario Tributario
B1: Fechas de Retención en la Fuente | N1: Fechas IVA Bimestral | W1: Fechas IVA Cuatrimestral
A2: Número mes | B2: MES | C2: Último dig | D2: DATO UN | E2: 2018 | F2: 2019 | G2: 2020 | H2: 2021 | I2: 2022 | J2: 2023 | K2: 2024 | L2: 2025 | N2: DATO UN | O2: Último Dig | P2: 2019 | Q2: 2020 | R2: 2021 | S2: 2022 | T2: 2023 | U2: 2024 | W2: DATO UN | X2: Último Dig | Y2: 2019 | Z2: 2020 | AA2: 2021 | AB2: 2022 | AC2: 2023 | AD2: 2024 | AF2: Últ Dígito
A3: 1 | B3: ENERO | C3: 0 | D3: =CONCATENATE(B3,C3) -> ENERO0 | E3: 43139 | F3: 43504 | G3: 43872 | H3: 44249 | I3: 44613 | J3: 44977 | K3: 45344 | L3: 45712 | N3: Enero - Febrero | O3: 0 | W3: Enero - Abril | X3: 0 | AF3: 0
A4: 2 | B4: FEBRERO | C4: 0 | D4: =CONCATENATE(B4,C4) -> FEBRERO0 | E4: 43167 | F4: 43532 | G4: 43900 | H4: 44278 | I4: 44642 | J4: 45006 | K4: 45373 | L4: 45741 | N4: Marzo - Abril | O4: 0 | W4: Mayo - Agosto | X4: 0 | AF4: 1
A5: 3 | B5: MARZO | C5: 0 | D5: =CONCATENATE(B5,C5) -> MARZO0 | E5: 43200 | F5: 43564 | G5: 43935 | H5: 44309 | I5: 44673 | J5: 45037 | K5: 45404 | L5: 45771 | N5: Mayo - Junio | O5: 0 | W5: Septiembre - Diciembre | X5: 0 | AF5: 2
A6: 4 | B6: ABRIL | C6: 0 | D6: =CONCATENATE(B6,C6) -> ABRIL0 | E6: 43229 | F6: 43594 | G6: 43963 | H6: 44340 | I6: 44704 | J6: 45069 | K6: 45436 | L6: 45800 | N6: Julio - Agosto | O6: 0 | W6: Enero - Abril | X6: 1 | AF6: 3
A7: 5 | B7: MAYO | C7: 0 | D7: =CONCATENATE(B7,C7) -> MAYO0 | E7: 43264 | F7: 43627 | G7: 43991 | H7: 44370 | I7: 44733 | J7: 45099 | K7: 45469 | L7: 45833 | N7: Septiembre - Octubre | O7: 0 | W7: Mayo - Agosto | X7: 1 | AF7: 4
A8: 6 | B8: JUNIO | C8: 0 | D8: =CONCATENATE(B8,C8) -> JUNIO0 | E8: 43291 | F8: 43655 | G8: 44019 | H8: 44399 | I8: 44764 | J8: 45128 | K8: 45496 | L8: 45860 | N8: Noviembre - Diciembre | O8: 0 | W8: Septiembre - Diciembre | X8: 1 | AF8: 5
A9: 7 | B9: JULIO | C9: 0 | D9: =CONCATENATE(B9,C9) -> JULIO0 | E9: 43321 | F9: 43686 | G9: 44054 | H9: 44432 | I9: 44796 | J9: 45161 | K9: 45530 | L9: 45895 | N9: Enero - Febrero | O9: 1 | W9: Enero - Abril | X9: 2 | AF9: 6
A10: 8 | B10: AGOSTO | C10: 0 | D10: =CONCATENATE(B10,C10) -> AGOSTO0 | E10: 43354 | F10: 43718 | G10: 44082 | H10: 44460 | I10: 44824 | J10: 45189 | K10: 45558 | L10: 45922 | N10: Marzo - Abril | O10: 1 | W10: Mayo - Agosto | X10: 2 | AF10: 7
A11: 9 | B11: SEPTIEMBRE | C11: 0 | D11: =CONCATENATE(B11,C11) -> SEPTIEMBRE0 | E11: 43382 | F11: 43746 | G11: 44110 | H11: 44490 | I11: 44855 | J11: 45223 | K11: 45588 | L11: 45953 | N11: Mayo - Junio | O11: 1 | W11: Septiembre - Diciembre | X11: 2 | AF11: 8
A12: 10 | B12: OCTUBRE | C12: 0 | D12: =CONCATENATE(B12,C12) -> OCTUBRE0 | E12: 43413 | F12: 43781 | G12: 44145 | H12: 44523 | I12: 44888 | J12: 45252 | K12: 45622 | L12: 45987 | N12: Julio - Agosto | O12: 1 | W12: Enero - Abril | X12: 3 | AF12: 9
A13: 11 | B13: NOVIEMBRE | C13: 0 | D13: =CONCATENATE(B13,C13) -> NOVIEMBRE0 | E13: 43444 | F13: 43809 | G13: 44175 | H13: 44553 | I13: 44918 | J13: 44917 | K13: 45649 | L13: 46014 | N13: Septiembre - Octubre | O13: 1 | W13: Mayo - Agosto | X13: 3
A14: 12 | B14: DICIEMBRE | C14: 0 | D14: =CONCATENATE(B14,C14) -> DICIEMBRE0 | E14: 43476 | F14: 43840 | G14: 44209 | H14: 44586 | I14: 44950 | J14: 45314 | K14: 45681 | L14: 46048 | N14: Noviembre - Diciembre | O14: 1 | W14: Septiembre - Diciembre | X14: 3
A15: 1 | B15: ENERO | C15: 1 | D15: =CONCATENATE(B15,C15) -> ENERO1 | E15: 43152 | F15: 43517 | G15: 43885 | H15: 44236 | I15: 44600 | J15: 44964 | K15: 45331 | L15: 45699 | N15: Enero - Febrero | O15: 2 | W15: Enero - Abril | X15: 4
A16: 2 | B16: FEBRERO | C16: 1 | D16: =CONCATENATE(B16,C16) -> FEBRERO1 | E16: 43181 | F16: 43545 | G16: 43914 | H16: 44264 | I16: 44628 | J16: 44992 | K16: 45362 | L16: 45727 | N16: Marzo - Abril | O16: 2 | W16: Mayo - Agosto | X16: 4
A17: 3 | B17: MARZO | C17: 1 | D17: =CONCATENATE(B17,C17) -> MARZO1 | E17: 43213 | F17: 43576 | G17: 43948 | H17: 44298 | I17: 44658 | J17: 45026 | K17: 45391 | L17: 45756 | N17: Mayo - Junio | O17: 2 | W17: Septiembre - Diciembre | X17: 4
A18: 4 | B18: ABRIL | C18: 1 | D18: =CONCATENATE(B18,C18) -> ABRIL1 | E18: 43243 | F18: 43607 | G18: 43977 | H18: 44326 | I18: 44691 | J18: 45055 | K18: 45422 | L18: 45789 | N18: Julio - Agosto | O18: 2 | W18: Enero - Abril | X18: 5
A19: 5 | B19: MAYO | C19: 1 | D19: =CONCATENATE(B19,C19) -> MAYO1 | E19: 43277 | F19: 43641 | G19: 44006 | H19: 44356 | I19: 44719 | J19: 45084 | K19: 45456 | L19: 45819 | N19: Septiembre - Octubre | O19: 2 | W19: Mayo - Agosto | X19: 5
A20: 6 | B20: JUNIO | C20: 1 | D20: =CONCATENATE(B20,C20) -> JUNIO1 | E20: 43305 | F20: 43668 | G20: 44033 | H20: 44385 | I20: 44750 | J20: 45114 | K20: 45483 | L20: 45847 | N20: Noviembre - Diciembre | O20: 2 | W20: Septiembre - Diciembre | X20: 5
A21: 7 | B21: JULIO | C21: 1 | D21: =CONCATENATE(B21,C21) -> JULIO1 | E21: 43335 | F21: 43700 | G21: 44068 | H21: 44418 | I21: 44782 | J21: 45147 | K21: 45516 | L21: 45881 | N21: Enero - Febrero | O21: 3 | W21: Enero - Abril | X21: 6
A22: 8 | B22: AGOSTO | C22: 1 | D22: =CONCATENATE(B22,C22) -> AGOSTO1 | E22: 43367 | F22: 43731 | G22: 44095 | H22: 44447 | I22: 44811 | J22: 45176 | K22: 45545 | L22: 45909 | N22: Marzo - Abril | O22: 3 | W22: Mayo - Agosto | X22: 6
A23: 9 | B23: SEPTIEMBRE | C23: 1 | D23: =CONCATENATE(B23,C23) -> SEPTIEMBRE1 | E23: 43396 | F23: 43760 | G23: 44124 | H23: 44476 | I23: 44841 | J23: 45209 | K23: 45574 | L23: 45939 | N23: Mayo - Junio | O23: 3 | W23: Septiembre - Diciembre | X23: 6
A24: 10 | B24: OCTUBRE | C24: 1 | D24: =CONCATENATE(B24,C24) -> OCTUBRE1 | E24: 43427 | F24: 43794 | G24: 44159 | H24: 44509 | I24: 44874 | J24: 45238 | K24: 45609 | L24: 45973 | N24: Julio - Agosto | O24: 3 | W24: Enero - Abril | X24: 7
... A32: 6 | B32: JUNIO | C32: 2 | D32: =CONCATENATE(B32,C32) -> JUNIO2 | E32: 43304 | F32: 43665 | G32: 44029 | H32: 44386 | I32: 44753 | J32: 45117 | K32: 45484 | L32: 45848 | N32: Noviembre - Diciembre | O32: 4 | W32: Septiembre - Diciembre | X32: 9
A33: 7 | B33: JULIO | C33: 2 | D33: =CONCATENATE(B33,C33) -> JULIO2 | E33: 43334 | F33: 43699 | G33: 44067 | H33: 44419 | I33: 44783 | J33: 45148 | K33: 45517 | L33: 45882 | N33: Enero - Febrero | O33: 5
A34: 8 | B34: AGOSTO | C34: 2 | D34: =CONCATENATE(B34,C34) -> AGOSTO2 | E34: 43364 | F34: 43728 | G34: 44092 | H34: 44448 | I34: 44812 | J34: 45177 | K34: 45546 | L34: 45910 | N34: Marzo - Abril | O34: 5
A35: 9 | B35: SEPTIEMBRE | C35: 2 | D35: =CONCATENATE(B35,C35) -> SEPTIEMBRE2 | E35: 43395 | F35: 43759 | G35: 44123 | H35: 44477 | I35: 44844 | J35: 45210 | K35: 45575 | L35: 45940 | N35: Mayo - Junio | O35: 5
A36: 10 | B36: OCTUBRE | C36: 2 | D36: =CONCATENATE(B36,C36) -> OCTUBRE2 | E36: 43426 | F36: 43791 | G36: 44158 | H36: 44510 | I36: 44875 | J36: 45239 | K36: 45610 | L36: 45974 | N36: Julio - Agosto | O36: 5
A37: 11 | B37: NOVIEMBRE | C37: 2 | D37: =CONCATENATE(B37,C37) -> NOVIEMBRE2 | E37: 43454 | F37: 43819 | G37: 44187 | H37: 44543 | I37: 44908 | J37: 45272 | K37: 45637 | L37: 46002 | N37: Septiembre - Octubre | O37: 5
A38: 12 | B38: DICIEMBRE | C38: 2 | D38: =CONCATENATE(B38,C38) -> DICIEMBRE2 | E38: 43488 | F38: 43852 | G38: 44221 | H38: 44574 | I38: 44938 | J38: 45302 | K38: 45671 | L38: 46036 | N38: Noviembre - Diciembre | O38: 5
A39: 1 | B39: ENERO | C39: 3 | D39: =CONCATENATE(B39,C39) -> ENERO3 | E39: 43150 | F39: 43515 | G39: 43881 | H39: 44238 | I39: 44602 | J39: 44966 | K39: 45335 | L39: 45701 | N39: Enero - Febrero | O39: 6
A40: 2 | B40: FEBRERO | C40: 3 | D40: =CONCATENATE(B40,C40) -> FEBRERO3 | E40: 43179 | F40: 43543 | G40: 43909 | H40: 44266 | I40: 44630 | J40: 44994 | K40: 45364 | L40: 45729 | N40: Marzo - Abril | O40: 6
A41: 3 | B41: MARZO | C41: 3 | D41: =CONCATENATE(B41,C41) -> MARZO3 | E41: 43209 | F41: 43578 | G41: 43944 | H41: 44300 | I41: 44662 | J41: 45028 | K41: 45393 | L41: 45758 | N41: Mayo - Junio | O41: 6
A42: 4 | B42: ABRIL | C42: 3 | D42: =CONCATENATE(B42,C42) -> ABRIL3 | E42: 43241 | F42: 43605 | G42: 43972 | H42: 44328 | I42: 44693 | J42: 45057 | K42: 45427 | L42: 45791 | N42: Julio - Agosto | O42: 6
A43: 5 | B43: MAYO | C43: 3 | D43: =CONCATENATE(B43,C43) -> MAYO3 | E43: 43273 | F43: 43636 | G43: 44001 | H43: 44358 | I43: 44721 | J43: 45086 | K43: 45460 | L43: 45821 | N43: Septiembre - Octubre | O43: 6
A44: 6 | B44: JUNIO | C44: 3 | D44: =CONCATENATE(B44,C44) -> JUNIO3 | E44: 43300 | F44: 43664 | G44: 44028 | H44: 44389 | I44: 44754 | J44: 45118 | K44: 45485 | L44: 45849 | N44: Noviembre - Diciembre | O44: 6
... A62: 12 | B62: DICIEMBRE | C62: 4 | D62: =CONCATENATE(B62,C62) -> DICIEMBRE4 | E62: 43486 | F62: 43850 | G62: 44217 | H62: 44578 | I62: 44942 | J62: 45306 | K62: 45673 | L62: 46038 | N62: Noviembre - Diciembre | O62: 9
A63: 1 | B63: ENERO | C63: 5 | D63: =CONCATENATE(B63,C63) -> ENERO5 | E63: 43146 | F63: 43511 | G63: 43879 | H63: 44242 | I63: 44606 | J63: 44970 | K63: 45337 | L63: 45705
A64: 2 | B64: FEBRERO | C64: 5 | D64: =CONCATENATE(B64,C64) -> FEBRERO5 | E64: 43174 | F64: 43539 | G64: 43907 | H64: 44270 | I64: 44634 | J64: 44998 | K64: 45366 | L64: 45733
A65: 3 | B65: MARZO | C65: 5 | D65: =CONCATENATE(B65,C65) -> MARZO5 | E65: 43207 | F65: 43571 | G65: 43942 | H65: 44302 | I65: 44664 | J65: 45030 | K65: 45397 | L65: 45762
A66: 4 | B66: ABRIL | C66: 5 | D66: =CONCATENATE(B66,C66) -> ABRIL5 | E66: 43237 | F66: 43601 | G66: 43970 | H66: 44330 | I66: 44697 | J66: 45061 | K66: 45429 | L66: 45793
A67: 5 | B67: MAYO | C67: 5 | D67: =CONCATENATE(B67,C67) -> MAYO5 | E67: 43271 | F67: 43634 | G67: 43999 | H67: 44363 | I67: 44725 | J67: 45091 | K67: 45462 | L67: 45825
A68: 6 | B68: JUNIO | C68: 5 | D68: =CONCATENATE(B68,C68) -> JUNIO5 | E68: 43298 | F68: 43662 | G68: 44026 | H68: 44391 | I68: 44756 | J68: 45120 | K68: 45489 | L68: 45853
A69: 7 | B69: JULIO | C69: 5 | D69: =CONCATENATE(B69,C69) -> JULIO5 | E69: 43328 | F69: 43693 | G69: 44062 | H69: 44425 | I69: 44789 | J69: 45153 | K69: 45520 | L69: 45888
A70: 8 | B70: AGOSTO | C70: 5 | D70: =CONCATENATE(B70,C70) -> AGOSTO5 | E70: 43361 | F70: 43725 | G70: 44089 | H70: 44453 | I70: 44817 | J70: 45182 | K70: 45551 | L70: 45915
A71: 9 | B71: SEPTIEMBRE | C71: 5 | D71: =CONCATENATE(B71,C71) -> SEPTIEMBRE5 | E71: 43390 | F71: 43754 | G71: 44118 | H71: 44482 | I71: 44847 | J71: 45216 | K71: 45581 | L71: 45946
A72: 10 | B72: OCTUBRE | C72: 5 | D72: =CONCATENATE(B72,C72) -> OCTUBRE5 | E72: 43423 | F72: 43788 | G72: 44153 | H72: 44516 | I72: 44881 | J72: 45245 | K72: 45615 | L72: 45980
A73: 11 | B73: NOVIEMBRE | C73: 5 | D73: =CONCATENATE(B73,C73) -> NOVIEMBRE5 | E73: 43451 | F73: 43816 | G73: 44182 | H73: 44546 | I73: 44911 | J73: 45275 | K73: 45642 | L73: 46007
A74: 12 | B74: DICIEMBRE | C74: 5 | D74: =CONCATENATE(B74,C74) -> DICIEMBRE5 | E74: 43483 | F74: 43847 | G74: 44216 | H74: 44579 | I74: 44943 | J74: 45307 | K74: 45674 | L74: 46041
... A122: 12 | B122: DICIEMBRE | C122: 9 | D122: =CONCATENATE(B122,C122) -> DICIEMBRE9 | E122: 43479 | F122: 43843 | G122: 44210 | H122: 44585 | I122: 44949 | J122: 45313 | K122: 45680 | L122: 46045

Sheet Resoluciones de Tarifas
A1: Resolución 01299 de 2020
A2: Recaudo | E2: Aporte
B3: Cuantía | C3: Ajustado a la Centena | E3: Número de escrituras autorizadas | F3: Aporte por escritura | G3: Ajustado a la Centena | K3: 2020 | L3: 2021 | M3: 2022 | N3: 2023 | O3: 2024 | P3: 2025
A4: 1 | B4: Acto sin cuantía y escritura Excenta | C4: 13200 | E4: 1 | F4: =E5-1 -> 500 | G4: 3200 | J4: Acto sin cuantía y escritura Excenta | K4: 13200 | L4: 13600 | M4: 14300 | N4: 15900 | O4: 17400 | P4: 18400
A5: 2 | B5: De 0.00 a 100.000.000,00 | C5: 19800 | E5: 501 | F5: =E6-1 -> 1000 | G5: 4100 | J5: De 0.00 a 100.000.000,00 | K5: 19800 | L5: 20400 | M5: 21400 | N5: 23900 | O5: 26200 | P5: 27600
A6: 3 | B6: De 100.000.001,00 a 300.000.000.00 | C6: 29800 | E6: 1001 | F6: =E7-1 -> 2000 | G6: 4900 | J6: De 100.000.001,00 a 300.000.000.00 | K6: 29800 | L6: 30900 | M6: 32300 | N6: 36100 | O6: 39500 | P6: 41700
A7: 4 | B7: De 300.000.001,00 a 500.000.000,00 | C7: 36000 | E7: 2001 | F7: =E8-1 -> 3000 | G7: 5700 | J7: De 300.000.001,00 a 500.000.000,00 | K7: 36000 | L7: 37200 | M7: 39000 | N7: 43500 | O7: 47600 | P7: 50300
A8: 5 | B8: De 500.000.001,00 a 1.000.000.000,00 | C8: 49200 | E8: 3001 | F8: =E9-1 -> 4000 | G8: 6600 | J8: De 500.000.001,00 a 1.000.000.000,00 | K8: 49200 | L8: 50900 | M8: 53300 | N8: 59400 | O8: 65000 | P8: 68600
A9: 6 | B9: De 1.000.000.001,00 a 1.500.000.000,00 | C9: 57900 | E9: 4001 | F9: =E10-1 -> 5000 | G9: 8800 | J9: De 1.000.000.001,00 a 1.500.000.000,00 | K9: 57900 | L9: 60000 | M9: 62800 | N9: 70000 | O9: 76700 | P9: 80900
A10: 7 | B10: De 1.500.000.001,00 en adelante | C10: 65800 | E10: 5001 | F10: =E11-1 -> 6000 | G10: 10500 | J10: De 1.500.000.001,00 en adelante | K10: 65800 | L10: 68100 | M10: 71300 | N10: 79600 | O10: 87200 | P10: 92000
E11: 6001 | F11: =E12-1 -> 7000 | G11: 12300
E12: 7001 | F12: =E13-1 -> 8000 | G12: 14000
E13: 8001 | F13: =E14-1 -> 9000 | G13: 19300
E14: 9001 | F14: =E15-1 -> 10000 | G14: 21100
E15: 10001 | F15: =E16-1 -> 11000 | G15: 24600
E16: 11001 | F16: =E17-1 -> 12000 | G16: 28500
E17: 12001 | F17: =E18-1 -> 13000 | G17: 37300
E18: 13001 | F18: =E19-1 -> 14000 | G18: 46100
E19: 14001 | F19: =E20-1 -> 15000 | G19: 57100
E20: 15001 | F20: =E21-1 -> 16000 | G20: 74600
E21: 16001 | F21: + | G21: 92200
A22: Resolución 00536 de 2021
A23: Recaudo | E23: Aporte
B24: Cuantía | C24: Ajustado a la Centena | E24: Número de escrituras autorizadas | F24: Aporte por escritura | G24: Ajustado a la Centena
A25: 1 | B25: Acto sin cuantía y escritura Excenta | C25: 13600 | E25: 1 | F25: =E26-1 -> 500 | G25: 3400
A26: 2 | B26: De 0.00 a 100.000.000,00 | C26: 20400 | E26: 501 | F26: =E27-1 -> 1000 | G26: 4300
A27: 3 | B27: De 100.000.001,00 a 300.000.000.00 | C27: 30900 | E27: 1001 | F27: =E28-1 -> 2000 | G27: 5100
A28: 4 | B28: De 300.000.001,00 a 500.000.000,00 | C28: 37200 | E28: 2001 | F28: =E29-1 -> 3000 | G28: 5900
A29: 5 | B29: De 500.000.001,00 a 1.000.000.000,00 | C29: 50900 | E29: 3001 | F29: =E30-1 -> 4000 | G29: 6800
A30: 6 | B30: De 1.000.000.001,00 a 1.500.000.000,00 | C30: 60000 | E30: 4001 | F30: =E31-1 -> 5000 | G30: 9100
A31: 7 | B31: De 1.500.000.001,00 en adelante | C31: 68100 | E31: 5001 | F31: =E32-1 -> 6000 | G31: 10900
E32: 6001 | F32: =E33-1 -> 7000 | G32: 12700
E33: 7001 | F33: =E34-1 -> 8000 | G33: 14500
E34: 8001 | F34: =E35-1 -> 9000 | G34: 20000
E35: 9001 | F35: =E36-1 -> 10000 | G35: 21800
E36: 10001 | F36: =E37-1 -> 11000 | G36: 25400
E37: 11001 | F37: =E38-1 -> 12000 | G37: 29500
E38: 12001 | F38: =E39-1 -> 13000 | G38: 38600
E39: 13001 | F39: =E40-1 -> 14000 | G39: 47700
E40: 14001 | F40: =E41-1 -> 15000 | G40: 59100
E41: 15001 | F41: =E42-1 -> 16000 | G41: 77200
E42: 16001 | F42: + | G42: 95400
A43: Resolución 00755 de 2022
A44: Recaudo | E44: Aporte
B45: Cuantía | C45: Ajustado a la Centena | E45: Número de escrituras autorizadas | F45: Aporte por escritura | G45: Ajustado a la Centena
A46: 1 | B46: Acto sin cuantía y escritura Excenta | C46: 14300 | E46: 1 | F46: =E47-1 -> 500 | G46: 3600
A47: 2 | B47: De 0.00 a 100.000.000,00 | C47: 21400 | E47: 501 | F47: =E48-1 -> 1000 | G47: 4500
A48: 3 | B48: De 100.000.001,00 a 300.000.000.00 | C48: 32300 | E48: 1001 | F48: =E49-1 -> 2000 | G48: 5300
A49: 4 | B49: De 300.000.001,00 a 500.000.000,00 | C49: 39000 | E49: 2001 | F49: =E50-1 -> 3000 | G49: 6200
A50: 5 | B50: De 500.000.001,00 a 1.000.000.000,00 | C50: 53300 | E50: 3001 | F50: =E51-1 -> 4000 | G50: 7100
A51: 6 | B51: De 1.000.000.001,00 a 1.500.000.000,00 | C51: 62800 | E51: 4001 | F51: =E52-1 -> 5000 | G51: 9500
A52: 7 | B52: De 1.500.000.001,00 en adelante | C52: 71300 | E52: 5001 | F52: =E53-1 -> 6000 | G52: 11400
E53: 6001 | F53: =E54-1 -> 7000 | G53: 13300
E54: 7001 | F54: =E55-1 -> 8000 | G54: 15200
E55: 8001 | F55: =E56-1 -> 9000 | G55: 20900
E56: 9001 | F56: =E57-1 -> 10000 | G56: 22800
E57: 10001 | F57: =E58-1 -> 11000 | G57: 26600
E58: 11001 | F58: =E59-1 -> 12000 | G58: 30900
E59: 12001 | F59: =E60-1 -> 13000 | G59: 40400
E60: 13001 | F60: =E61-1 -> 14000 | G60: 49900
E61: 14001 | F61: =E62-1 -> 15000 | G61: 61800
E62: 15001 | F62: =E63-1 -> 16000 | G62: 80800
E63: 16001 | F63: + | G63: 99900
A64: Resolución 00387 de 2023
A65: Recaudo | E65: Aporte
B66: Cuantía | C66: Ajustado a la Centena | E66: Número de escrituras autorizadas | F66: Aporte por escritura | G66: Ajustado a la Centena
A67: 1 | B67: Acto sin cuantía y escritura Excenta | C67: 15900 | E67: 1 | F67: =E68-1 -> 500 | G67: 4000
A68: 2 | B68: De 0.00 a 100.000.000,00 | C68: 23900 | E68: 501 | F68: =E69-1 -> 1000 | G68: 5000
A69: 3 | B69: De 100.000.001,00 a 300.000.000.00 | C69: 36100 | E69: 1001 | F69: =E70-1 -> 2000 | G69: 6000
A70: 4 | B70: De 300.000.001,00 a 500.000.000,00 | C70: 43500 | E70: 2001 | F70: =E71-1 -> 3000 | G70: 6900
A71: 5 | B71: De 500.000.001,00 a 1.000.000.000,00 | C71: 59400 | E71: 3001 | F71: =E72-1 -> 4000 | G71: 7900
A72: 6 | B72: De 1.000.000.001,00 a 1.500.000.000,00 | C72: 70000 | E72: 4001 | F72: =E73-1 -> 5000 | G72: 10600
A73: 7 | B73: De 1.500.000.001,00 en adelante | C73: 79600 | E73: 5001 | F73: =E74-1 -> 6000 | G73: 12700
E74: 6001 | F74: =E75-1 -> 7000 | G74: 14800
E75: 7001 | F75: =E76-1 -> 8000 | G75: 16900
E76: 8001 | F76: =E77-1 -> 9000 | G76: 23400
E77: 9001 | F77: =E78-1 -> 10000 | G77: 25500
E78: 10001 | F78: =E79-1 -> 11000 | G78: 29700
E79: 11001 | F79: =E80-1 -> 12000 | G79: 34500
E80: 12001 | F80: =E81-1 -> 13000 | G80: 45100
E81: 13001 | F81: =E82-1 -> 14000 | G81: 55700
E82: 14001 | F82: =E83-1 -> 15000 | G82: 68900
E83: 15001 | F83: =E84-1 -> 16000 | G83: 90200
E84: 16001 | F84: + | G84: 111400
A85: Resolución 00773 de 2024
A86: Recaudo | E86: Aporte
B87: Cuantía | C87: Ajustado a la Centena | E87: Número de escrituras autorizadas | F87: Aporte por escritura | G87: Ajustado a la Centena
A88: 1 | B88: Acto sin cuantía y escritura Excenta | C88: 17400 | D88: 1 | E88: 1 | F88: =E89-1 -> 500 | G88: 4300
A89: 2 | B89: De 0.00 a 100.000.000,00 | C89: 26200 | D89: 2 | E89: 501 | F89: =E90-1 -> 1000 | G89: 5500
A90: 3 | B90: De 100.000.001,00 a 300.000.000.00 | C90: 39500 | D90: 3 | E90: 1001 | F90: =E91-1 -> 2000 | G90: 6500
A91: 4 | B91: De 300.000.001,00 a 500.000.000,00 | C91: 47600 | D91: 4 | E91: 2001 | F91: =E92-1 -> 3000 | G91: 7500
A92: 5 | B92: De 500.000.001,00 a 1.000.000.000,00 | C92: 65000 | D92: 5 | E92: 3001 | F92: =E93-1 -> 4000 | G92: 8700
A93: 6 | B93: De 1.000.000.001,00 a 1.500.000.000,00 | C93: 76700 | D93: 6 | E93: 4001 | F93: =E94-1 -> 5000 | G93: 11600
A94: 7 | B94: De 1.500.000.001,00 en adelante | C94: 87200 | D94: 7 | E94: 5001 | F94: =E95-1 -> 6000 | G94: 13900
D95: 8 | E95: 6001 | F95: =E96-1 -> 7000 | G95: 16200
D96: 9 | E96: 7001 | F96: =E97-1 -> 8000 | G96: 18500
D97: 10 | E97: 8001 | F97: =E98-1 -> 9000 | G97: 25600
D98: 11 | E98: 9001 | F98: =E99-1 -> 10000 | G98: 27900
D99: 12 | E99: 10001 | F99: =E100-1 -> 11000 | G99: 32500
D100: 13 | E100: 11001 | F100: =E101-1 -> 12000 | G100: 37800
...

Sheet Recaudo
A1: MES | C1: VALOR | D1: FECHA CONSIGNACION | F1: Tarifa Plena | G1: Tarifa Especial | I1: Escritura Inicial | J1: Escritura Final | K1: Total | M1: Valor según rango | N1: Número de escrituras | O1: Recaudado | P1: Aporte a recaudos
A2: 2019 | F2: Tarifa Plena | G2: Tarifa Especial | I2: Rango de Escrituras | N2: Número de escrituras | O2: Recaudado | P2: Aporte a recaudos
A3: MES | C3: VALOR | D3: FECHA CONSIGNACION | F3: 4600 | G3: =F3/2 -> 2300 | I3: Escritura Inicial | J3: Escritura Final | K3: Total | M3: 12400 | O3: =M3*N3 -> 0 | P3: =O3/2 -> 0
A4: Julio | E4: =IF(AND(EOMONTH(DATE($A$2,MONTH("1-"&A4&"-"&$A$2),1),0)>=Generales!$B$4,DATE($A$2,MONTH("1-"&A4&"-"&$A$2),1)<=Generales!$C$4),"","FUERA DE RANGO") -> FUERA DE RANGO | K4: =(J4-I4)+1 -> 1 | M4: 18600 | O4: =N4*M4 -> 0 | P4: =O4/2 -> 0
A5: Agosto | E5: =IF(AND(EOMONTH(DATE($A$2,MONTH("1-"&A5&"-"&$A$2),1),0)>=Generales!$B$4,DATE($A$2,MONTH("1-"&A5&"-"&$A$2),1)<=Generales!$C$4),"","FUERA DE RANGO") -> FUERA DE RANGO | I5: =J4+1 -> 1 | K5: =(J5-I5)+1 -> 0 | M5: 28200 | O5: =M5*N5 -> 0 | P5: =O5/2 -> 0
A6: Septiembre | E6: =IF(AND(EOMONTH(DATE($A$2,MONTH("1-"&A6&"-"&$A$2),1),0)>=Generales!$B$4,DATE($A$2,MONTH("1-"&A6&"-"&$A$2),1)<=Generales!$C$4),"","FUERA DE RANGO") -> FUERA DE RANGO | I6: =J5+1 -> 1 | K6: =(J6-I6)+1 -> 0 | M6: 34000 | O6: =M6*N6 -> 0 | P6: =O6/2 -> 0
A7: Octubre | E7: =IF(AND(EOMONTH(DATE($A$2,MONTH("1-"&A7&"-"&$A$2),1),0)>=Generales!$B$4,DATE($A$2,MONTH("1-"&A7&"-"&$A$2),1)<=Generales!$C$4),"","FUERA DE RANGO") -> FUERA DE RANGO | I7: =J6+1 -> 1 | K7: =(J7-I7)+1 -> 0 | M7: 46400 | O7: =M7*N7 -> 0 | P7: =O7/2 -> 0
A8: Noviembre | E8: =IF(AND(EOMONTH(DATE($A$2,MONTH("1-"&A8&"-"&$A$2),1),0)>=Generales!$B$4,DATE($A$2,MONTH("1-"&A8&"-"&$A$2),1)<=Generales!$C$4),"","FUERA DE RANGO") -> FUERA DE RANGO | I8: 1717 | K8: =(J8-I8)+1 -> -1716 | M8: 54700 | O8: =M8*N8 -> 0 | P8: =O8/2 -> 0
A9: Diciembre | E9: =IF(AND(EOMONTH(DATE($A$2,MONTH("1-"&A9&"-"&$A$2),1),0)>=Generales!$B$4,DATE($A$2,MONTH("1-"&A9&"-"&$A$2),1)<=Generales!$C$4),"","FUERA DE RANGO") -> FUERA DE RANGO | I9: =J8+1 -> 1 | K9: =(J9-I9)+1 -> 0 | M9: 62100 | O9: =M9*N9 -> 0 | P9: =O9/2 -> 0
K10: =(J10-I10)+1 -> 1 | N10: =SUM(N3:N9) -> 0 | O10: =SUM(O3:O9) -> 0 | P10: =SUM(P3:P9) -> 0
K11: =(J11-I11)+1 -> 1
A12: 2020 | K12: =(J12-I12)+1 -> 1
A13: MES | B13: BANCO | C13: VALOR | D13: FECHA CONSIGNACION | F13: =VLOOKUP(G14,'Resoluciones de Tarifas'!E4:G21,3,TRUE) -> 3200 | G13: =F13/2 -> 1600 | K13: =(J13-I13)+1 -> 1 | M13: Formato de liquidación de recaudos
A14: Enero | B14: PSE | D14: 43866 | E14: =IF(AND(EOMONTH(DATE($A$12,MONTH("1-"&A14&"-"&$A$12),1),0)>=Generales!$B$4,DATE($A$12,MONTH("1-"&A14&"-"&$A$12),1)<=Generales!$C$4),"","FUERA DE RANGO") -> FUERA DE RANGO | F14: #EP Generan Aportes Año anterior | G14: =G15-G16-G17 -> 1 | I14: 1 | K14: =(J14-I14)+1 -> 0 | M14: Año | N14: 2020
A15: Febrero | B15: PSE | D15: 43896 | E15: =IF(AND(EOMONTH(DATE($A$12,MONTH("1-"&A15&"-"&$A$12),1),0)>=Generales!$B$4,DATE($A$12,MONTH("1-"&A15&"-"&$A$12),1)<=Generales!$C$4),"","FUERA DE RANGO") -> FUERA DE RANGO | F15: Total Escrituras Autorizadas | G15: =K10 -> 1 | M15: =HLOOKUP($N$14,'Resoluciones de Tarifas'!$K$3:$P$10,2,FALSE) -> 13200 | O15: =M15*N15 -> 0 | P15: =O15/2 -> 0
A16: Febrero | B16: PSE | D16: 43896 | E16: =IF(AND(EOMONTH(DATE($A$12,MONTH("1-"&A16&"-"&$A$12),1),0)>=Generales!$B$4,DATE($A$12,MONTH("1-"&A16&"-"&$A$12),1)<=Generales!$C$4),"","FUERA DE RANGO") -> FUERA DE RANGO | F16: No computadas (parr 1. art. 48) | G16: 0 | I16: =J14+1 -> 1 | K16: =(J16-I16)+1 -> 0 | M16: =HLOOKUP($N$14,'Resoluciones de Tarifas'!$K$3:$P$10,3,FALSE) -> 19800 | O16: =M16*N16 -> 0 | P16: =O16/2 -> 0
A17: Marzo | B17: PSE | D17: 43935 | E17: =IF(AND(EOMONTH(DATE($A$12,MONTH("1-"&A17&"-"&$A$12),1),0)>=Generales!$B$4,DATE($A$12,MONTH("1-"&A17&"-"&$A$12),1)<=Generales!$C$4),"","FUERA DE RANGO") -> FUERA DE RANGO | F17: No autorizadas (otras) | G17: 0 | I17: =J16+1 -> 1 | K17: =(J17-I17)+1 -> 0 | M17: =HLOOKUP($N$14,'Resoluciones de Tarifas'!$K$3:$P$10,4,FALSE) -> 29800 | O17: =M17*N17 -> 0 | P17: =O17/2 -> 0
A18: Abril | B18: PSE | D18: 43963 | E18: =IF(AND(EOMONTH(DATE($A$12,MONTH("1-"&A18&"-"&$A$12),1),0)>=Generales!$B$4,DATE($A$12,MONTH("1-"&A18&"-"&$A$12),1)<=Generales!$C$4),"","FUERA DE RANGO") -> FUERA DE RANGO | I18: =J17+1 -> 1 | K18: =(J18-I18)+1 -> 0 | M18: =HLOOKUP($N$14,'Resoluciones de Tarifas'!$K$3:$P$10,5,FALSE) -> 36000 | O18: =M18*N18 -> 0 | P18: =O18/2 -> 0
A19: Mayo | B19: PSE | D19: 43985 | E19: =IF(AND(EOMONTH(DATE($A$12,MONTH("1-"&A19&"-"&$A$12),1),0)>=Generales!$B$4,DATE($A$12,MONTH("1-"&A19&"-"&$A$12),1)<=Generales!$C$4),"","FUERA DE RANGO") -> FUERA DE RANGO | I19: =J18+1 -> 1 | K19: =(J19-I19)+1 -> 0 | M19: =HLOOKUP($N$14,'Resoluciones de Tarifas'!$K$3:$P$10,6,FALSE) -> 49200 | O19: =M19*N19 -> 0 | P19: =O19/2 -> 0
A20: Junio | B20: PSE | D20: 44021 | E20: =IF(AND(EOMONTH(DATE($A$12,MONTH("1-"&A20&"-"&$A$12),1),0)>=Generales!$B$4,DATE($A$12,MONTH("1-"&A20&"-"&$A$12),1)<=Generales!$C$4),"","FUERA DE RANGO") -> FUERA DE RANGO | I20: =J19+1 -> 1 | K20: =(J20-I20)+1 -> 0 | M20: =HLOOKUP($N$14,'Resoluciones de Tarifas'!$K$3:$P$10,7,FALSE) -> 57900 | O20: =M20*N20 -> 0 | P20: =O20/2 -> 0
A21: Julio | B21: PSE | D21: 44054 | E21: =IF(AND(EOMONTH(DATE($A$12,MONTH("1-"&A21&"-"&$A$12),1),0)>=Generales!$B$4,DATE($A$12,MONTH("1-"&A21&"-"&$A$12),1)<=Generales!$C$4),"","FUERA DE RANGO") -> FUERA DE RANGO | I21: =J20+1 -> 1 | K21: =(J21-I21)+1 -> 0 | M21: =HLOOKUP($N$14,'Resoluciones de Tarifas'!$K$3:$P$10,8,FALSE) -> 65800 | O21: =M21*N21 -> 0 | P21: =O21/2 -> 0
A22: Agosto | B22: PSE | D22: 44084 | E22: =IF(AND(EOMONTH(DATE($A$12,MONTH("1-"&A22&"-"&$A$12),1),0)>=Generales!$B$4,DATE($A$12,MONTH("1-"&A22&"-"&$A$12),1)<=Generales!$C$4),"","FUERA DE RANGO") -> FUERA DE RANGO | I22: =J21+1 -> 1 | K22: =(J22-I22)+1 -> 0 | N22: =SUM(N15:N21) -> 0 | O22: =SUM(O15:O21) -> 0 | P22: =SUM(P15:P21) -> 0
A23: Septiembre | B23: PSE | D23: 44117 | E23: =IF(AND(EOMONTH(DATE($A$12,MONTH("1-"&A23&"-"&$A$12),1),0)>=Generales!$B$4,DATE($A$12,MONTH("1-"&A23&"-"&$A$12),1)<=Generales!$C$4),"","FUERA DE RANGO") -> FUERA DE RANGO | I23: =J22+1 -> 1 | K23: =(J23-I23)+1 -> 0
A24: Octubre | B24: PSE | D24: 44145 | E24: =IF(AND(EOMONTH(DATE($A$12,MONTH("1-"&A24&"-"&$A$12),1),0)>=Generales!$B$4,DATE($A$12,MONTH("1-"&A24&"-"&$A$12),1)<=Generales!$C$4),"","FUERA DE RANGO") -> FUERA DE RANGO | I24: =J23+1 -> 1 | K24: =(J24-I24)+1 -> 0
A25: Noviembre | B25: PSE | D25: 44175 | E25: =IF(AND(EOMONTH(DATE($A$12,MONTH("1-"&A25&"-"&$A$12),1),0)>=Generales!$B$4,DATE($A$12,MONTH("1-"&A25&"-"&$A$12),1)<=Generales!$C$4),"","FUERA DE RANGO") -> FUERA DE RANGO | I25: =J24+1 -> 1 | K25: =(J25-I25)+1 -> 0
A26: Diciembre | B26: PSE | D26: 44531 | E26: =IF(AND(EOMONTH(DATE($A$12,MONTH("1-"&A26&"-"&$A$12),1),0)>=Generales!$B$4,DATE($A$12,MONTH("1-"&A26&"-"&$A$12),1)<=Generales!$C$4),"","FUERA DE RANGO") -> FUERA DE RANGO | I26: =J25+1 -> 1 | K26: =(J26-I26)+1 -> 0
A28: 2021 | M28: Formato de liquidación de recaudos
A29: MES | B29: BANCO | C29: VALOR | D29: FECHA CONSIGNACION | F29: =VLOOKUP(G30,'Resoluciones de Tarifas'!E25:G42,3,TRUE) -> 5900 | G29: =F29/2 -> 2950 | K29: =(J29-I29)+1 -> 1 | M29: Año | N29: 2021
A30: Enero | E30: =IF(AND(EOMONTH(DATE($A$28,MONTH("1-"&A30&"-"&$A$28),1),0)>=Generales!$B$4,DATE($A$28,MONTH("1-"&A30&"-"&$A$28),1)<=Generales!$C$4),"","FUERA DE RANGO") -> FUERA DE RANGO | F30: #EP Generan Aportes Año anterior | G30: 3000 | I30: 1 | K30: =(J30-I30)+1 -> 0 | M30: =HLOOKUP($N$29,'Resoluciones de Tarifas'!$K$3:$P$10,2,FALSE) -> 13600 | O30: =M30*N30 -> 0 | P30: =O30/2 -> 0
A31: Febrero | E31: =IF(AND(EOMONTH(DATE($A$28,MONTH("1-"&A31&"-"&$A$28),1),0)>=Generales!$B$4,DATE($A$28,MONTH("1-"&A31&"-"&$A$28),1)<=Generales!$C$4),"","FUERA DE RANGO") -> FUERA DE RANGO | F31: Total Escrituras Autorizadas | G31: =K26 -> 0 | I31: =J30+1 -> 1 | K31: =(J31-I31)+1 -> 0 | M31: =HLOOKUP($N$29,'Resoluciones de Tarifas'!$K$3:$P$10,3,FALSE) -> 20400 | O31: =M31*N31 -> 0 | P31: =O31/2 -> 0
A32: Marzo | E32: =IF(AND(EOMONTH(DATE($A$28,MONTH("1-"&A32&"-"&$A$28),1),0)>=Generales!$B$4,DATE($A$28,MONTH("1-"&A32&"-"&$A$28),1)<=Generales!$C$4),"","FUERA DE RANGO") -> FUERA DE RANGO | F32: No computadas (parr 1. art. 48) | G32: 0 | I32: =J31+1 -> 1 | J32: 984 | K32: =(J32-I32)+1 -> 984 | M32: =HLOOKUP($N$29,'Resoluciones de Tarifas'!$K$3:$P$10,4,FALSE) -> 30900 | O32: =M32*N32 -> 0 | P32: =O32/2 -> 0
A33: Abril | E33: =IF(AND(EOMONTH(DATE($A$28,MONTH("1-"&A33&"-"&$A$28),1),0)>=Generales!$B$4,DATE($A$28,MONTH("1-"&A33&"-"&$A$28),1)<=Generales!$C$4),"","FUERA DE RANGO") -> FUERA DE RANGO | F33: No autorizadas (otras) | G33: 0 | I33: =J32+1 -> 985 | J33: 1336 | K33: =(J33-I33)+1 -> 352 | L33: 48 | M33: =HLOOKUP($N$29,'Resoluciones de Tarifas'!$K$3:$P$10,5,FALSE) -> 37200 | O33: =M33*N33 -> 0 | P33: =O33/2 -> 0
A34: Mayo | E34: =IF(AND(EOMONTH(DATE($A$28,MONTH("1-"&A34&"-"&$A$28),1),0)>=Generales!$B$4,DATE($A$28,MONTH("1-"&A34&"-"&$A$28),1)<=Generales!$C$4),"","FUERA DE RANGO") -> FUERA DE RANGO | I34: =J33+1 -> 1337 | J34: 1679 | K34: =(J34-I34)+1 -> 343 | L34: 40 | M34: =HLOOKUP($N$29,'Resoluciones de Tarifas'!$K$3:$P$10,6,FALSE) -> 50900 | O34: =M34*N34 -> 0 | P34: =O34/2 -> 0
A35: Junio | E35: =IF(AND(EOMONTH(DATE($A$28,MONTH("1-"&A35&"-"&$A$28),1),0)>=Generales!$B$4,DATE($A$28,MONTH("1-"&A35&"-"&$A$28),1)<=Generales!$C$4),"","FUERA DE RANGO") -> FUERA DE RANGO | I35: =J34+1 -> 1680 | J35: 2041 | K35: =(J35-I35)+1 -> 362 | L35: 23 | M35: =HLOOKUP($N$29,'Resoluciones de Tarifas'!$K$3:$P$10,7,FALSE) -> 60000 | O35: =M35*N35 -> 0 | P35: =O35/2 -> 0
A36: Julio | E36: =IF(AND(EOMONTH(DATE($A$28,MONTH("1-"&A36&"-"&$A$28),1),0)>=Generales!$B$4,DATE($A$28,MONTH("1-"&A36&"-"&$A$28),1)<=Generales!$C$4),"","FUERA DE RANGO") -> FUERA DE RANGO | I36: =J35+1 -> 2042 | J36: 2391 | K36: =(J36-I36)+1 -> 350 | L36: 27 | M36: =HLOOKUP($N$29,'Resoluciones de Tarifas'!$K$3:$P$10,8,FALSE) -> 68100 | O36: =M36*N36 -> 0 | P36: =O36/2 -> 0
A37: Agosto | E37: =IF(AND(EOMONTH(DATE($A$28,MONTH("1-"&A37&"-"&$A$28),1),0)>=Generales!$B$4,DATE($A$28,MONTH("1-"&A37&"-"&$A$28),1)<=Generales!$C$4),"","FUERA DE RANGO") -> FUERA DE RANGO | I37: =J36+1 -> 2392 | J37: 2766 | K37: =(J37-I37)+1 -> 375 | L37: 18 | N37: =SUM(N30:N36) -> 0 | O37: =SUM(O30:O36) -> 0 | P37: =SUM(P30:P36) -> 0
A38: Septiembre | E38: =IF(AND(EOMONTH(DATE($A$28,MONTH("1-"&A38&"-"&$A$28),1),0)>=Generales!$B$4,DATE($A$28,MONTH("1-"&A38&"-"&$A$28),1)<=Generales!$C$4),"","FUERA DE RANGO") -> FUERA DE RANGO | I38: =J37+1 -> 2767 | J38: 3168 | K38: =(J38-I38)+1 -> 402 | L38: 5
A39: Octubre | E39: =IF(AND(EOMONTH(DATE($A$28,MONTH("1-"&A39&"-"&$A$28),1),0)>=Generales!$B$4,DATE($A$28,MONTH("1-"&A39&"-"&$A$28),1)<=Generales!$C$4),"","FUERA DE RANGO") -> FUERA DE RANGO | I39: =J38+1 -> 3169 | J39: 3557 | K39: =(J39-I39)+1 -> 389 | L39: 13
A40: Noviembre | E40: =IF(AND(EOMONTH(DATE($A$28,MONTH("1-"&A40&"-"&$A$28),1),0)>=Generales!$B$4,DATE($A$28,MONTH("1-"&A40&"-"&$A$28),1)<=Generales!$C$4),"","FUERA DE RANGO") -> FUERA DE RANGO | I40: =J39+1 -> 3558 | J40: 3987 | K40: =(J40-I40)+1 -> 430 | L40: 31
A41: Diciembre | E41: =IF(AND(EOMONTH(DATE($A$28,MONTH("1-"&A41&"-"&$A$28),1),0)>=Generales!$B$4,DATE($A$28,MONTH("1-"&A41&"-"&$A$28),1)<=Generales!$C$4),"","FUERA DE RANGO") -> FUERA DE RANGO | I41: =J40+1 -> 3988 | K41: =(J41-I41)+1 -> -3987 | L41: 19
K42: =(J42-I42)+1 -> 1 | L42: =SUM(L33:L41) -> 224 | M42: Formato de liquidación de recaudos
A43: 2022 | K43: =(J43-I43)+1 -> 1 | M43: Año | N43: 2022
A44: MES | B44: BANCO | C44: VALOR | D44: FECHA CONSIGNACION | F44: =VLOOKUP(G45,'Resoluciones de Tarifas'!E46:G63,3,TRUE) -> #N/A | G44: =F44/2 -> #N/A | K44: =(J44-I44)+1 -> 1 | M44: =HLOOKUP($N$43,'Resoluciones de Tarifas'!$K$3:$P$10,2,FALSE) -> 14300 | N44: 13 | O44: =M44*N44 -> 185900 | P44: =O44/2 -> 92950
A45: Enero | E45: =IF(AND(EOMONTH(DATE($A$43,MONTH("1-"&A45&"-"&$A$43),1),0)>=Generales!$B$4,DATE($A$43,MONTH("1-"&A45&"-"&$A$43),1)<=Generales!$C$4),"","FUERA DE RANGO") -> FUERA DE RANGO | F45: #EP Generan Aportes Año anterior | G45: =G46-G47-G48 -> -224 | I45: 1 | K45: =(J45-I45)+1 -> 0 | L45: 13 | M45: =HLOOKUP($N$43,'Resoluciones de Tarifas'!$K$3:$P$10,3,FALSE) -> 21400 | N45: 0 | O45: =M45*N45 -> 0 | P45: =O45/2 -> 0
A46: Febrero | E46: =IF(AND(EOMONTH(DATE($A$43,MONTH("1-"&A46&"-"&$A$43),1),0)>=Generales!$B$4,DATE($A$43,MONTH("1-"&A46&"-"&$A$43),1)<=Generales!$C$4),"","FUERA DE RANGO") -> FUERA DE RANGO | F46: Total Escrituras Autorizadas | G46: =J41 -> 0 | I46: =J45+1 -> 1 | K46: =(J46-I46)+1 -> 0 | L46: 51 | M46: =HLOOKUP($N$43,'Resoluciones de Tarifas'!$K$3:$P$10,4,FALSE) -> 32300 | N46: 0 | O46: =M46*N46 -> 0 | P46: =O46/2 -> 0
A47: Marzo | E47: =IF(AND(EOMONTH(DATE($A$43,MONTH("1-"&A47&"-"&$A$43),1),0)>=Generales!$B$4,DATE($A$43,MONTH("1-"&A47&"-"&$A$43),1)<=Generales!$C$4),"","FUERA DE RANGO") -> FUERA DE RANGO | F47: No computadas (parr 1. art. 48) | G47: 224 | I47: =J46+1 -> 1 | K47: =(J47-I47)+1 -> 0 | L47: 37 | M47: =HLOOKUP($N$43,'Resoluciones de Tarifas'!$K$3:$P$10,5,FALSE) -> 39000 | N47: 0 | O47: =M47*N47 -> 0 | P47: =O47/2 -> 0
A48: Abril | E48: =IF(AND(EOMONTH(DATE($A$43,MONTH("1-"&A48&"-"&$A$43),1),0)>=Generales!$B$4,DATE($A$43,MONTH("1-"&A48&"-"&$A$43),1)<=Generales!$C$4),"","FUERA DE RANGO") -> FUERA DE RANGO | F48: No autorizadas (otras) | G48: 0 | I48: =J47+1 -> 1 | K48: =(J48-I48)+1 -> 0 | L48: 32 | M48: =HLOOKUP($N$43,'Resoluciones de Tarifas'!$K$3:$P$10,6,FALSE) -> 53300 | N48: 0 | O48: =M48*N48 -> 0 | P48: =O48/2 -> 0
A49: Mayo | E49: =IF(AND(EOMONTH(DATE($A$43,MONTH("1-"&A49&"-"&$A$43),1),0)>=Generales!$B$4,DATE($A$43,MONTH("1-"&A49&"-"&$A$43),1)<=Generales!$C$4),"","FUERA DE RANGO") -> FUERA DE RANGO | I49: =J48+1 -> 1 | K49: =(J49-I49)+1 -> 0 | L49: 14 | M49: =HLOOKUP($N$43,'Resoluciones de Tarifas'!$K$3:$P$10,7,FALSE) -> 62800 | N49: 0 | O49: =M49*N49 -> 0 | P49: =O49/2 -> 0
A50: Junio | E50: =IF(AND(EOMONTH(DATE($A$43,MONTH("1-"&A50&"-"&$A$43),1),0)>=Generales!$B$4,DATE($A$43,MONTH("1-"&A50&"-"&$A$43),1)<=Generales!$C$4),"","FUERA DE RANGO") -> FUERA DE RANGO | I50: =J49+1 -> 1 | K50: =(J50-I50)+1 -> 0 | L50: 20 | M50: =HLOOKUP($N$43,'Resoluciones de Tarifas'!$K$3:$P$10,8,FALSE) -> 71300 | N50: 0 | O50: =M50*N50 -> 0 | P50: =O50/2 -> 0
A51: Julio | E51: =IF(AND(EOMONTH(DATE($A$43,MONTH("1-"&A51&"-"&$A$43),1),0)>=Generales!$B$4,DATE($A$43,MONTH("1-"&A51&"-"&$A$43),1)<=Generales!$C$4),"","FUERA DE RANGO") -> FUERA DE RANGO | I51: =J50+1 -> 1 | K51: =(J51-I51)+1 -> 0 | L51: 25 | N51: =SUM(N44:N50) -> 13 | O51: =SUM(O44:O50) -> 185900 | P51: =SUM(P44:P50) -> 92950
A52: Agosto | E52: =IF(AND(EOMONTH(DATE($A$43,MONTH("1-"&A52&"-"&$A$43),1),0)>=Generales!$B$4,DATE($A$43,MONTH("1-"&A52&"-"&$A$43),1)<=Generales!$C$4),"","FUERA DE RANGO") -> FUERA DE RANGO | I52: =J51+1 -> 1 | K52: =(J52-I52)+1 -> 0 | L52: 22
A53: Septiembre | E53: =IF(AND(EOMONTH(DATE($A$43,MONTH("1-"&A53&"-"&$A$43),1),0)>=Generales!$B$4,DATE($A$43,MONTH("1-"&A53&"-"&$A$43),1)<=Generales!$C$4),"","FUERA DE RANGO") -> FUERA DE RANGO | I53: =J52+1 -> 1 | K53: =(J53-I53)+1 -> 0 | L53: 15
A54: Octubre | E54: =IF(AND(EOMONTH(DATE($A$43,MONTH("1-"&A54&"-"&$A$43),1),0)>=Generales!$B$4,DATE($A$43,MONTH("1-"&A54&"-"&$A$43),1)<=Generales!$C$4),"","FUERA DE RANGO") -> FUERA DE RANGO | I54: =J53+1 -> 1 | K54: =(J54-I54)+1 -> 0 | L54: 10
A55: Noviembre | E55: =IF(AND(EOMONTH(DATE($A$43,MONTH("1-"&A55&"-"&$A$43),1),0)>=Generales!$B$4,DATE($A$43,MONTH("1-"&A55&"-"&$A$43),1)<=Generales!$C$4),"","FUERA DE RANGO") -> FUERA DE RANGO | I55: =J54+1 -> 1 | K55: =((J55-I55)+1) -> 0 | L55: 20
A56: Diciembre | E56: =IF(AND(EOMONTH(DATE($A$43,MONTH("1-"&A56&"-"&$A$43),1),0)>=Generales!$B$4,DATE($A$43,MONTH("1-"&A56&"-"&$A$43),1)<=Generales!$C$4),"","FUERA DE RANGO") -> FUERA DE RANGO | I56: =J55+1 -> 1 | K56: =(J56-I56)+1 -> 0 | L56: 13
L57: =SUM(L45:L56) -> 272
A58: 2023 | M58: Formato de liquidación de recaudos
A59: MES | B59: BANCO | C59: VALOR | D59: FECHA CONSIGNACION | F59: =VLOOKUP(G60,'Resoluciones de Tarifas'!E67:G84,3,TRUE) -> #N/A | G59: =F59/2 -> #N/A | M59: Año | N59: 2023
A60: Enero | F60: #EP Generan Aportes Año anterior | G60: =G61-G62-G63 -> -280 | I60: 1 | K60: =(J60-I60)+1 -> 0 | L60: 1 | M60: =HLOOKUP($N$59,'Resoluciones de Tarifas'!$K$3:$P$10,2,FALSE) -> 15900 | O60: =M60*N60 -> 0 | P60: =O60/2 -> 0
A61: Febrero | E61: =IF(AND(EOMONTH(DATE($A$58,MONTH("1-"&A61&"-"&$A$58),1),0)>=Generales!$B$4,DATE($A$58,MONTH("1-"&A61&"-"&$A$58),1)<=Generales!$C$4),"","FUERA DE RANGO") -> FUERA DE RANGO | F61: Total Escrituras Autorizadas | G61: =J56 -> 0 | I61: =J60+1 -> 1 | K61: =(J61-I61)+1 -> 0 | L61: 7 | M61: =HLOOKUP($N$59,'Resoluciones de Tarifas'!$K$3:$P$10,3,FALSE) -> 23900 | O61: =M61*N61 -> 0 | P61: =O61/2 -> 0
A62: Marzo | E62: =IF(AND(EOMONTH(DATE($A$58,MONTH("1-"&A62&"-"&$A$58),1),0)>=Generales!$B$4,DATE($A$58,MONTH("1-"&A62&"-"&$A$58),1)<=Generales!$C$4),"","FUERA DE RANGO") -> FUERA DE RANGO | F62: No computadas (parr 1. art. 48) | G62: 272 | I62: =J61+1 -> 1 | K62: =(J62-I62)+1 -> 0 | L62: 13 | M62: =HLOOKUP($N$59,'Resoluciones de Tarifas'!$K$3:$P$10,4,FALSE) -> 36100 | O62: =M62*N62 -> 0 | P62: =O62/2 -> 0
A63: Abril | E63: =IF(AND(EOMONTH(DATE($A$58,MONTH("1-"&A63&"-"&$A$58),1),0)>=Generales!$B$4,DATE($A$58,MONTH("1-"&A63&"-"&$A$58),1)<=Generales!$C$4),"","FUERA DE RANGO") -> FUERA DE RANGO | F63: No autorizadas (otras) | G63: 8 | I63: =J62+1 -> 1 | K63: =(J63-I63)+1 -> 0 | L63: 1 | M63: =HLOOKUP($N$59,'Resoluciones de Tarifas'!$K$3:$P$10,5,FALSE) -> 43500 | O63: =M63*N63 -> 0 | P63: =O63/2 -> 0
A64: Mayo | E64: =IF(AND(EOMONTH(DATE($A$58,MONTH("1-"&A64&"-"&$A$58),1),0)>=Generales!$B$4,DATE($A$58,MONTH("1-"&A64&"-"&$A$58),1)<=Generales!$C$4),"","FUERA DE RANGO") -> FUERA DE RANGO | I64: =J63+1 -> 1 | K64: =(J64-I64)+1 -> 0 | L64: 3 | M64: =HLOOKUP($N$59,'Resoluciones de Tarifas'!$K$3:$P$10,6,FALSE) -> 59400 | O64: =M64*N64 -> 0 | P64: =O64/2 -> 0
A65: Junio | E65: =IF(AND(EOMONTH(DATE($A$58,MONTH("1-"&A65&"-"&$A$58),1),0)>=Generales!$B$4,DATE($A$58,MONTH("1-"&A65&"-"&$A$58),1)<=Generales!$C$4),"","FUERA DE RANGO") -> FUERA DE RANGO | I65: =J64+1 -> 1 | K65: =(J65-I65)+1 -> 0 | L65: 12 | M65: =HLOOKUP($N$59,'Resoluciones de Tarifas'!$K$3:$P$10,7,FALSE) -> 70000 | O65: =M65*N65 -> 0 | P65: =O65/2 -> 0
A66: Julio | E66: =IF(AND(EOMONTH(DATE($A$58,MONTH("1-"&A66&"-"&$A$58),1),0)>=Generales!$B$4,DATE($A$58,MONTH("1-"&A66&"-"&$A$58),1)<=Generales!$C$4),"","FUERA DE RANGO") -> FUERA DE RANGO | I66: =J65+1 -> 1 | K66: =(J66-I66)+1 -> 0 | L66: 11 | M66: =HLOOKUP($N$59,'Resoluciones de Tarifas'!$K$3:$P$10,8,FALSE) -> 79600 | O66: =M66*N66 -> 0 | P66: =O66/2 -> 0
A67: Agosto | E67: =IF(AND(EOMONTH(DATE($A$58,MONTH("1-"&A67&"-"&$A$58),1),0)>=Generales!$B$4,DATE($A$58,MONTH("1-"&A67&"-"&$A$58),1)<=Generales!$C$4),"","FUERA DE RANGO") -> FUERA DE RANGO | I67: =J66+1 -> 1 | K67: =(J67-I67)+1 -> 0 | L67: 12 | N67: =SUM(N60:N66) -> 0 | O67: =SUM(O60:O66) -> 0 | P67: =SUM(P60:P66) -> 0
A68: Septiembre | E68: =IF(AND(EOMONTH(DATE($A$58,MONTH("1-"&A68&"-"&$A$58),1),0)>=Generales!$B$4,DATE($A$58,MONTH("1-"&A68&"-"&$A$58),1)<=Generales!$C$4),"","FUERA DE RANGO") -> FUERA DE RANGO | I68: =J67+1 -> 1 | K68: =(J68-I68)+1 -> 0 | L68: 7
A69: Octubre | E69: =IF(AND(EOMONTH(DATE($A$58,MONTH("1-"&A69&"-"&$A$58),1),0)>=Generales!$B$4,DATE($A$58,MONTH("1-"&A69&"-"&$A$58),1)<=Generales!$C$4),"","FUERA DE RANGO") -> FUERA DE RANGO | I69: =J68+1 -> 1 | K69: =(J69-I69)+1 -> 0 | L69: 15
A70: Noviembre | E70: =IF(AND(EOMONTH(DATE($A$58,MONTH("1-"&A70&"-"&$A$58),1),0)>=Generales!$B$4,DATE($A$58,MONTH("1-"&A70&"-"&$A$58),1)<=Generales!$C$4),"","FUERA DE RANGO") -> FUERA DE RANGO | I70: =J69+1 -> 1 | K70: =(J70-I70)+1 -> 0 | L70: 10
A71: Diciembre | E71: =IF(AND(EOMONTH(DATE($A$58,MONTH("1-"&A71&"-"&$A$58),1),0)>=Generales!$B$4,DATE($A$58,MONTH("1-"&A71&"-"&$A$58),1)<=Generales!$C$4),"","FUERA DE RANGO") -> FUERA DE RANGO | I71: =J70+1 -> 1 | K71: =(J71-I71)+1 -> 0 | L71: 14
L72: =SUM(L60:L71) -> 106
A73: 2024 | M73: Formato de liquidación de recaudos
A74: MES | B74: BANCO | C74: VALOR | D74: FECHA CONSIGNACION | F74: =VLOOKUP(G75,'Resoluciones de Tarifas'!E88:G105,3,TRUE) -> #N/A | G74: =F74/2 -> #N/A | M74: Año | N74: 2024
A75: Enero | F75: #EP Generan Aportes Año anterior | G75: =G76-G77-G78 -> -106 | I75: 1 | K75: =(J75-I75)+1 -> 0 | L75: 4 | M75: =HLOOKUP($N$74,'Resoluciones de Tarifas'!$K$3:$P$10,2,FALSE) -> 17400 | O75: =M75*N75 -> 0 | P75: =O75/2 -> 0
A76: Febrero | F76: Total Escrituras Autorizadas | G76: =J71 -> 0 | I76: =J75+1 -> 1 | K76: =(J76-I76)+1 -> 0 | L76: 1 | M76: =HLOOKUP($N$74,'Resoluciones de Tarifas'!$K$3:$P$10,3,FALSE) -> 26200 | O76: =M76*N76 -> 0 | P76: =O76/2 -> 0
A77: Marzo | E77: =IF(AND(EOMONTH(DATE($A$73,MONTH("1-"&A77&"-"&$A$73),1),0)>=Generales!$B$4,DATE($A$73,MONTH("1-"&A77&"-"&$A$73),1)<=Generales!$C$4),"","FUERA DE RANGO") -> FUERA DE RANGO | F77: No computadas (parr 1. art. 48) | G77: 106 | I77: =J76+1 -> 1 | K77: =(J77-I77)+1 -> 0 | M77: =HLOOKUP($N$74,'Resoluciones de Tarifas'!$K$3:$P$10,4,FALSE) -> 39500 | O77: =M77*N77 -> 0 | P77: =O77/2 -> 0
A78: Abril | E78: =IF(AND(EOMONTH(DATE($A$73,MONTH("1-"&A78&"-"&$A$73),1),0)>=Generales!$B$4,DATE($A$73,MONTH("1-"&A78&"-"&$A$73),1)<=Generales!$C$4),"","FUERA DE RANGO") -> FUERA DE RANGO | F78: No autorizadas (otras) | G78: 0 | I78: =J77+1 -> 1 | K78: =(J78-I78)+1 -> 0 | M78: =HLOOKUP($N$74,'Resoluciones de Tarifas'!$K$3:$P$10,5,FALSE) -> 47600 | O78: =M78*N78 -> 0 | P78: =O78/2 -> 0
A79: Mayo | E79: =IF(AND(EOMONTH(DATE($A$73,MONTH("1-"&A79&"-"&$A$73),1),0)>=Generales!$B$4,DATE($A$73,MONTH("1-"&A79&"-"&$A$73),1)<=Generales!$C$4),"","FUERA DE RANGO") -> FUERA DE RANGO | I79: =J78+1 -> 1 | K79: =(J79-I79)+1 -> 0 | M79: =HLOOKUP($N$74,'Resoluciones de Tarifas'!$K$3:$P$10,6,FALSE) -> 65000 | O79: =M79*N79 -> 0 | P79: =O79/2 -> 0
A80: Junio | E80: =IF(AND(EOMONTH(DATE($A$73,MONTH("1-"&A80&"-"&$A$73),1),0)>=Generales!$B$4,DATE($A$73,MONTH("1-"&A80&"-"&$A$73),1)<=Generales!$C$4),"","FUERA DE RANGO") -> FUERA DE RANGO | I80: =J79+1 -> 1 | K80: =(J80-I80)+1 -> 0 | M80: =HLOOKUP($N$74,'Resoluciones de Tarifas'!$K$3:$P$10,7,FALSE) -> 76700 | O80: =M80*N80 -> 0 | P80: =O80/2 -> 0
A81: Julio | E81: =IF(AND(EOMONTH(DATE($A$73,MONTH("1-"&A81&"-"&$A$73),1),0)>=Generales!$B$4,DATE($A$73,MONTH("1-"&A81&"-"&$A$73),1)<=Generales!$C$4),"","FUERA DE RANGO") -> FUERA DE RANGO | I81: =J80+1 -> 1 | K81: =(J81-I81)+1 -> 0 | M81: =HLOOKUP($N$74,'Resoluciones de Tarifas'!$K$3:$P$10,8,FALSE) -> 87200 | O81: =M81*N81 -> 0 | P81: =O81/2 -> 0
A82: Agosto | E82: =IF(AND(EOMONTH(DATE($A$73,MONTH("1-"&A82&"-"&$A$73),1),0)>=Generales!$B$4,DATE($A$73,MONTH("1-"&A82&"-"&$A$73),1)<=Generales!$C$4),"","FUERA DE RANGO") -> FUERA DE RANGO | I82: =J81+1 -> 1 | K82: =(J82-I82)+1 -> 0 | N82: =SUM(N75:N81) -> 0 | O82: =SUM(O75:O81) -> 0 | P82: =SUM(P75:P81) -> 0
A83: Septiembre | E83: =IF(AND(EOMONTH(DATE($A$73,MONTH("1-"&A83&"-"&$A$73),1),0)>=Generales!$B$4,DATE($A$73,MONTH("1-"&A83&"-"&$A$73),1)<=Generales!$C$4),"","FUERA DE RANGO") -> FUERA DE RANGO | I83: =J82+1 -> 1 | K83: =(J83-I83)+1 -> 0
A84: Octubre | E84: =IF(AND(EOMONTH(DATE($A$73,MONTH("1-"&A84&"-"&$A$73),1),0)>=Generales!$B$4,DATE($A$73,MONTH("1-"&A84&"-"&$A$73),1)<=Generales!$C$4),"","FUERA DE RANGO") -> FUERA DE RANGO | I84: =J83+1 -> 1 | K84: =(J84-I84)+1 -> 0
A85: Noviembre | E85: =IF(AND(EOMONTH(DATE($A$73,MONTH("1-"&A85&"-"&$A$73),1),0)>=Generales!$B$4,DATE($A$73,MONTH("1-"&A85&"-"&$A$73),1)<=Generales!$C$4),"","FUERA DE RANGO") -> FUERA DE RANGO | I85: =J84+1 -> 1 | K85: =(J85-I85)+1 -> 0
A86: Diciembre | E86: =IF(AND(EOMONTH(DATE($A$73,MONTH("1-"&A86&"-"&$A$73),1),0)>=Generales!$B$4,DATE($A$73,MONTH("1-"&A86&"-"&$A$73),1)<=Generales!$C$4),"","FUERA DE RANGO") -> FUERA DE RANGO | I86: =J85+1 -> 1 | K86: =(J86-I86)+1 -> 0
A88: 2025
A89: MES | B89: BANCO | C89: VALOR | D89: FECHA CONSIGNACION | F89: =VLOOKUP(G90,'Resoluciones de Tarifas'!E109:G126,3,TRUE) -> #N/A | G89: =F89/2 -> #N/A | M89: Formato de liquidación de recaudos
A90: Enero | F90: #EP Generan Aportes Año anterior | G90: =G91-G92-G93 -> 0 | I90: =J89+1 -> 1 | K90: =(J90-I90)+1 -> 0 | M90: Año | N90: 2025
A91: Febrero | E91: =IF(AND(EOMONTH(DATE($A$88,MONTH("1-"&A91&"-"&$A$88),1),0)>=Generales!$B$4,DATE($A$88,MONTH("1-"&A91&"-"&$A$88),1)<=Generales!$C$4),"","FUERA DE RANGO") -> FUERA DE RANGO | F91: Total Escrituras Autorizadas | G91: =J86 -> 0 | I91: =J90+1 -> 1 | K91: =(J91-I91)+1 -> 0 | L91: 2 | M91: =HLOOKUP($N$90,'Resoluciones de Tarifas'!$K$3:$P$10,2,FALSE) -> 18400 | N91: 5 | O91: =M91*N91 -> 92000 | P91: =O91/2 -> 46000
A92: Marzo | E92: =IF(AND(EOMONTH(DATE($A$88,MONTH("1-"&A92&"-"&$A$88),1),0)>=Generales!$B$4,DATE($A$88,MONTH("1-"&A92&"-"&$A$88),1)<=Generales!$C$4),"","FUERA DE RANGO") -> FUERA DE RANGO | F92: No computadas (parr 1. art. 48) | I92: =J91+1 -> 1 | K92: =(J92-I92)+1 -> 0 | L92: 5 | M92: =HLOOKUP($N$90,'Resoluciones de Tarifas'!$K$3:$P$10,3,FALSE) -> 27600 | N92: 7 | O92: =M92*N92 -> 193200 | P92: =O92/2 -> 96600
A93: Abril | E93: =IF(AND(EOMONTH(DATE($A$88,MONTH("1-"&A93&"-"&$A$88),1),0)>=Generales!$B$4,DATE($A$88,MONTH("1-"&A93&"-"&$A$88),1)<=Generales!$C$4),"","FUERA DE RANGO") -> FUERA DE RANGO | F93: No autorizadas (otras) | G93: 0 | I93: =J92+1 -> 1 | K93: =(J93-I93)+1 -> 0 | L93: 4 | M93: =HLOOKUP($N$90,'Resoluciones de Tarifas'!$K$3:$P$10,4,FALSE) -> 41700 | N93: 1 | O93: =M93*N93 -> 41700 | P93: =O93/2 -> 20850
A94: Mayo | E94: =IF(AND(EOMONTH(DATE($A$88,MONTH("1-"&A94&"-"&$A$88),1),0)>=Generales!$B$4,DATE($A$88,MONTH("1-"&A94&"-"&$A$88),1)<=Generales!$C$4),"","FUERA DE RANGO") -> FUERA DE RANGO | I94: =J93+1 -> 1 | K94: =(J94-I94)+1 -> 0 | L94: 3 | M94: =HLOOKUP($N$90,'Resoluciones de Tarifas'!$K$3:$P$10,5,FALSE) -> 50300 | N94: 0 | O94: =M94*N94 -> 0 | P94: =O94/2 -> 0
A95: Junio | E95: =IF(AND(EOMONTH(DATE($A$88,MONTH("1-"&A95&"-"&$A$88),1),0)>=Generales!$B$4,DATE($A$88,MONTH("1-"&A95&"-"&$A$88),1)<=Generales!$C$4),"","FUERA DE RANGO") -> FUERA DE RANGO | I95: =J94+1 -> 1 | K95: =(J95-I95)+1 -> 0 | M95: =HLOOKUP($N$90,'Resoluciones de Tarifas'!$K$3:$P$10,6,FALSE) -> 68600 | N95: 0 | O95: =M95*N95 -> 0 | P95: =O95/2 -> 0
A96: Julio | E96: =IF(AND(EOMONTH(DATE($A$88,MONTH("1-"&A96&"-"&$A$88),1),0)>=Generales!$B$4,DATE($A$88,MONTH("1-"&A96&"-"&$A$88),1)<=Generales!$C$4),"","FUERA DE RANGO") -> FUERA DE RANGO | I96: =J95+1 -> 1 | K96: =(J96-I96)+1 -> 0 | M96: =HLOOKUP($N$90,'Resoluciones de Tarifas'!$K$3:$P$10,7,FALSE) -> 80900 | N96: 0 | O96: =M96*N96 -> 0 | P96: =O96/2 -> 0
A97: Agosto | E97: =IF(AND(EOMONTH(DATE($A$88,MONTH("1-"&A97&"-"&$A$88),1),0)>=Generales!$B$4,DATE($A$88,MONTH("1-"&A97&"-"&$A$88),1)<=Generales!$C$4),"","FUERA DE RANGO") -> FUERA DE RANGO | I97: =J96+1 -> 1 | K97: =(J97-I97)+1 -> 0 | M97: =HLOOKUP($N$90,'Resoluciones de Tarifas'!$K$3:$P$10,8,FALSE) -> 92000 | N97: 0 | O97: =M97*N97 -> 0 | P97: =O97/2 -> 0
A98: Septiembre | E98: =IF(AND(EOMONTH(DATE($A$88,MONTH("1-"&A98&"-"&$A$88),1),0)>=Generales!$B$4,DATE($A$88,MONTH("1-"&A98&"-"&$A$88),1)<=Generales!$C$4),"","FUERA DE RANGO") | I98: =J97+1 -> 1 | J98: 659 | K98: =(J98-I98)+1 -> 659 | N98: =SUM(N91:N97) -> 13 | O98: =SUM(O91:O97) -> 326900 | P98: =SUM(P91:P97) -> 163450
A99: Octubre | E99: =IF(AND(EOMONTH(DATE($A$88,MONTH("1-"&A99&"-"&$A$88),1),0)>=Generales!$B$4,DATE($A$88,MONTH("1-"&A99&"-"&$A$88),1)<=Generales!$C$4),"","FUERA DE RANGO") | I99: =J98+1 -> 660 | J99: 736 | K99: =(J99-I99)+1 -> 77
A100: Noviembre | E100: =IF(AND(EOMONTH(DATE($A$88,MONTH("1-"&A100&"-"&$A$88),1),0)>=Generales!$B$4,DATE($A$88,MONTH("1-"&A100&"-"&$A$88),1)<=Generales!$C$4),"","FUERA DE RANGO") | I100: =J99+1 -> 737 | J100: 784 | K100: =(J100-I100)+1 -> 48
A101: Diciembre | E101: =IF(AND(EOMONTH(DATE($A$88,MONTH("1-"&A101&"-"&$A$88),1),0)>=Generales!$B$4,DATE($A$88,MONTH("1-"&A101&"-"&$A$88),1)<=Generales!$C$4),"","FUERA DE RANGO") | I101: =J100+1 -> 785 | K101: =(J101-I101)+1 -> -784

Sheet Fondo (Recaudo + Aporte)
A1: MES | B1: BANCO | C1: Recaudo | D1: Aporte | E1: VALOR | F1: FECHA CONSIGNACIÓN | H1: ¿Existen inconsistencias en la liquidación? | I1: Liquidado | J1: Tarifa Plena | K1: Tarifa Especial | L1: Exentas de aportes + No autorizadas | N1: ¿Coincide con el rango reportado?
A2: Julio | B2: =Recaudo!B4 -> 0 | C2: =Recaudo!C4 -> 0 | E2: =IF(C2="FUERA DE RANGO","FUERA DE RANGO",C2+D2) -> 0 | F2: =Recaudo!D4 -> 0 | G2: =Recaudo!E4 -> FUERA DE RANGO | H2: =IF(D2<I2,D2-I2,"NO") -> -23000 | I2: =((Recaudo!F3*J2)+(Recaudo!G3*K2)) -> 23000 | J2: 5 | K2: 0 | L2: 0 | M2: =K2+J2 -> 5 | N2: =IF('Fondo (Recaudo + Aporte)'!M2+L2=Recaudo!K3,"SÍ","NO") -> NO
A3: Agosto | B3: =Recaudo!B5 -> 0 | C3: =Recaudo!C5 -> 0 | E3: =IF(C3="FUERA DE RANGO","FUERA DE RANGO",C3+D3) -> 0 | F3: =Recaudo!D5 -> 0 | G3: =Recaudo!E5 -> FUERA DE RANGO | H3: =IF(D3<I3,D3-I3,"NO") -> NO | I3: =((Recaudo!F4*J3)+(Recaudo!G4*K3)) -> 0 | J3: 5 | K3: 0 | L3: 0 | M3: =K3+J3 -> 5 | N3: =IF('Fondo (Recaudo + Aporte)'!M3+L3=Recaudo!K4,"SÍ","NO") -> NO
A4: Septiembre | B4: =Recaudo!B6 -> 0 | C4: =Recaudo!C6 -> 0 | E4: =IF(C4="FUERA DE RANGO","FUERA DE RANGO",C4+D4) -> 0 | F4: =Recaudo!D6 -> 0 | G4: =Recaudo!E6 -> FUERA DE RANGO | H4: =IF(D4<I4,D4-I4,"NO") -> NO | I4: =((Recaudo!F5*J4)+(Recaudo!G5*K4)) -> 0 | J4: 5 | K4: 0 | L4: 0 | M4: =K4+J4 -> 5 | N4: =IF('Fondo (Recaudo + Aporte)'!M4+L4=Recaudo!K5,"SÍ","NO") -> NO
A5: Octubre | B5: =Recaudo!B7 -> 0 | C5: =Recaudo!C7 -> 0 | E5: =IF(C5="FUERA DE RANGO","FUERA DE RANGO",C5+D5) -> 0 | F5: =Recaudo!D7 -> 0 | G5: =Recaudo!E7 -> FUERA DE RANGO | H5: =IF(D5<I5,D5-I5,"NO") -> NO | I5: =((Recaudo!F6*J5)+(Recaudo!G6*K5)) -> 0 | J5: 5 | K5: 0 | L5: 0 | M5: =K5+J5 -> 5 | N5: =IF('Fondo (Recaudo + Aporte)'!M5+L5=Recaudo!K6,"SÍ","NO") -> NO
A6: Noviembre | B6: =Recaudo!B8 -> 0 | C6: =Recaudo!C8 -> 0 | E6: =IF(C6="FUERA DE RANGO","FUERA DE RANGO",C6+D6) -> 0 | F6: =Recaudo!D8 -> 0 | G6: =Recaudo!E8 -> FUERA DE RANGO | H6: =IF(D6<I6,D6-I6,"NO") -> NO | I6: =((Recaudo!F7*J6)+(Recaudo!G7*K6)) -> 0 | J6: 5 | K6: 0 | L6: 0 | M6: =K6+J6 -> 5 | N6: =IF('Fondo (Recaudo + Aporte)'!M6+L6=Recaudo!K7,"SÍ","NO") -> NO
A7: Diciembre | B7: =Recaudo!B9 -> 0 | C7: =Recaudo!C9 -> 0 | E7: =IF(C7="FUERA DE RANGO","FUERA DE RANGO",C7+D7) -> 0 | F7: =Recaudo!D9 -> 0 | G7: =Recaudo!E9 -> FUERA DE RANGO | H7: =IF(D7<I7,D7-I7,"NO") -> NO | I7: =((Recaudo!F8*J7)+(Recaudo!G8*K7)) -> 0 | J7: 5 | K7: 0 | L7: 0 | M7: =K7+J7 -> 5 | N7: =IF('Fondo (Recaudo + Aporte)'!M7+L7=Recaudo!K8,"SÍ","NO") -> NO
A11: AÑO 2020 | B11: BANCO | C11: Recaudo | D11: Aporte | E11: VALOR | F11: FECHA CONSIGNACIÓN
A12: MES
A13: Enero | B13: =Recaudo!B14 -> PSE | E13: =IF(C13="FUERA DE RANGO","FUERA DE RANGO",C13+D13) -> 0 | F13: =Recaudo!D14 -> 43866 | G13: =Recaudo!E14 -> FUERA DE RANGO | H13: =IF(D13<I13,D13-I13,"NO") -> NO | I13: =((Recaudo!$F$13*J13)+(Recaudo!$G$13*K13)) -> 0 | N13: =IF('Fondo (Recaudo + Aporte)'!M13+L13=Recaudo!K14,"SÍ","NO") -> SÍ
A14: Febrero | B14: PSE | E14: =IF(C14="FUERA DE RANGO","FUERA DE RANGO",C14+D14) -> 0 | F14: =Recaudo!D15 -> 43896 | G14: =Recaudo!E15 -> FUERA DE RANGO | H14: =IF(D14<I14,D14-I14,"NO") -> NO | I14: =((Recaudo!$F$13*J14)+(Recaudo!$G$13*K14)) -> 0 | M14: =K14+J14 -> 0 | N14: =IF('Fondo (Recaudo + Aporte)'!M14+L14=Recaudo!K15,"SÍ","NO") -> SÍ | Q14: =P14+O14 -> 0 | S14: 931900 | T14: 1406150 | U14: =T14+S14 -> 2338050
A15: Febrero | B15: =Recaudo!B16 -> PSE | E15: =IF(C15="FUERA DE RANGO","FUERA DE RANGO",C15+D15) -> 0 | F15: =Recaudo!D16 -> 43896 | G15: =Recaudo!E16 -> FUERA DE RANGO | H15: =IF(D15<I15,D15-I15,"NO") -> NO | I15: =((Recaudo!$F$13*J15)+(Recaudo!$G$13*K15)) -> 0 | M15: =K15+J15 -> 0 | N15: =IF('Fondo (Recaudo + Aporte)'!M15+L15=Recaudo!K16,"SÍ","NO") -> SÍ
A16: Marzo | B16: =Recaudo!B17 -> PSE | C16: =Recaudo!C17 -> 0 | E16: =IF(C16="FUERA DE RANGO","FUERA DE RANGO",C16+D16) -> 0 | F16: =Recaudo!D17 -> 43935 | G16: =Recaudo!E17 -> FUERA DE RANGO | H16: =IF(D16<I16,D16-I16,"NO") -> NO | I16: =((Recaudo!$F$13*J16)+(Recaudo!$G$13*K16)) -> 0 | M16: =K16+J16 -> 0 | N16: =IF('Fondo (Recaudo + Aporte)'!M16+L16=Recaudo!K17,"SÍ","NO") -> SÍ
A17: Abril | B17: =Recaudo!B18 -> PSE | C17: =Recaudo!C33 -> 0 | D17: =E17-C17 -> 5898800 | E17: 5898800 | F17: =Recaudo!D33 -> 0 | G17: =Recaudo!E18 -> FUERA DE RANGO | H17: =IF(D17<I17,D17-I17,"NO") -> NO | I17: =((Recaudo!F29*J17)+(Recaudo!$G$29*K17)) -> 0 | M17: =K17+J17 -> 0 | N17: =IF('Fondo (Recaudo + Aporte)'!M17+L17=Recaudo!K18,"SÍ","NO") -> SÍ
A18: Mayo | B18: =Recaudo!B19 -> PSE | C18: =Recaudo!C34 -> 0 | E18: =IF(C18="FUERA DE RANGO","FUERA DE RANGO",C18+D18) -> 0 | F18: =Recaudo!D19 -> 43985 | G18: =Recaudo!E19 -> FUERA DE RANGO | H18: =IF(D18<I18,D18-I18,"NO") -> NO | I18: =((Recaudo!$F$13*J18)+(Recaudo!$G$13*K18)) -> 0 | M18: =K18+J18 -> 0 | N18: =IF('Fondo (Recaudo + Aporte)'!M18+L18=Recaudo!K19,"SÍ","NO") -> SÍ
A19: Junio | B19: =Recaudo!B20 -> PSE | C19: =Recaudo!C35 -> 0 | E19: =IF(C19="FUERA DE RANGO","FUERA DE RANGO",C19+D19) -> 0 | F19: =Recaudo!D20 -> 44021 | G19: =Recaudo!E20 -> FUERA DE RANGO | H19: =IF(D19<I19,D19-I19,"NO") -> NO | I19: =((Recaudo!$F$13*J19)+(Recaudo!$G$13*K19)) -> 0 | M19: =K19+J19 -> 0 | N19: =IF('Fondo (Recaudo + Aporte)'!M19+L19=Recaudo!K20,"SÍ","NO") -> SÍ
A20: Julio | B20: =Recaudo!B21 -> PSE | C20: =Recaudo!C36 -> 0 | E20: =IF(C20="FUERA DE RANGO","FUERA DE RANGO",C20+D20) -> 0 | F20: =Recaudo!D21 -> 44054 | G20: =Recaudo!E21 -> FUERA DE RANGO | H20: =IF(D20<I20,D20-I20,"NO") -> NO | I20: =((Recaudo!$F$13*J20)+(Recaudo!$G$13*K20)) -> 0 | M20: =K20+J20 -> 0 | N20: =IF('Fondo (Recaudo + Aporte)'!M20+L20=Recaudo!K21,"SÍ","NO") -> SÍ
A21: Agosto | B21: =Recaudo!B22 -> PSE | C21: =Recaudo!C37 -> 0 | E21: =IF(C21="FUERA DE RANGO","FUERA DE RANGO",C21+D21) -> 0 | F21: =Recaudo!D22 -> 44084 | G21: =Recaudo!E22 -> FUERA DE RANGO | H21: =IF(D21<I21,D21-I21,"NO") -> NO | I21: =((Recaudo!$F$13*J21)+(Recaudo!$G$13*K21)) -> 0 | M21: =K21+J21 -> 0 | N21: =IF('Fondo (Recaudo + Aporte)'!M21+L21=Recaudo!K22,"SÍ","NO") -> SÍ
A22: Septiembre | B22: =Recaudo!B23 -> PSE | C22: =Recaudo!C38 -> 0 | E22: =IF(C22="FUERA DE RANGO","FUERA DE RANGO",C22+D22) -> 0 | F22: =Recaudo!D23 -> 44117 | G22: =Recaudo!E23 -> FUERA DE RANGO | H22: =IF(D22<I22,D22-I22,"NO") -> NO | I22: =((Recaudo!$F$13*J22)+(Recaudo!$G$13*K22)) -> 0 | M22: =K22+J22 -> 0 | N22: =IF('Fondo (Recaudo + Aporte)'!M22+L22=Recaudo!K23,"SÍ","NO") -> SÍ
A23: Octubre | B23: =Recaudo!B24 -> PSE | C23: =Recaudo!C39 -> 0 | E23: =IF(C23="FUERA DE RANGO","FUERA DE RANGO",C23+D23) -> 0 | F23: =Recaudo!D24 -> 44145 | G23: =Recaudo!E24 -> FUERA DE RANGO | H23: =IF(D23<I23,D23-I23,"NO") -> NO | I23: =((Recaudo!$F$13*J23)+(Recaudo!$G$13*K23)) -> 0 | M23: =K23+J23 -> 0 | N23: =IF('Fondo (Recaudo + Aporte)'!M23+L23=Recaudo!K24,"SÍ","NO") -> SÍ
A24: Noviembre | B24: =Recaudo!B25 -> PSE | C24: =Recaudo!C40 -> 0 | E24: =IF(C24="FUERA DE RANGO","FUERA DE RANGO",C24+D24) -> 0 | F24: =Recaudo!D25 -> 44175 | G24: =Recaudo!E25 -> FUERA DE RANGO | H24: =IF(D24<I24,D24-I24,"NO") -> NO | I24: =((Recaudo!$F$13*J24)+(Recaudo!$G$13*K24)) -> 0 | M24: =K24+J24 -> 0 | N24: =IF('Fondo (Recaudo + Aporte)'!M24+L24=Recaudo!K25,"SÍ","NO") -> SÍ
A25: Diciembre | B25: =Recaudo!B26 -> PSE | C25: =Recaudo!C41 -> 0 | E25: =IF(C25="FUERA DE RANGO","FUERA DE RANGO",C25+D25) -> 0 | F25: =Recaudo!D26 -> 44531 | G25: =Recaudo!E26 -> FUERA DE RANGO | H25: =IF(D25<I25,D25-I25,"NO") -> NO | I25: =((Recaudo!$F$13*J25)+(Recaudo!$G$13*K25)) -> 0 | M25: =K25+J25 -> 0 | N25: =IF('Fondo (Recaudo + Aporte)'!M25+L25=Recaudo!K26,"SÍ","NO") -> SÍ
A27: AÑO 2021 | B27: BANCO | C27: Recaudo | D27: Aporte | E27: VALOR | F27: FECHA CONSIGNACIÓN
A28: MES
A29: Enero | B29: =Recaudo!B30 -> 0 | C29: =Recaudo!C30 -> 0 | E29: =IF(C29="FUERA DE RANGO","FUERA DE RANGO",C29+D29) -> 0 | F29: =Recaudo!D30 -> 0 | G29: =Recaudo!E30 -> FUERA DE RANGO | H29: =IF(D29<I29,D29-I29,"NO") -> NO | I29: =((Recaudo!$F$29*J29)+(Recaudo!$G$29*K29)) -> 0 | M29: =K29+J29 -> 0 | N29: =IF('Fondo (Recaudo + Aporte)'!M29+L29=Recaudo!K30,"SÍ","NO") -> SÍ
A30: Febrero | B30: =Recaudo!B31 -> 0 | C30: =Recaudo!C31 -> 0 | E30: =IF(C30="FUERA DE RANGO","FUERA DE RANGO",C30+D30) -> 0 | F30: =Recaudo!D31 -> 0 | G30: =Recaudo!E31 -> FUERA DE RANGO | H30: =IF(D30<I30,D30-I30,"NO") -> NO | I30: =((Recaudo!$F$29*J30)+(Recaudo!$G$29*K30)) -> 0 | M30: =K30+J30 -> 0 | N30: =IF('Fondo (Recaudo + Aporte)'!M30+L30=Recaudo!K31,"SÍ","NO") -> SÍ
A31: Marzo | B31: =Recaudo!B32 -> 0 | C31: =Recaudo!C32 -> 0 | E31: =IF(C31="FUERA DE RANGO","FUERA DE RANGO",C31+D31) -> 0 | F31: =Recaudo!D32 -> 0 | G31: =Recaudo!E32 -> FUERA DE RANGO | H31: =IF(D31<I31,D31-I31,"NO") -> NO | I31: =((Recaudo!$F$29*J31)+(Recaudo!$G$29*K31)) -> 0 | M31: =K31+J31 -> 0 | N31: =IF('Fondo (Recaudo + Aporte)'!M31+L31=Recaudo!K32,"SÍ","NO") -> NO
A32: Abril | B32: =Recaudo!B33 -> 0 | C32: =Recaudo!C33 -> 0 | E32: 5898800 | F32: =Recaudo!D33 -> 0 | G32: =Recaudo!E33 -> FUERA DE RANGO | H32: =IF(D32<I32,D32-I32,"NO") -> NO | I32: =((Recaudo!$F$29*J32)+(Recaudo!$G$29*K32)) -> 0 | M32: =K32+J32 -> 0 | N32: =IF('Fondo (Recaudo + Aporte)'!M32+L32=Recaudo!K33,"SÍ","NO") -> NO
A33: Mayo | B33: =Recaudo!B34 -> 0 | C33: =Recaudo!C34 -> 0 | E33: =IF(C33="FUERA DE RANGO","FUERA DE RANGO",C33+D33) -> 0 | F33: =Recaudo!D34 -> 0 | G33: =Recaudo!E34 -> FUERA DE RANGO | H33: =IF(D33<I33,D33-I33,"NO") -> NO | I33: =((Recaudo!$F$29*J33)+(Recaudo!$G$29*K33)) -> 0 | M33: =K33+J33 -> 0 | N33: =IF('Fondo (Recaudo + Aporte)'!M33+L33=Recaudo!K34,"SÍ","NO") -> NO
A34: Junio | B34: =Recaudo!B35 -> 0 | C34: =Recaudo!C35 -> 0 | E34: =IF(C34="FUERA DE RANGO","FUERA DE RANGO",C34+D34) -> 0 | F34: =Recaudo!D35 -> 0 | G34: =Recaudo!E35 -> FUERA DE RANGO | H34: =IF(D34<I34,D34-I34,"NO") -> NO | I34: =((Recaudo!$F$29*J34)+(Recaudo!$G$29*K34)) -> 0 | M34: =K34+J34 -> 0 | N34: =IF('Fondo (Recaudo + Aporte)'!M34+L34=Recaudo!K35,"SÍ","NO") -> NO
A35: Julio | B35: =Recaudo!B36 -> 0 | C35: =Recaudo!C36 -> 0 | E35: =IF(C35="FUERA DE RANGO","FUERA DE RANGO",C35+D35) -> 0 | F35: =Recaudo!D36 -> 0 | G35: =Recaudo!E36 -> FUERA DE RANGO | H35: =IF(D35<I35,D35-I35,"NO") -> NO | I35: =((Recaudo!$F$29*J35)+(Recaudo!$G$29*K35)) -> 0 | M35: =K35+J35 -> 0 | N35: =IF('Fondo (Recaudo + Aporte)'!M35+L35=Recaudo!K36,"SÍ","NO") -> NO
A36: Agosto | B36: =Recaudo!B37 -> 0 | C36: =Recaudo!C37 -> 0 | E36: =IF(C36="FUERA DE RANGO","FUERA DE RANGO",C36+D36) -> 0 | F36: =Recaudo!D37 -> 0 | G36: =Recaudo!E37 -> FUERA DE RANGO | H36: =IF(D36<I36,D36-I36,"NO") -> NO | I36: =((Recaudo!$F$29*J36)+(Recaudo!$G$29*K36)) -> 0 | M36: =K36+J36 -> 0 | N36: =IF('Fondo (Recaudo + Aporte)'!M36+L36=Recaudo!K37,"SÍ","NO") -> NO
A37: Septiembre | B37: =Recaudo!B38 -> 0 | C37: =Recaudo!C38 -> 0 | E37: =IF(C37="FUERA DE RANGO","FUERA DE RANGO",C37+D37) -> 0 | F37: =Recaudo!D38 -> 0 | G37: =Recaudo!E38 -> FUERA DE RANGO | H37: =IF(D37<I37,D37-I37,"NO") -> NO | I37: =((Recaudo!$F$29*J37)+(Recaudo!$G$29*K37)) -> 0 | M37: =K37+J37 -> 0 | N37: =IF('Fondo (Recaudo + Aporte)'!M37+L37=Recaudo!K38,"SÍ","NO") -> NO
A38: Octubre | B38: =Recaudo!B39 -> 0 | C38: =Recaudo!C39 -> 0 | E38: =IF(C38="FUERA DE RANGO","FUERA DE RANGO",C38+D38) -> 0 | F38: =Recaudo!D39 -> 0 | G38: =Recaudo!E39 -> FUERA DE RANGO | H38: =IF(D38<I38,D38-I38,"NO") -> NO | I38: =((Recaudo!$F$29*J38)+(Recaudo!$G$29*K38)) -> 0 | M38: =K38+J38 -> 0 | N38: =IF('Fondo (Recaudo + Aporte)'!M38+L38=Recaudo!K39,"SÍ","NO") -> NO
A39: Noviembre | B39: =Recaudo!B40 -> 0 | C39: =Recaudo!C40 -> 0 | E39: =IF(C39="FUERA DE RANGO","FUERA DE RANGO",C39+D39) -> 0 | F39: =Recaudo!D40 -> 0 | G39: =Recaudo!E40 -> FUERA DE RANGO | H39: =IF(D39<I39,D39-I39,"NO") -> NO | I39: =((Recaudo!$F$29*J39)+(Recaudo!$G$29*K39)) -> 0 | M39: =K39+J39 -> 0 | N39: =IF('Fondo (Recaudo + Aporte)'!M39+L39=Recaudo!K40,"SÍ","NO") -> NO
A40: Diciembre | B40: =Recaudo!B41 -> 0 | C40: =Recaudo!C41 -> 0 | E40: =IF(C40="FUERA DE RANGO","FUERA DE RANGO",C40+D40) -> 0 | F40: =Recaudo!D41 -> 0 | G40: =Recaudo!E41 -> FUERA DE RANGO | H40: =IF(D40<I40,D40-I40,"NO") -> NO | I40: =((Recaudo!$F$29*J40)+(Recaudo!$G$29*K40)) -> 0 | M40: =K40+J40 -> 0 | N40: =IF('Fondo (Recaudo + Aporte)'!M40+L40=Recaudo!K41,"SÍ","NO") -> NO
A42: AÑO 2022 | B42: BANCO | C42: Recaudo | D42: Aporte | E42: VALOR | F42: FECHA CONSIGNACIÓN
A43: MES
A44: Enero | B44: =Recaudo!B45 -> 0 | C44: =Recaudo!C45 -> 0 | E44: =IF(C44="FUERA DE RANGO","FUERA DE RANGO",C44+D44) -> 0 | F44: =Recaudo!D45 -> 0 | G44: =Recaudo!E45 -> FUERA DE RANGO | H44: =IF(D44<I44,D44-I44,"NO") -> NO | I44: =((Recaudo!$F$29*J44)+(Recaudo!$G$29*K44)) -> 0 | M44: =K44+J44 -> 0 | N44: =IF('Fondo (Recaudo + Aporte)'!M44+L44=Recaudo!K45,"SÍ","NO") -> SÍ
A45: Febrero | B45: =Recaudo!B46 -> 0 | C45: =Recaudo!C46 -> 0 | E45: =IF(C45="FUERA DE RANGO","FUERA DE RANGO",C45+D45) -> 0 | F45: =Recaudo!D46 -> 0 | G45: =Recaudo!E46 -> FUERA DE RANGO | H45: =IF(D45<I45,D45-I45,"NO") -> #N/A | I45: =((Recaudo!$F$44*J45)+(Recaudo!$G$44*K45)) -> #N/A | M45: =K45+J45 -> 0 | N45: =IF('Fondo (Recaudo + Aporte)'!M45+L45=Recaudo!K46,"SÍ","NO") -> SÍ
A46: Marzo | B46: =Recaudo!B47 -> 0 | C46: =Recaudo!C47 -> 0 | E46: =IF(C46="FUERA DE RANGO","FUERA DE RANGO",C46+D46) -> 0 | F46: =Recaudo!D47 -> 0 | G46: =Recaudo!E47 -> FUERA DE RANGO | H46: =IF(D46<I46,D46-I46,"NO") -> #N/A | I46: =((Recaudo!$F$44*J46)+(Recaudo!$G$44*K46)) -> #N/A | M46: =K46+J46 -> 0 | N46: =IF('Fondo (Recaudo + Aporte)'!M46+L46=Recaudo!K47,"SÍ","NO") -> SÍ
A47: Abril | B47: =Recaudo!B48 -> 0 | C47: =Recaudo!C48 -> 0 | E47: =IF(C47="FUERA DE RANGO","FUERA DE RANGO",C47+D47) -> 0 | F47: =Recaudo!D48 -> 0 | G47: =Recaudo!E48 -> FUERA DE RANGO | H47: =IF(D47<I47,D47-I47,"NO") -> #N/A | I47: =((Recaudo!$F$44*J47)+(Recaudo!$G$44*K47)) -> #N/A | M47: =K47+J47 -> 0 | N47: =IF('Fondo (Recaudo + Aporte)'!M47+L47=Recaudo!K48,"SÍ","NO") -> SÍ
A48: Mayo | B48: =Recaudo!B49 -> 0 | C48: =Recaudo!C49 -> 0 | E48: =IF(C48="FUERA DE RANGO","FUERA DE RANGO",C48+D48) -> 0 | F48: =Recaudo!D49 -> 0 | G48: =Recaudo!E49 -> FUERA DE RANGO | H48: =IF(D48<I48,D48-I48,"NO") -> #N/A | I48: =((Recaudo!$F$44*J48)+(Recaudo!$G$44*K48)) -> #N/A | M48: =K48+J48 -> 0 | N48: =IF('Fondo (Recaudo + Aporte)'!M48+L48=Recaudo!K49,"SÍ","NO") -> SÍ
A49: Junio | B49: =Recaudo!B50 -> 0 | C49: =Recaudo!C50 -> 0 | E49: =IF(C49="FUERA DE RANGO","FUERA DE RANGO",C49+D49) -> 0 | F49: =Recaudo!D50 -> 0 | G49: =Recaudo!E50 -> FUERA DE RANGO | H49: =IF(D49<I49,D49-I49,"NO") -> #N/A | I49: =((Recaudo!$F$44*J49)+(Recaudo!$G$44*K49)) -> #N/A | M49: =K49+J49 -> 0 | N49: =IF('Fondo (Recaudo + Aporte)'!M49+L49=Recaudo!K50,"SÍ","NO") -> SÍ
A50: Julio | B50: =Recaudo!B51 -> 0 | C50: =Recaudo!C51 -> 0 | E50: =IF(C50="FUERA DE RANGO","FUERA DE RANGO",C50+D50) -> 0 | F50: 44774 | G50: =Recaudo!E51 -> FUERA DE RANGO | H50: =IF(D50<I50,D50-I50,"NO") -> #N/A | I50: =((Recaudo!$F$44*J50)+(Recaudo!$G$44*K50)) -> #N/A | M50: =K50+J50 -> 0 | N50: =IF('Fondo (Recaudo + Aporte)'!M50+L50=Recaudo!K51,"SÍ","NO") -> SÍ
A51: Agosto | B51: =Recaudo!B52 -> 0 | C51: =Recaudo!C52 -> 0 | E51: =C51+D51 -> 0 | F51: 44805 | G51: =Recaudo!E52 -> FUERA DE RANGO | H51: =IF(D51<I51,D51-I51,"NO") -> #N/A | I51: =((Recaudo!$F$44*J51)+(Recaudo!$G$44*K51)) -> #N/A | M51: =K51+J51 -> 0 | N51: =IF('Fondo (Recaudo + Aporte)'!M51+L51=Recaudo!K52,"SÍ","NO") -> SÍ
A52: Septiembre | B52: =Recaudo!B53 -> 0 | C52: =Recaudo!C53 -> 0 | E52: =C52+D52 -> 0 | F52: =Recaudo!D53 -> 0 | G52: =Recaudo!E53 -> FUERA DE RANGO | H52: =IF(D52<I52,D52-I52,"NO") -> #N/A | I52: =((Recaudo!$F$44*J52)+(Recaudo!$G$44*K52)) -> #N/A | M52: =K52+J52 -> 0 | N52: =IF('Fondo (Recaudo + Aporte)'!M52+L52=Recaudo!K53,"SÍ","NO") -> SÍ
A53: Octubre | B53: =Recaudo!B54 -> 0 | C53: =Recaudo!C54 -> 0 | E53: =C53+D53 -> 0 | F53: =Recaudo!D54 -> 0 | G53: =Recaudo!E54 -> FUERA DE RANGO | H53: =IF(D53<I53,D53-I53,"NO") -> #N/A | I53: =((Recaudo!$F$44*J53)+(Recaudo!$G$44*K53)) -> #N/A | M53: =K53+J53 -> 0 | N53: =IF('Fondo (Recaudo + Aporte)'!M53+L53=Recaudo!K54,"SÍ","NO") -> SÍ
A54: Noviembre | B54: =Recaudo!B56 -> 0 | C54: =Recaudo!C55 -> 0 | E54: =C54+D54 -> 0 | F54: =Recaudo!D55 -> 0 | G54: =Recaudo!E55 -> FUERA DE RANGO | H54: =IF(D54<I54,D54-I54,"NO") -> #N/A | I54: =((Recaudo!$F$44*J54)+(Recaudo!$G$44*K54)) -> #N/A | M54: =K54+J54 -> 0 | N54: =IF('Fondo (Recaudo + Aporte)'!M54+L54=Recaudo!K55,"SÍ","NO") -> SÍ
A55: Diciembre | B55: =Recaudo!B56 -> 0 | C55: =Recaudo!C56 -> 0 | E55: =C55+D55 -> 0 | F55: =Recaudo!D56 -> 0 | G55: =Recaudo!E56 -> FUERA DE RANGO | H55: =IF(D55<I55,D55-I55,"NO") -> #N/A | I55: =((Recaudo!$F$44*J55)+(Recaudo!$G$44*K55)) -> #N/A | M55: =K55+J55 -> 0 | N55: =IF('Fondo (Recaudo + Aporte)'!M55+L55=Recaudo!K56,"SÍ","NO") -> SÍ
A57: AÑO 2023 | B57: BANCO | C57: Recaudo | D57: Aporte | E57: VALOR | F57: FECHA CONSIGNACIÓN
A58: MES
A59: Enero | B59: =Recaudo!B60 -> 0 | C59: =Recaudo!C60 -> 0 | E59: =C59+D59 -> 0 | F59: =Recaudo!D60 -> 0 | G59: =Recaudo!E60 -> 0 | H59: =IF(D59<I59,D59-I59,"NO") -> #N/A | I59: =((Recaudo!$F$44*J59)+(Recaudo!$G$44*K59)) -> #N/A | M59: =K59+J59 -> 0 | N59: =IF('Fondo (Recaudo + Aporte)'!M59+L59=Recaudo!K60,"SÍ","NO") -> SÍ
A60: Febrero | B60: PSE | C60: =Recaudo!C61 -> 0 | E60: =C60+D60 -> 0 | F60: =Recaudo!D61 -> 0 | G60: =Recaudo!E61 -> FUERA DE RANGO | H60: =IF(D60<I60,D60-I60,"NO") -> #N/A | I60: =((Recaudo!$F$59*J60)+(Recaudo!$G$59*K60)) -> #N/A | M60: =K60+J60 -> 0 | N60: =IF('Fondo (Recaudo + Aporte)'!M60+L60=Recaudo!K61,"SÍ","NO") -> SÍ
A61: Marzo | B61: =Recaudo!B62 -> 0 | C61: =Recaudo!C62 -> 0 | E61: =C61+D61 -> 0 | F61: =Recaudo!D62 -> 0 | G61: =Recaudo!E62 -> FUERA DE RANGO | H61: =IF(D61<I61,D61-I61,"NO") -> #N/A | I61: =((Recaudo!$F$59*J61)+(Recaudo!$G$59*K61)) -> #N/A | M61: =K61+J61 -> 0 | N61: =IF('Fondo (Recaudo + Aporte)'!M61+L61=Recaudo!K62,"SÍ","NO") -> SÍ
A62: Abril | B62: =Recaudo!B63 -> 0 | C62: =Recaudo!C63 -> 0 | E62: =C62+D62 -> 0 | F62: =Recaudo!D63 -> 0 | G62: =Recaudo!E63 -> FUERA DE RANGO | H62: =IF(D62<I62,D62-I62,"NO") -> #N/A | I62: =((Recaudo!$F$59*J62)+(Recaudo!$G$59*K62)) -> #N/A | M62: =K62+J62 -> 0 | N62: =IF('Fondo (Recaudo + Aporte)'!M62+L62=Recaudo!K63,"SÍ","NO") -> SÍ | O62: ERROR EXPLICADO
A63: Mayo | B63: =Recaudo!B64 -> 0 | C63: =Recaudo!C64 -> 0 | E63: =C63+D63 -> 0 | F63: =Recaudo!D64 -> 0 | G63: =Recaudo!E64 -> FUERA DE RANGO | H63: =IF(D63<I63,D63-I63,"NO") -> #N/A | I63: =((Recaudo!$F$59*J63)+(Recaudo!$G$59*K63)) -> #N/A | M63: =K63+J63 -> 0 | N63: =IF('Fondo (Recaudo + Aporte)'!M63+L63=Recaudo!K64,"SÍ","NO") -> SÍ | O63: ERROR EXPLICADO
A64: Junio | B64: =Recaudo!B65 -> 0 | C64: =Recaudo!C65 -> 0 | E64: =C64+D64 -> 0 | F64: =Recaudo!D65 -> 0 | G64: =Recaudo!E65 -> FUERA DE RANGO | H64: =IF(D64<I64,D64-I64,"NO") -> #N/A | I64: =((Recaudo!$F$59*J64)+(Recaudo!$G$59*K64)) -> #N/A | M64: =K64+J64 -> 0 | N64: =IF('Fondo (Recaudo + Aporte)'!M64+L64=Recaudo!K65,"SÍ","NO") -> SÍ
A65: Julio | B65: =Recaudo!B66 -> 0 | C65: =Recaudo!C66 -> 0 | E65: =C65+D65 -> 0 | F65: =Recaudo!D66 -> 0 | G65: =Recaudo!E66 -> FUERA DE RANGO | H65: =IF(D65<I65,D65-I65,"NO") -> #N/A | I65: =((Recaudo!$F$59*J65)+(Recaudo!$G$59*K65)) -> #N/A | M65: =K65+J65 -> 0 | N65: =IF('Fondo (Recaudo + Aporte)'!M65+L65=Recaudo!K66,"SÍ","NO") -> SÍ
A66: Agosto | B66: =Recaudo!B67 -> 0 | C66: =Recaudo!C67 -> 0 | E66: =C66+D66 -> 0 | F66: =Recaudo!D67 -> 0 | G66: =Recaudo!E67 -> FUERA DE RANGO | H66: =IF(D66<I66,D66-I66,"NO") -> #N/A | I66: =((Recaudo!$F$59*J66)+(Recaudo!$G$59*K66)) -> #N/A | M66: =K66+J66 -> 0 | N66: =IF('Fondo (Recaudo + Aporte)'!M66+L66=Recaudo!K67,"SÍ","NO") -> SÍ
A67: Septiembre | B67: =Recaudo!B68 -> 0 | C67: =Recaudo!C68 -> 0 | E67: =C67+D67 -> 0 | F67: =Recaudo!D68 -> 0 | G67: =Recaudo!E68 -> FUERA DE RANGO | H67: =IF(D67<I67,D67-I67,"NO") -> #N/A | I67: =((Recaudo!$F$59*J67)+(Recaudo!$G$59*K67)) -> #N/A | M67: =K67+J67 -> 0 | N67: =IF('Fondo (Recaudo + Aporte)'!M67+L67=Recaudo!K68,"SÍ","NO") -> SÍ
A68: Octubre | B68: =Recaudo!B69 -> 0 | C68: =Recaudo!C69 -> 0 | E68: =C68+D68 -> 0 | F68: =Recaudo!D69 -> 0 | G68: =Recaudo!E69 -> FUERA DE RANGO | H68: =IF(D68<I68,D68-I68,"NO") -> #N/A | I68: =((Recaudo!$F$59*J68)+(Recaudo!$G$59*K68)) -> #N/A | M68: =K68+J68 -> 0 | N68: =IF('Fondo (Recaudo + Aporte)'!M68+L68=Recaudo!K69,"SÍ","NO") -> SÍ
A69: Noviembre | B69: =Recaudo!B70 -> 0 | C69: =Recaudo!C70 -> 0 | E69: =C69+D69 -> 0 | F69: =Recaudo!D70 -> 0 | G69: =Recaudo!E70 -> FUERA DE RANGO | H69: =IF(D69<I69,D69-I69,"NO") -> #N/A | I69: =((Recaudo!$F$59*J69)+(Recaudo!$G$59*K69)) -> #N/A | M69: =K69+J69 -> 0 | N69: =IF('Fondo (Recaudo + Aporte)'!M69+L69=Recaudo!K70,"SÍ","NO") -> SÍ
A70: Diciembre | B70: =Recaudo!B71 -> 0 | C70: =Recaudo!C71 -> 0 | E70: =C70+D70 -> 0 | F70: =Recaudo!D71 -> 0 | G70: =Recaudo!E71 -> FUERA DE RANGO | H70: =IF(D70<I70,D70-I70,"NO") -> #N/A | I70: =((Recaudo!$F$59*J70)+(Recaudo!$G$59*K70)) -> #N/A | M70: =K70+J70 -> 0 | N70: =IF('Fondo (Recaudo + Aporte)'!M70+L70=Recaudo!K71,"SÍ","NO") -> SÍ
A72: AÑO 2024 | B72: BANCO | C72: Recaudo | D72: Aporte | E72: VALOR | F72: FECHA CONSIGNACIÓN
A73: MES
A74: Enero | B74: =Recaudo!B76 -> 0 | C74: =Recaudo!C75 -> 0 | E74: =C74+D74 -> 0 | F74: =Recaudo!D75 -> 0 | G74: =Recaudo!E75 -> 0 | H74: =IF(D74<I74,D74-I74,"NO") -> NO | I74: =((6000*J74)+((6000/2)*K74)) -> 0 | M74: =K74+J74 -> 0 | N74: =IF('Fondo (Recaudo + Aporte)'!M74+L74=Recaudo!K75,"SÍ","NO") -> SÍ
A75: Febrero | B75: =Recaudo!B76 -> 0 | C75: =Recaudo!C76 -> 0 | E75: =C75+D75 -> 0 | F75: =Recaudo!D76 -> 0 | G75: =Recaudo!E76 -> 0 | H75: =IF(D75<I75,D75-I75,"NO") -> #N/A | I75: =((Recaudo!$F$74*J75)+(Recaudo!$G$74*K75)) -> #N/A | M75: =K75+J75 -> 0 | N75: =IF('Fondo (Recaudo + Aporte)'!M75+L75=Recaudo!K76,"SÍ","NO") -> SÍ
A76: Marzo | B76: =Recaudo!B77 -> 0 | C76: =Recaudo!C77 -> 0 | E76: =C76+D76 -> 0 | F76: =Recaudo!D77 -> 0 | G76: =Recaudo!E77 -> FUERA DE RANGO | H76: =IF(D76<I76,D76-I76,"NO") -> #N/A | I76: =((Recaudo!$F$74*J76)+(Recaudo!$G$74*K76)) -> #N/A | M76: =K76+J76 -> 0 | N76: =IF('Fondo (Recaudo + Aporte)'!M76+L76=Recaudo!K77,"SÍ","NO") -> SÍ
A77: Abril | B77: =Recaudo!B78 -> 0 | C77: =Recaudo!C78 -> 0 | E77: =C77+D77 -> 0 | F77: =Recaudo!D78 -> 0 | G77: =Recaudo!E78 -> FUERA DE RANGO | H77: =IF(D77<I77,D77-I77,"NO") -> #N/A | I77: =((Recaudo!$F$74*J77)+(Recaudo!$G$74*K77)) -> #N/A | M77: =K77+J77 -> 0 | N77: =IF('Fondo (Recaudo + Aporte)'!M77+L77=Recaudo!K78,"SÍ","NO") -> SÍ
A78: Mayo | B78: =Recaudo!B79 -> 0 | C78: =Recaudo!C79 -> 0 | E78: =C78+D78 -> 0 | F78: =Recaudo!D79 -> 0 | G78: =Recaudo!E79 -> FUERA DE RANGO | H78: =IF(D78<I78,D78-I78,"NO") -> #N/A | I78: =((Recaudo!$F$74*J78)+(Recaudo!$G$74*K78)) -> #N/A | M78: =K78+J78 -> 0 | N78: =IF('Fondo (Recaudo + Aporte)'!M78+L78=Recaudo!K79,"SÍ","NO") -> SÍ | O78: ERROR DE 1
A79: Junio | B79: =Recaudo!B80 -> 0 | C79: =Recaudo!C80 -> 0 | E79: =C79+D79 -> 0 | F79: =Recaudo!D80 -> 0 | G79: =Recaudo!E80 -> FUERA DE RANGO | H79: =IF(D79<I79,D79-I79,"NO") -> #N/A | I79: =((Recaudo!$F$74*J79)+(Recaudo!$G$74*K79)) -> #N/A | M79: =K79+J79 -> 0 | N79: =IF('Fondo (Recaudo + Aporte)'!M79+L79=Recaudo!K80,"SÍ","NO") -> SÍ
A80: Julio | B80: =Recaudo!B81 -> 0 | C80: =Recaudo!C81 -> 0 | E80: =C80+D80 -> 0 | F80: =Recaudo!D81 -> 0 | G80: =Recaudo!E81 -> FUERA DE RANGO | H80: =IF(D80<I80,D80-I80,"NO") -> #N/A | I80: =((Recaudo!$F$74*J80)+(Recaudo!$G$74*K80)) -> #N/A | M80: =K80+J80 -> 0 | N80: =IF('Fondo (Recaudo + Aporte)'!M80+L80=Recaudo!K81,"SÍ","NO") -> SÍ
A81: Agosto | B81: =Recaudo!B82 -> 0 | C81: =Recaudo!C82 -> 0 | E81: =C81+D81 -> 0 | F81: =Recaudo!D82 -> 0 | G81: =Recaudo!E82 -> FUERA DE RANGO | H81: =IF(D81<I81,D81-I81,"NO") -> #N/A | I81: =((Recaudo!$F$74*J81)+(Recaudo!$G$74*K81)) -> #N/A | M81: =K81+J81 -> 0 | N81: =IF('Fondo (Recaudo + Aporte)'!M81+L81=Recaudo!K82,"SÍ","NO") -> SÍ
A82: Septiembre | B82: =Recaudo!B83 -> 0 | C82: =Recaudo!C83 -> 0 | E82: =C82+D82 -> 0 | F82: =Recaudo!D83 -> 0 | G82: =Recaudo!E83 -> FUERA DE RANGO | H82: =IF(D82<I82,D82-I82,"NO") -> #N/A | I82: =((Recaudo!$F$74*J82)+(Recaudo!$G$74*K82)) -> #N/A | M82: =K82+J82 -> 0 | N82: =IF('Fondo (Recaudo + Aporte)'!M82+L82=Recaudo!K83,"SÍ","NO") -> SÍ
A83: Octubre | B83: =Recaudo!B84 -> 0 | C83: =Recaudo!C84 -> 0 | E83: =C83+D83 -> 0 | F83: =Recaudo!D84 -> 0 | G83: =Recaudo!E84 -> FUERA DE RANGO | H83: =IF(D83<I83,D83-I83,"NO") -> #N/A | I83: =((Recaudo!$F$74*J83)+(Recaudo!$G$74*K83)) -> #N/A | M83: =K83+J83 -> 0 | N83: =IF('Fondo (Recaudo + Aporte)'!M83+L83=Recaudo!K84,"SÍ","NO") -> SÍ
A84: Noviembre | B84: =Recaudo!B85 -> 0 | C84: =Recaudo!C85 -> 0 | E84: =C84+D84 -> 0 | F84: =Recaudo!D85 -> 0 | G84: =Recaudo!E85 -> FUERA DE RANGO | H84: =IF(D84<I84,D84-I84,"NO") -> #N/A | I84: =((Recaudo!$F$74*J84)+(Recaudo!$G$74*K84)) -> #N/A | M84: =K84+J84 -> 0 | N84: =IF('Fondo (Recaudo + Aporte)'!M84+L84=Recaudo!K85,"SÍ","NO") -> SÍ
A85: Diciembre | B85: =Recaudo!B86 -> 0 | C85: =Recaudo!C86 -> 0 | E85: =C85+D85 -> 0 | F85: =Recaudo!D86 -> 0 | G85: =Recaudo!E86 -> FUERA DE RANGO | H85: =IF(D85<I85,D85-I85,"NO") -> #N/A | I85: =((Recaudo!$F$74*J85)+(Recaudo!$G$74*K85)) -> #N/A | M85: =K85+J85 -> 0 | N85: =IF('Fondo (Recaudo + Aporte)'!M85+L85=Recaudo!K86,"SÍ","NO") -> SÍ
A87: AÑO 2025 | B87: BANCO | C87: Recaudo | D87: Aporte | E87: VALOR | F87: FECHA CONSIGNACIÓN
A88: MES
A89: Enero | B89: =Recaudo!B91 -> 0 | C89: =Recaudo!C90 -> 0 | E89: =C89+D89 -> 0 | F89: =Recaudo!D90 -> 0 | G89: =Recaudo!E90 -> 0 | H89: =IF(D89<I89,D89-I89,"NO") -> NO | I89: =((12200*J89)+((12200/2)*K89)) -> 0 | M89: =K89+J89 -> 0 | N89: =IF('Fondo (Recaudo + Aporte)'!M89+L89=Recaudo!K90,"SÍ","NO") -> SÍ
A90: Febrero | B90: =Recaudo!B91 -> 0 | C90: =Recaudo!C91 -> 0 | E90: =C90+D90 -> 0 | F90: =Recaudo!D91 -> 0 | G90: =Recaudo!E91 -> FUERA DE RANGO | H90: =IF(D90<I90,D90-I90,"NO") -> #N/A | I90: =((Recaudo!$F$89*J90)+(Recaudo!$G$89*K90)) -> #N/A | M90: =K90+J90 -> 0 | N90: =IF('Fondo (Recaudo + Aporte)'!M90+L90=Recaudo!K91,"SÍ","NO") -> SÍ
A91: Marzo | B91: =Recaudo!B92 -> 0 | C91: =Recaudo!C92 -> 0 | E91: =C91+D91 -> 0 | F91: =Recaudo!D92 -> 0 | G91: =Recaudo!E92 -> FUERA DE RANGO | H91: =IF(D91<I91,D91-I91,"NO") -> #N/A | I91: =((Recaudo!$F$89*J91)+(Recaudo!$G$89*K91)) -> #N/A | M91: =K91+J91 -> 0 | N91: =IF('Fondo (Recaudo + Aporte)'!M91+L91=Recaudo!K92,"SÍ","NO") -> SÍ
A92: Abril | B92: =Recaudo!B93 -> 0 | C92: =Recaudo!C93 -> 0 | E92: =C92+D92 -> 0 | F92: =Recaudo!D93 -> 0 | G92: =Recaudo!E93 -> FUERA DE RANGO | H92: =IF(D92<I92,D92-I92,"NO") -> #N/A | I92: =((Recaudo!$F$89*J92)+(Recaudo!$G$89*K92)) -> #N/A | M92: =K92+J92 -> 0 | N92: =IF('Fondo (Recaudo + Aporte)'!M92+L92=Recaudo!K93,"SÍ","NO") -> SÍ
A93: Mayo | B93: =Recaudo!B94 -> 0 | C93: =Recaudo!C94 -> 0 | E93: =C93+D93 -> 0 | F93: =Recaudo!D94 -> 0 | G93: =Recaudo!E94 -> FUERA DE RANGO | H93: =IF(D93<I93,D93-I93,"NO") -> #N/A | I93: =((Recaudo!$F$89*J93)+(Recaudo!$G$89*K93)) -> #N/A | M93: =K93+J93 -> 0 | N93: =IF('Fondo (Recaudo + Aporte)'!M93+L93=Recaudo!K94,"SÍ","NO") -> SÍ | O93: ERROR por 33 se metieron como tarifa especial, pero se supone son exentas VIPA.
A94: Junio | B94: =Recaudo!B95 -> 0 | C94: =Recaudo!C95 -> 0 | E94: =C94+D94 -> 0 | F94: =Recaudo!D95 -> 0 | G94: =Recaudo!E95 -> FUERA DE RANGO | H94: =IF(D94<I94,D94-I94,"NO") -> #N/A | I94: =((Recaudo!$F$89*J94)+(Recaudo!$G$89*K94)) -> #N/A | M94: =K94+J94 -> 0 | N94: =IF('Fondo (Recaudo + Aporte)'!M94+L94=Recaudo!K95,"SÍ","NO") -> SÍ
A95: Julio | B95: =Recaudo!B96 -> 0 | C95: =Recaudo!C96 -> 0 | E95: =C95+D95 -> 0 | F95: =Recaudo!D96 -> 0 | G95: =Recaudo!E96 -> FUERA DE RANGO | H95: =IF(D95<I95,D95-I95,"NO") -> #N/A | I95: =((Recaudo!$F$89*J95)+(Recaudo!$G$89*K95)) -> #N/A | M95: =K95+J95 -> 0 | N95: =IF('Fondo (Recaudo + Aporte)'!M95+L95=Recaudo!K96,"SÍ","NO") -> SÍ | O95: No cuadra por 1
A96: Agosto | B96: =Recaudo!B97 -> 0 | C96: =Recaudo!C97 -> 0 | E96: =C96+D96 -> 0 | F96: =Recaudo!D97 -> 0 | G96: =Recaudo!E97 -> FUERA DE RANGO | H96: =IF(D96<I96,D96-I96,"NO") -> #N/A | I96: =((Recaudo!$F$89*J96)+(Recaudo!$G$89*K96)) -> #N/A | M96: =K96+J96 -> 0 | N96: =IF('Fondo (Recaudo + Aporte)'!M96+L96=Recaudo!K97,"SÍ","NO") -> SÍ
A97: Septiembre | B97: =Recaudo!B98 -> 0 | C97: =Recaudo!C98 -> 0 | E97: =C97+D97 -> 0 | F97: =Recaudo!D98 -> 0 | G97: =Recaudo!E98 | H97: =IF(D97<I97,D97-I97,"NO") -> #N/A | I97: =((Recaudo!$F$89*J97)+(Recaudo!$G$89*K97)) -> #N/A | M97: =K97+J97 -> 0 | N97: =IF('Fondo (Recaudo + Aporte)'!M97+L97=Recaudo!K98,"SÍ","NO") -> NO
A98: Octubre | B98: =Recaudo!B99 -> 0 | C98: =Recaudo!C99 -> 0 | E98: =C98+D98 -> 0 | F98: =Recaudo!D99 -> 0 | G98: =Recaudo!E99 | H98: =IF(D98<I98,D98-I98,"NO") -> #N/A | I98: =((Recaudo!$F$89*J98)+(Recaudo!$G$89*K98)) -> #N/A | M98: =K98+J98 -> 0 | N98: =IF('Fondo (Recaudo + Aporte)'!M98+L98=Recaudo!K99,"SÍ","NO") -> NO
A99: Noviembre | B99: =Recaudo!B100 -> 0 | C99: =Recaudo!C100 -> 0 | E99: =C99+D99 -> 0 | F99: =Recaudo!D100 -> 0 | G99: =Recaudo!E100 | H99: =IF(D99<I99,D99-I99,"NO") -> #N/A | I99: =((Recaudo!$F$89*J99)+(Recaudo!$G$89*K99)) -> #N/A | M99: =K99+J99 -> 0 | N99: =IF('Fondo (Recaudo + Aporte)'!M99+L99=Recaudo!K100,"SÍ","NO") -> NO
A100: Diciembre | B100: =Recaudo!B101 -> 0 | C100: =Recaudo!C101 -> 0 | E100: =C100+D100 -> 0 | F100: =Recaudo!D101 -> 0 | G100: =Recaudo!E101 | H100: =IF(D100<I100,D100-I100,"NO") -> #N/A | I100: =((Recaudo!$F$89*J100)+(Recaudo!$G$89*K100)) -> #N/A | M100: =K100+J100 -> 0 | N100: =IF('Fondo (Recaudo + Aporte)'!M100+L100=Recaudo!K101,"SÍ","NO") -> NO

Sheet Admin. Justicia
A2: AÑO 2017
A3: MES | B3: BANCO | C3: VALOR | D3: FECHA CONSIGNACION | F3: CUMPLE | G3: OBSERVACIONES
A4: Junio
A5: Julio
A6: Agosto
A7: Septiembre
A8: Octubre
A9: Noviembre
A10: Diciembre
A13: MES | B13: BANCO | C13: VALOR | D13: FECHA CONSIGNACIÓN | E13: FECHA DE OBLIGACIÓN | F13: CUMPLE | G13: OBSERVACIONES | H13: INGRESOS BRUTOS | I13: ING. EXCLUIDOS | J13: 0.125
A14: Julio | E14: 43685 | F14: =IF(E14>=D14,"CUMPLE","NO CUMPLE") -> CUMPLE | G14: Ninguna | J14: =(H14-I14)*12.5% -> 0
A15: Agosto | E15: 43714 | F15: =IF(E15>=D15,"CUMPLE","NO CUMPLE") -> CUMPLE | G15: Ninguna | J15: =(H15-I15)*12.5% -> 0
A16: Septiembre | E16: 43745 | F16: =IF(E16>=D16,"CUMPLE","NO CUMPLE") -> CUMPLE | G16: Ninguna | J16: =(H16-I16)*12.5% -> 0
A17: Octubre | E17: 43777 | F17: =IF(E17>=D17,"CUMPLE","NO CUMPLE") -> CUMPLE | G17: Ninguna | J17: =(H17-I17)*12.5% -> 0
A18: Noviembre | E18: 43805 | F18: =IF(E18>=D18,"CUMPLE","NO CUMPLE") -> CUMPLE | G18: Ninguna | J18: =(H18-I18)*12.5% -> 0
A19: Diciembre | E19: 43839 | F19: =IF(E19>=D19,"CUMPLE","NO CUMPLE") -> CUMPLE | G19: Ninguna | J19: =(H19-I19)*12.5% -> 0
A21: AÑO 2020
A22: MES | B22: BANCO | C22: VALOR | D22: FECHA CONSIGNACIÓN | E22: FECHA DE OBLIGACIÓN | F22: CUMPLE | G22: OBSERVACIONES
A23: Enero | E23: 43868 | F23: CUMPLE | G23: Ninguna | J23: =(H23-I23)*12.5% -> 0
A24: Febrero | E24: 43896 | F24: CUMPLE | G24: Ninguna | J24: =(H24-I24)*12.5% -> 0
A25: Marzo | E25: 43928 | F25: =IF(E25>=D25,"CUMPLE","NO CUMPLE") -> CUMPLE | G25: Ninguna | J25: =(H25-I25)*12.5% -> 0
A26: Abril | E26: 43959 | F26: =IF(E26>=D26,"CUMPLE","NO CUMPLE") -> CUMPLE | G26: Ninguna | J26: =(H26-I26)*12.5% -> 0
A27: Mayo | E27: 43987 | F27: =IF(E27>=D27,"CUMPLE","NO CUMPLE") -> CUMPLE | G27: Ninguna | J27: =(H27-I27)*12.5% -> 0
A28: Junio | E28: 44019 | F28: =IF(E28>=D28,"CUMPLE","NO CUMPLE") -> CUMPLE | G28: Ninguna | J28: =(H28-I28)*12.5% -> 0
A29: Julio | E29: 44053 | F29: =IF(E29>=D29,"CUMPLE","NO CUMPLE") -> CUMPLE | G29: Ninguna | J29: =(H29-I29)*12.5% -> 0
A30: Agosto | E30: 44081 | F30: =IF(E30>=D30,"CUMPLE","NO CUMPLE") -> CUMPLE | G30: Ninguna | J30: =(H30-I30)*12.5% -> 0
A31: Septiembre | E31: 44111 | F31: =IF(E31>=D31,"CUMPLE","NO CUMPLE") -> CUMPLE | G31: Ninguna | J31: =(H31-I31)*12.5% -> 0
A32: Octubre | E32: 44144 | F32: =IF(E32>=D32,"CUMPLE","NO CUMPLE") -> CUMPLE | G32: Ninguna | J32: =(H32-I32)*12.5% -> 0
A33: Noviembre | E33: 44172 | F33: =IF(E33>=D33,"CUMPLE","NO CUMPLE") -> CUMPLE | G33: Ninguna | J33: =(H33-I33)*12.5% -> 0
A34: Diciembre | E34: 44204 | F34: =IF(E34>=D34,"CUMPLE","NO CUMPLE") -> CUMPLE | G34: Ninguna | J34: =(H34-I34)*12.5% -> 0
A36: AÑO 2021
A37: MES | B37: BANCO | C37: VALOR | D37: FECHA CONSIGNACIÓN | E37: FECHA DE OBLIGACIÓN | F37: CUMPLE | G37: OBSERVACIONES
A38: Enero | E38: 44232 | F38: =IF(E38>=D38,"CUMPLE","NO CUMPLE") -> CUMPLE | G38: Ninguna | J38: =(H38-I38)*12.5% -> 0
A39: Febrero | E39: 44260 | F39: =IF(E39>=D39,"CUMPLE","NO CUMPLE") -> CUMPLE | G39: Ninguna | J39: =(H39-I39)*12.5% -> 0
A40: Marzo | E40: 44295 | F40: =IF(E40>=D40,"CUMPLE","NO CUMPLE") -> CUMPLE | G40: Ninguna | J40: =(H40-I40)*12.5% -> 0
A41: Abril | E41: 44323 | F41: =IF(E41>=D41,"CUMPLE","NO CUMPLE") -> CUMPLE | G41: Ninguna | J41: =(H41-I41)*12.5% -> 0
A42: Mayo | E42: 44355 | F42: =IF(E42>=D42,"CUMPLE","NO CUMPLE") -> CUMPLE | G42: Ninguna | J42: =(H42-I42)*12.5% -> 0
A43: Junio | E43: 44385 | F43: =IF(E43>=D43,"CUMPLE","NO CUMPLE") -> CUMPLE | G43: Ninguna | J43: =(H43-I43)*12.5% -> 0
A44: Julio | E44: 44414 | F44: =IF(E44>=D44,"CUMPLE","NO CUMPLE") -> CUMPLE | G44: Ninguna | J44: =(H44-I44)*12.5% -> 0
A45: Agosto | E45: 44446 | F45: =IF(E45>=D45,"CUMPLE","NO CUMPLE") -> CUMPLE | G45: Ninguna | J45: =(H45-I45)*12.5% -> 0
A46: Septiembre | E46: 44476 | F46: =IF(E46>=D46,"CUMPLE","NO CUMPLE") -> CUMPLE | G46: Ninguna | J46: =(H46-I46)*12.5% -> 0
A47: Octubre | E47: 44508 | F47: =IF(E47>=D47,"CUMPLE","NO CUMPLE") -> CUMPLE | G47: Ninguna | J47: =(H47-I47)*12.5% -> 0
A48: Noviembre | E48: 44537 | F48: =IF(E48>=D48,"CUMPLE","NO CUMPLE") -> CUMPLE | G48: Ninguna | J48: =(H48-I48)*12.5% -> 0
A49: Diciembre | E49: 44568 | F49: =IF(E49>=D49,"CUMPLE","NO CUMPLE") -> CUMPLE | G49: Ninguna | J49: =(H49-I49)*12.5% -> 0
A51: AÑO 2022
A52: MES | B52: BANCO | C52: VALOR | D52: FECHA CONSIGNACIÓN | E52: FECHA DE OBLIGACIÓN | F52: CUMPLE | G52: OBSERVACIONES
A53: Enero | E53: 44599 | F53: =IF(E53>=D53,"CUMPLE","NO CUMPLE") -> CUMPLE | G53: Ninguna | J53: =(H53-I53)*12.5% -> 0
A54: Febrero | E54: 44627 | F54: =IF(E54>=D54,"CUMPLE","NO CUMPLE") -> CUMPLE | G54: Ninguna | J54: =(H54-I54)*12.5% -> 0
A55: Marzo | E55: 44658 | F55: =IF(E55>=D55,"CUMPLE","NO CUMPLE") -> CUMPLE | G55: Ninguna | J55: =(H55-I55)*12.5% -> 0
A56: Abril | E56: 44687 | F56: =IF(E56>=D56,"CUMPLE","NO CUMPLE") -> CUMPLE | G56: Ninguna | J56: =(H56-I56)*12.5% -> 0
A57: Mayo | E57: 44719 | F57: =IF(E57>=D57,"CUMPLE","NO CUMPLE") -> CUMPLE | G57: Ninguna | J57: =(H57-I57)*12.5% -> 0
A58: Junio | E58: 44750 | F58: =IF(E58>=D58,"CUMPLE","NO CUMPLE") -> CUMPLE | G58: Ninguna | J58: =(H58-I58)*12.5% -> 0
A59: Julio | E59: 44778 | F59: =IF(E59>=D59,"CUMPLE","NO CUMPLE") -> CUMPLE | G59: Ninguna | J59: =(H59-I59)*12.5% -> 0
A60: Agosto | E60: 44811 | F60: =IF(E60>=D60,"CUMPLE","NO CUMPLE") -> CUMPLE | G60: Ninguna | J60: =(H60-I60)*12.5% -> 0
A61: Septiembre | E61: 44841 | F61: =IF(E61>=D61,"CUMPLE","NO CUMPLE") -> CUMPLE | G61: Ninguna | J61: =(H61-I61)*12.5% -> 0
A62: Octubre | E62: 44873 | F62: =IF(E62>=D62,"CUMPLE","NO CUMPLE") -> CUMPLE | G62: Ninguna | J62: =(H62-I62)*12.5% -> 0
A63: Noviembre | E63: 44902 | F63: =IF(E63>=D63,"CUMPLE","NO CUMPLE") -> CUMPLE | G63: Ninguna | J63: =(H63-I63)*12.5% -> 0
A64: Diciembre | E64: 44932 | F64: =IF(E64>=D64,"CUMPLE","NO CUMPLE") -> CUMPLE | G64: Ninguna | J64: =(H64-I64)*12.5% -> 0
A66: AÑO 2023
A67: MES | B67: BANCO | C67: VALOR | D67: FECHA CONSIGNACIÓN | E67: FECHA DE OBLIGACIÓN | F67: CUMPLE | G67: OBSERVACIONES
A68: Enero | E68: 44964 | F68: =IF(E68>=D68,"CUMPLE","NO CUMPLE") -> CUMPLE | G68: Ninguna | J68: =(H68-I68)*12.5% -> 0
A69: Febrero | E69: 44992 | F69: =IF(E69>=D69,"CUMPLE","NO CUMPLE") -> CUMPLE | G69: Ninguna | J69: =(H69-I69)*12.5% -> 0
A70: Marzo | E70: 45027 | F70: =IF(E70>=D70,"CUMPLE","NO CUMPLE") -> CUMPLE | G70: Ninguna | J70: =(H70-I70)*12.5% -> 0
A71: Abril | E71: 45054 | F71: =IF(E71>=D71,"CUMPLE","NO CUMPLE") -> CUMPLE | G71: Ninguna | J71: =(H71-I71)*12.5% -> 0
A72: Mayo | E72: 45084 | F72: =IF(E72>=D72,"CUMPLE","NO CUMPLE") -> CUMPLE | G72: Ninguna | J72: =(H72-I72)*12.5% -> 0
A73: Junio | E73: 45117 | F73: =IF(E73>=D73,"CUMPLE","NO CUMPLE") -> CUMPLE | G73: Ninguna | J73: =(H73-I73)*12.5% -> 0
A74: Julio | E74: 45146 | F74: =IF(E74>=D74,"CUMPLE","NO CUMPLE") -> CUMPLE | G74: Ninguna | J74: =(H74-I74)*12.5% -> 0
A75: Agosto | E75: 45176 | F75: =IF(E75>=D75,"CUMPLE","NO CUMPLE") -> CUMPLE | G75: Ninguna | J75: =(H75-I75)*12.5% -> 0
A76: Septiembre | E76: 45205 | F76: =IF(E76>=D76,"CUMPLE","NO CUMPLE") -> CUMPLE | G76: Ninguna | J76: =(H76-I76)*12.5% -> 0
A77: Octubre | E77: 45238 | F77: =IF(E77>=D77,"CUMPLE","NO CUMPLE") -> CUMPLE | G77: Ninguna | J77: =(H77-I77)*12.5% -> 0
A78: Noviembre | E78: 45267 | F78: =IF(E78>=D78,"CUMPLE","NO CUMPLE") -> CUMPLE | G78: Ninguna | J78: =(H78-I78)*12.5% -> 0
A79: Diciembre | E79: 45300 | F79: =IF(E79>=D79,"CUMPLE","NO CUMPLE") -> CUMPLE | G79: Ninguna | J79: =(H79-I79)*12.5% -> 0
A81: AÑO 2024
A82: MES | B82: BANCO | C82: VALOR | D82: FECHA CONSIGNACIÓN | E82: FECHA DE OBLIGACIÓN | F82: CUMPLE | G82: OBSERVACIONES
A83: Enero | E83: 45329 | F83: =IF(E83>=D83,"CUMPLE","NO CUMPLE") -> CUMPLE | G83: Ninguna | J83: =(H83-I83)*12.5% -> 0
A84: Febrero | E84: 45358 | F84: =IF(E84>=D84,"CUMPLE","NO CUMPLE") -> CUMPLE | G84: Ninguna | J84: =(H84-I84)*12.5% -> 0
A85: Marzo | E85: 45387 | F85: =IF(E85>=D85,"CUMPLE","NO CUMPLE") -> CUMPLE | G85: Ninguna | J85: =(H85-I85)*12.5% -> 0
A86: Abril | E86: 45420 | F86: =IF(E86>=D86,"CUMPLE","NO CUMPLE") -> CUMPLE | G86: Ninguna | J86: =(H86-I86)*12.5% -> 0
A87: Mayo | E87: 45454 | F87: =IF(E87>=D87,"CUMPLE","NO CUMPLE") -> CUMPLE | G87: Ninguna | J87: =(H87-I87)*12.5% -> 0
A88: Junio | E88: 45481 | F88: =IF(E88>=D88,"CUMPLE","NO CUMPLE") -> CUMPLE | G88: Ninguna | J88: =(H88-I88)*12.5% -> 0
A89: Julio | E89: 45512 | F89: =IF(E89>=D89,"CUMPLE","NO CUMPLE") -> CUMPLE | G89: Ninguna | J89: =(H89-I89)*12.5% -> 0
A90: Agosto | E90: 45541 | F90: =IF(E90>=D90,"CUMPLE","NO CUMPLE") -> CUMPLE | G90: Ninguna | J90: =(H90-I90)*12.5% -> 0
A91: Septiembre | E91: 45572 | F91: =IF(E91>=D91,"CUMPLE","NO CUMPLE") -> CUMPLE | G91: Ninguna | J91: =(H91-I91)*12.5% -> 0
A92: Octubre | E92: 45604 | F92: =IF(E92>=D92,"CUMPLE","NO CUMPLE") -> CUMPLE | G92: Ninguna | J92: =(H92-I92)*12.5% -> 0
A93: Noviembre | E93: 45632 | F93: =IF(E93>=D93,"CUMPLE","NO CUMPLE") -> CUMPLE | G93: Ninguna | J93: =(H93-I93)*12.5% -> 0
A94: Diciembre | E94: 45666 | F94: =IF(E94>=D94,"CUMPLE","NO CUMPLE") -> CUMPLE | G94: Ninguna | J94: =(H94-I94)*12.5% -> 0
A96: AÑO 2025
A97: MES | B97: BANCO | C97: VALOR | D97: FECHA CONSIGNACIÓN | E97: FECHA DE OBLIGACIÓN | F97: CUMPLE | G97: OBSERVACIONES
A98: Enero | E98: 45695 | F98: =IF(E98>=D98,"CUMPLE","NO CUMPLE") -> CUMPLE | G98: Ninguna | J98: =(H98-I98)*12.5% -> 0
A99: Febrero | E99: 45727 | F99: =IF(E99>=D99,"CUMPLE","NO CUMPLE") -> CUMPLE | G99: Ninguna | J99: =(H99-I99)*12.5% -> 0
A100: Marzo | E100: 45758 | F100: =IF(E100>=D100,"CUMPLE","NO CUMPLE") -> CUMPLE | G100: Ninguna | J100: =(H100-I100)*12.5% -> 0
A101: Abril | E101: 45786 | F101: =IF(E101>=D101,"CUMPLE","NO CUMPLE") -> CUMPLE | G101: Ninguna | J101: =(H101-I101)*12.5% -> 0
A102: Mayo | E102: 45817 | F102: =IF(E102>=D102,"CUMPLE","NO CUMPLE") -> CUMPLE | G102: Ninguna | J102: =(H102-I102)*12.5% -> 0
A103: Junio | E103: 45847 | F103: =IF(E103>=D103,"CUMPLE","NO CUMPLE") -> CUMPLE | G103: Ninguna | J103: =(H103-I103)*12.5% -> 0
A104: Julio | E104: 45880 | F104: =IF(E104>=D104,"CUMPLE","NO CUMPLE") -> CUMPLE | G104: Ninguna | J104: =(H104-I104)*12.5% -> 0
A105: Agosto | E105: 45909 | F105: =IF(E105>=D105,"CUMPLE","NO CUMPLE") -> CUMPLE | G105: Ninguna | J105: =(H105-I105)*12.5% -> 0
A106: Septiembre | E106: 45939 | F106: =IF(E106>=D106,"CUMPLE","NO CUMPLE") -> CUMPLE | G106: Ninguna | J106: =(H106-I106)*12.5% -> 0
A107: Octubre | E107: 45972 | F107: =IF(E107>=D107,"CUMPLE","NO CUMPLE") -> CUMPLE | G107: Ninguna | J107: =(H107-I107)*12.5% -> 0
A108: Noviembre | E108: 46001 | F108: =IF(E108>=D108,"CUMPLE","NO CUMPLE") -> CUMPLE | G108: Ninguna | J108: =(H108-I108)*12.5% -> 0
A109: Diciembre | E109: 46030 | F109: =IF(E109>=D109,"CUMPLE","NO CUMPLE") -> CUMPLE | G109: Ninguna | J109: =(H109-I109)*12.5% -> 0

Sheet 10% RC
A2: AÑO 2019
A3: MES | B3: BANCO | C3: VALOR | D3: FECHA CONSIGNACION | E3: FECHA ENVIO
A4: Julio | E4: =D4 -> 0
A5: Agosto | E5: =D5 -> 0
A6: Septiembre | E6: =D6 -> 0
A7: Octubre | E7: =D7 -> 0
A8: Noviembre | E8: =D8 -> 0
A9: Diciembre | E9: =D9 -> 0
A11: AÑO 2020
A12: MES | B12: BANCO | C12: VALOR | D12: FECHA CONSIGNACION | E12: FECHA ENVIO
A13: Enero | E13: =D13 -> 0
A14: Febrero | E14: =D14 -> 0
A15: Marzo | E15: =D15 -> 0
A16: Abril | E16: =D16 -> 0
A17: Mayo | E17: =D17 -> 0
A18: Junio | E18: =D18 -> 0
A19: Julio | E19: =D19 -> 0
A20: Agosto | E20: =D20 -> 0
A21: Septiembre | E21: =D21 -> 0
A22: Octubre | E22: =D22 -> 0
A23: Noviembre | E23: =D23 -> 0
A24: Diciembre | E24: =D24 -> 0
A26: AÑO 2021
A27: MES | B27: BANCO | C27: VALOR | D27: FECHA CONSIGNACION | E27: FECHA ENVIO
A28: Enero | E28: =D28 -> 0
A29: Febrero | E29: =D29 -> 0
A30: Marzo | E30: =D30 -> 0
A31: Abril | E31: =D31 -> 0
A32: Mayo | E32: =D32 -> 0
A33: Junio | E33: =D33 -> 0
A34: Julio | E34: =D34 -> 0
A35: Agosto | E35: =D35 -> 0
A36: Septiembre | E36: =D36 -> 0
A37: Octubre | E37: =D37 -> 0
A38: Noviembre | E38: =D38 -> 0
A39: Diciembre | E39: =D39 -> 0
A41: AÑO 2022
A42: MES | B42: BANCO | C42: VALOR | D42: FECHA CONSIGNACION | E42: FECHA ENVIO
A43: Enero | E43: =D43 -> 0
A44: Febrero | E44: =D44 -> 0
A45: Marzo | E45: =D45 -> 0
A46: Abril | E46: =D46 -> 0
A47: Mayo | E47: =D47 -> 0
A48: Junio | E48: =D47 -> 0
A49: Julio | E49: =D48 -> 0
A50: Agosto | E50: =D50 -> 0
A51: Septiembre | E51: =D51 -> 0
A52: Octubre | E52: =D52 -> 0
A53: Noviembre | E53: =D53 -> 0
A54: Diciembre | E54: =D54 -> 0
A56: AÑO 2023
A57: MES | B57: BANCO | C57: VALOR | D57: FECHA CONSIGNACION | E57: FECHA ENVIO
A58: Enero | E58: =D58 -> 0
A59: Febrero | E59: =D59 -> 0
A60: Marzo | E60: =D60 -> 0
A61: Abril | E61: =D61 -> 0
A62: Mayo | E62: =D62 -> 0
A63: Junio | E63: =D63 -> 0
A64: Julio | E64: =D64 -> 0
A65: Agosto | E65: =D65 -> 0
A66: Septiembre | E66: =D66 -> 0
A67: Octubre | E67: =D67 -> 0
A68: Noviembre | E68: =D68 -> 0
A69: Diciembre | E69: =D69 -> 0
A71: AÑO 2024
A72: MES | B72: BANCO | C72: VALOR | D72: FECHA CONSIGNACION | E72: FECHA ENVIO
A73: Enero | E73: =D73 -> 0
A74: Febrero | E74: =D74 -> 0
A75: Marzo | E75: =D75 -> 0
A76: Abril | E76: =D76 -> 0
A77: Mayo | E77: =D77 -> 0
A78: Junio | E78: =D78 -> 0
A79: Julio | E79: =D79 -> 0
A80: Agosto | E80: =D80 -> 0
A81: Septiembre | E81: =D81 -> 0
A82: Octubre | E82: =D82 -> 0
A83: Noviembre | E83: =D83 -> 0
A84: Diciembre | E84: =D84 -> 0
A86: AÑO 2025
A87: MES | B87: BANCO | C87: VALOR | D87: FECHA CONSIGNACION | E87: FECHA ENVIO
A88: Enero | E88: =D88 -> 0
A89: Febrero | E89: =D89 -> 0
A90: Marzo | E90: =D90 -> 0
A91: Abril | E91: =D91 -> 0
A92: Mayo | E92: =D92 -> 0
A93: Junio | E93: =D93 -> 0
A94: Julio | E94: =D94 -> 0
A95: Agosto | E95: =D95 -> 0
A96: Septiembre | E96: =D96 -> 0
A97: Octubre | E97: =D97 -> 0
A98: Noviembre | E98: =D98 -> 0
A99: Diciembre | E99: =D99 -> 0

Sheet Retefuente
A1: ÚLTIMO DÍGITO CC | C1: 9
A4: 2019
A5: MES | C5: BANCO | D5: VALOR | E5: FECHA CONSIGNACION | F5: FECHA PAGO SEGÚN CALENDARIO TRIBUTARIO | G5: DIAS INCUMPLIDOS
A6: Julio | B6: =CONCATENATE(A6,$C$1) -> Julio9 | F6: =VLOOKUP(B6,'Calendario Tributario'!$D$3:$K$122,3,0) -> 43689 | G6: =IF(E6-F6>0,E6-F6,0) -> 0 | H6: =IF(AND(EOMONTH(DATE($A$4,MONTH("1-"&A6&"-"&$A$4),1),0)>=Generales!$B$4,DATE($A$4,MONTH("1-"&A6&"-"&$A$4),1)<=Generales!$C$4),"","FUERA DE RANGO") -> FUERA DE RANGO
A7: Agosto | B7: =CONCATENATE(A7,$C$1) -> Agosto9 | F7: =VLOOKUP(B7,'Calendario Tributario'!$D$3:$K$122,3,0) -> 43719 | G7: =IF(E7-F7>0,E7-F7,0) -> 0 | H7: =IF(AND(EOMONTH(DATE($A$4,MONTH("1-"&A7&"-"&$A$4),1),0)>=Generales!$B$4,DATE($A$4,MONTH("1-"&A7&"-"&$A$4),1)<=Generales!$C$4),"","FUERA DE RANGO") -> FUERA DE RANGO
A8: Septiembre | B8: =CONCATENATE(A8,$C$1) -> Septiembre9 | F8: =VLOOKUP(B8,'Calendario Tributario'!$D$3:$K$122,3,0) -> 43747 | G8: =IF(E8-F8>0,E8-F8,0) -> 0 | H8: =IF(AND(EOMONTH(DATE($A$4,MONTH("1-"&A8&"-"&$A$4),1),0)>=Generales!$B$4,DATE($A$4,MONTH("1-"&A8&"-"&$A$4),1)<=Generales!$C$4),"","FUERA DE RANGO") -> FUERA DE RANGO
A9: Octubre | B9: =CONCATENATE(A9,$C$1) -> Octubre9 | F9: =VLOOKUP(B9,'Calendario Tributario'!$D$3:$K$122,3,0) -> 43782 | G9: =IF(E9-F9>0,E9-F9,0) -> 0 | H9: =IF(AND(EOMONTH(DATE($A$4,MONTH("1-"&A9&"-"&$A$4),1),0)>=Generales!$B$4,DATE($A$4,MONTH("1-"&A9&"-"&$A$4),1)<=Generales!$C$4),"","FUERA DE RANGO") -> FUERA DE RANGO
A10: Noviembre | B10: =CONCATENATE(A10,$C$1) -> Noviembre9 | F10: =VLOOKUP(B10,'Calendario Tributario'!$D$3:$K$122,3,0) -> 43810 | G10: =IF(E10-F10>0,E10-F10,0) -> 0 | H10: =IF(AND(EOMONTH(DATE($A$4,MONTH("1-"&A10&"-"&$A$4),1),0)>=Generales!$B$4,DATE($A$4,MONTH("1-"&A10&"-"&$A$4),1)<=Generales!$C$4),"","FUERA DE RANGO") -> FUERA DE RANGO
A11: Diciembre | B11: =CONCATENATE(A11,$C$1) -> Diciembre9 | F11: =VLOOKUP(B11,'Calendario Tributario'!$D$3:$K$122,3,0) -> 43843 | G11: =IF(E11-F11>0,E11-F11,0) -> 0 | H11: =IF(AND(EOMONTH(DATE($A$4,MONTH("1-"&A11&"-"&$A$4),1),0)>=Generales!$B$4,DATE($A$4,MONTH("1-"&A11&"-"&$A$4),1)<=Generales!$C$4),"","FUERA DE RANGO") -> FUERA DE RANGO
A13: 2020
A14: MES | C14: BANCO | D14: VALOR | E14: FECHA CONSIGNACION | F14: FECHA PAGO SEGÚN CALENDARIO TRIBUTARIO | G14: DIAS INCUMPLIDOS
A15: Enero | B15: =CONCATENATE(A15,$C$1) -> Enero9 | F15: =VLOOKUP(B15,'Calendario Tributario'!$D$3:$K$122,4,0) -> 43873 | G15: =IF(E15-F15>0,E15-F15,0) -> 0 | H15: =IF(AND(EOMONTH(DATE($A$13,MONTH("1-"&A15&"-"&$A$13),1),0)>=Generales!$B$4,DATE($A$13,MONTH("1-"&A15&"-"&$A$13),1)<=Generales!$C$4),"","FUERA DE RANGO") -> FUERA DE RANGO
A16: Febrero | B16: =CONCATENATE(A16,$C$1) -> Febrero9 | F16: =VLOOKUP(B16,'Calendario Tributario'!$D$3:$K$122,4,0) -> 43901 | G16: =IF(E16-F16<0,0,E16-F16) -> 0 | H16: =IF(AND(EOMONTH(DATE($A$13,MONTH("1-"&A16&"-"&$A$13),1),0)>=Generales!$B$4,DATE($A$13,MONTH("1-"&A16&"-"&$A$13),1)<=Generales!$C$4),"","FUERA DE RANGO") -> FUERA DE RANGO
A17: Marzo | B17: =CONCATENATE(A17,$C$1) -> Marzo9 | F17: =VLOOKUP(B17,'Calendario Tributario'!$D$3:$K$122,4,0) -> 43936 | G17: =IF(E17-F17<0,0,E17-F17) -> 0 | H17: =IF(AND(EOMONTH(DATE($A$13,MONTH("1-"&A17&"-"&$A$13),1),0)>=Generales!$B$4,DATE($A$13,MONTH("1-"&A17&"-"&$A$13),1)<=Generales!$C$4),"","FUERA DE RANGO") -> FUERA DE RANGO
A18: Abril | B18: =CONCATENATE(A18,$C$1) -> Abril9 | F18: =VLOOKUP(B18,'Calendario Tributario'!$D$3:$K$122,4,0) -> 43964 | G18: =IF(E18-F18<0,0,E18-F18) -> 0 | H18: =IF(AND(EOMONTH(DATE($A$13,MONTH("1-"&A18&"-"&$A$13),1),0)>=Generales!$B$4,DATE($A$13,MONTH("1-"&A18&"-"&$A$13),1)<=Generales!$C$4),"","FUERA DE RANGO") -> FUERA DE RANGO
A19: Mayo | B19: =CONCATENATE(A19,$C$1) -> Mayo9 | F19: =VLOOKUP(B19,'Calendario Tributario'!$D$3:$K$122,4,0) -> 43992 | G19: =IF(E19-F19<0,0,E19-F19) -> 0 | H19: =IF(AND(EOMONTH(DATE($A$13,MONTH("1-"&A19&"-"&$A$13),1),0)>=Generales!$B$4,DATE($A$13,MONTH("1-"&A19&"-"&$A$13),1)<=Generales!$C$4),"","FUERA DE RANGO") -> FUERA DE RANGO
A20: Junio | B20: =CONCATENATE(A20,$C$1) -> Junio9 | F20: =VLOOKUP(B20,'Calendario Tributario'!$D$3:$K$122,4,0) -> 44020 | G20: =IF(E20-F20<0,0,E20-F20) -> 0 | H20: =IF(AND(EOMONTH(DATE($A$13,MONTH("1-"&A20&"-"&$A$13),1),0)>=Generales!$B$4,DATE($A$13,MONTH("1-"&A20&"-"&$A$13),1)<=Generales!$C$4),"","FUERA DE RANGO") -> FUERA DE RANGO
A21: Julio | B21: =CONCATENATE(A21,$C$1) -> Julio9 | F21: =VLOOKUP(B21,'Calendario Tributario'!$D$3:$K$122,4,0) -> 44055 | G21: =IF(E21-F21<0,0,E21-F21) -> 0 | H21: =IF(AND(EOMONTH(DATE($A$13,MONTH("1-"&A21&"-"&$A$13),1),0)>=Generales!$B$4,DATE($A$13,MONTH("1-"&A21&"-"&$A$13),1)<=Generales!$C$4),"","FUERA DE RANGO") -> FUERA DE RANGO
A22: Agosto | B22: =CONCATENATE(A22,$C$1) -> Agosto9 | F22: =VLOOKUP(B22,'Calendario Tributario'!$D$3:$K$122,4,0) -> 44083 | G22: =IF(E22-F22<0,0,E22-F22) -> 0 | H22: =IF(AND(EOMONTH(DATE($A$13,MONTH("1-"&A22&"-"&$A$13),1),0)>=Generales!$B$4,DATE($A$13,MONTH("1-"&A22&"-"&$A$13),1)<=Generales!$C$4),"","FUERA DE RANGO") -> FUERA DE RANGO
A23: Septiembre | B23: =CONCATENATE(A23,$C$1) -> Septiembre9 | F23: =VLOOKUP(B23,'Calendario Tributario'!$D$3:$K$122,4,0) -> 44111 | G23: =IF(E23-F23<0,0,E23-F23) -> 0 | H23: =IF(AND(EOMONTH(DATE($A$13,MONTH("1-"&A23&"-"&$A$13),1),0)>=Generales!$B$4,DATE($A$13,MONTH("1-"&A23&"-"&$A$13),1)<=Generales!$C$4),"","FUERA DE RANGO") -> FUERA DE RANGO
A24: Octubre | B24: =CONCATENATE(A24,$C$1) -> Octubre9 | F24: =VLOOKUP(B24,'Calendario Tributario'!$D$3:$K$122,4,0) -> 44146 | G24: =IF(E24-F24<0,0,E24-F24) -> 0 | H24: =IF(AND(EOMONTH(DATE($A$13,MONTH("1-"&A24&"-"&$A$13),1),0)>=Generales!$B$4,DATE($A$13,MONTH("1-"&A24&"-"&$A$13),1)<=Generales!$C$4),"","FUERA DE RANGO") -> FUERA DE RANGO
A25: Noviembre | B25: =CONCATENATE(A25,$C$1) -> Noviembre9 | F25: =VLOOKUP(B25,'Calendario Tributario'!$D$3:$K$122,4,0) -> 44176 | G25: =IF(E25-F25<0,0,E25-F25) -> 0 | H25: =IF(AND(EOMONTH(DATE($A$13,MONTH("1-"&A25&"-"&$A$13),1),0)>=Generales!$B$4,DATE($A$13,MONTH("1-"&A25&"-"&$A$13),1)<=Generales!$C$4),"","FUERA DE RANGO") -> FUERA DE RANGO
A26: Diciembre | B26: =CONCATENATE(A26,$C$1) -> Diciembre9 | F26: =VLOOKUP(B26,'Calendario Tributario'!$D$3:$K$122,4,0) -> 44210 | G26: =IF(E26-F26<0,0,E26-F26) -> 0 | H26: =IF(AND(EOMONTH(DATE($A$13,MONTH("1-"&A26&"-"&$A$13),1),0)>=Generales!$B$4,DATE($A$13,MONTH("1-"&A26&"-"&$A$13),1)<=Generales!$C$4),"","FUERA DE RANGO") -> FUERA DE RANGO
A28: 2021
A29: MES | C29: BANCO | D29: VALOR | E29: FECHA CONSIGNACION | F29: FECHA PAGO SEGÚN CALENDARIO TRIBUTARIO | G29: DIAS INCUMPLIDOS
A30: Enero | B30: =CONCATENATE(A30,$C$1) -> Enero9 | F30: =VLOOKUP(B30,'Calendario Tributario'!$D$3:$K$122,5,0) -> 44246 | G30: =IF(E30-F30<0,0,E30-F30) -> 0 | H30: =IF(AND(EOMONTH(DATE($A$28,MONTH("1-"&A30&"-"&$A$28),1),0)>=Generales!$B$4,DATE($A$28,MONTH("1-"&A30&"-"&$A$28),1)<=Generales!$C$4),"","FUERA DE RANGO") -> FUERA DE RANGO
A31: Febrero | B31: =CONCATENATE(A31,$C$1) -> Febrero9 | F31: =VLOOKUP(B31,'Calendario Tributario'!$D$3:$K$122,5,0) -> 44274 | G31: =IF(E31-F31<0,0,E31-F31) -> 0 | H31: =IF(AND(EOMONTH(DATE($A$28,MONTH("1-"&A31&"-"&$A$28),1),0)>=Generales!$B$4,DATE($A$28,MONTH("1-"&A31&"-"&$A$28),1)<=Generales!$C$4),"","FUERA DE RANGO") -> FUERA DE RANGO
A32: Marzo | B32: =CONCATENATE(A32,$C$1) -> Marzo9 | F32: =VLOOKUP(B32,'Calendario Tributario'!$D$3:$K$122,5,0) -> 44308 | G32: =IF(E32-F32<0,0,E32-F32) -> 0 | H32: =IF(AND(EOMONTH(DATE($A$28,MONTH("1-"&A32&"-"&$A$28),1),0)>=Generales!$B$4,DATE($A$28,MONTH("1-"&A32&"-"&$A$28),1)<=Generales!$C$4),"","FUERA DE RANGO") -> FUERA DE RANGO
A33: Abril | B33: =CONCATENATE(A33,$C$1) -> Abril9 | F33: =VLOOKUP(B33,'Calendario Tributario'!$D$3:$K$122,5,0) -> 44337 | G33: =IF(E33-F33<0,0,E33-F33) -> 0 | H33: =IF(AND(EOMONTH(DATE($A$28,MONTH("1-"&A33&"-"&$A$28),1),0)>=Generales!$B$4,DATE($A$28,MONTH("1-"&A33&"-"&$A$28),1)<=Generales!$C$4),"","FUERA DE RANGO") -> FUERA DE RANGO
A34: Mayo | B34: =CONCATENATE(A34,$C$1) -> Mayo9 | F34: =VLOOKUP(B34,'Calendario Tributario'!$D$3:$K$122,5,0) -> 44369 | G34: =IF(E34-F34<0,0,E34-F34) -> 0 | H34: =IF(AND(EOMONTH(DATE($A$28,MONTH("1-"&A34&"-"&$A$28),1),0)>=Generales!$B$4,DATE($A$28,MONTH("1-"&A34&"-"&$A$28),1)<=Generales!$C$4),"","FUERA DE RANGO") -> FUERA DE RANGO
A35: Junio | B35: =CONCATENATE(A35,$C$1) -> Junio9 | F35: =VLOOKUP(B35,'Calendario Tributario'!$D$3:$K$122,5,0) -> 44398 | G35: =IF(E35-F35<0,0,E35-F35) -> 0 | H35: =IF(AND(EOMONTH(DATE($A$28,MONTH("1-"&A35&"-"&$A$28),1),0)>=Generales!$B$4,DATE($A$28,MONTH("1-"&A35&"-"&$A$28),1)<=Generales!$C$4),"","FUERA DE RANGO") -> FUERA DE RANGO
A36: Julio | B36: =CONCATENATE(A36,$C$1) -> Julio9 | F36: =VLOOKUP(B36,'Calendario Tributario'!$D$3:$K$122,5,0) -> 44431 | G36: =IF(E36-F36<0,0,E36-F36) -> 0 | H36: =IF(AND(EOMONTH(DATE($A$28,MONTH("1-"&A36&"-"&$A$28),1),0)>=Generales!$B$4,DATE($A$28,MONTH("1-"&A36&"-"&$A$28),1)<=Generales!$C$4),"","FUERA DE RANGO") -> FUERA DE RANGO
A37: Agosto | B37: =CONCATENATE(A37,$C$1) -> Agosto9 | F37: =VLOOKUP(B37,'Calendario Tributario'!$D$3:$K$122,5,0) -> 44459 | G37: =IF(E37-F37<0,0,E37-F37) -> 0 | H37: =IF(AND(EOMONTH(DATE($A$28,MONTH("1-"&A37&"-"&$A$28),1),0)>=Generales!$B$4,DATE($A$28,MONTH("1-"&A37&"-"&$A$28),1)<=Generales!$C$4),"","FUERA DE RANGO") -> FUERA DE RANGO
A38: Septiembre | B38: =CONCATENATE(A38,$C$1) -> Septiembre9 | F38: =VLOOKUP(B38,'Calendario Tributario'!$D$3:$K$122,5,0) -> 44489 | G38: =IF(E38-F38<0,0,E38-F38) -> 0 | H38: =IF(AND(EOMONTH(DATE($A$28,MONTH("1-"&A38&"-"&$A$28),1),0)>=Generales!$B$4,DATE($A$28,MONTH("1-"&A38&"-"&$A$28),1)<=Generales!$C$4),"","FUERA DE RANGO") -> FUERA DE RANGO
A39: Octubre | B39: =CONCATENATE(A39,$C$1) -> Octubre9 | F39: =VLOOKUP(B39,'Calendario Tributario'!$D$3:$K$122,5,0) -> 44522 | G39: =IF(E39-F39<0,0,E39-F39) -> 0 | H39: =IF(AND(EOMONTH(DATE($A$28,MONTH("1-"&A39&"-"&$A$28),1),0)>=Generales!$B$4,DATE($A$28,MONTH("1-"&A39&"-"&$A$28),1)<=Generales!$C$4),"","FUERA DE RANGO") -> FUERA DE RANGO
A40: Noviembre | B40: =CONCATENATE(A40,$C$1) -> Noviembre9 | F40: =VLOOKUP(B40,'Calendario Tributario'!$D$3:$K$122,5,0) -> 44552 | G40: =IF(E40-F40<0,0,E40-F40) -> 0 | H40: =IF(AND(EOMONTH(DATE($A$28,MONTH("1-"&A40&"-"&$A$28),1),0)>=Generales!$B$4,DATE($A$28,MONTH("1-"&A40&"-"&$A$28),1)<=Generales!$C$4),"","FUERA DE RANGO") -> FUERA DE RANGO
A41: Diciembre | B41: =CONCATENATE(A41,$C$1) -> Diciembre9 | F41: =VLOOKUP(B41,'Calendario Tributario'!$D$3:$K$122,5,0) -> 44585 | G41: =IF(E41-F41<0,0,E41-F41) -> 0 | H41: =IF(AND(EOMONTH(DATE($A$28,MONTH("1-"&A41&"-"&$A$28),1),0)>=Generales!$B$4,DATE($A$28,MONTH("1-"&A41&"-"&$A$28),1)<=Generales!$C$4),"","FUERA DE RANGO") -> FUERA DE RANGO
A43: 2022
A44: MES | C44: BANCO | D44: VALOR | E44: FECHA CONSIGNACION | F44: FECHA PAGO SEGÚN CALENDARIO TRIBUTARIO | G44: DIAS INCUMPLIDOS
A45: Enero | B45: =CONCATENATE(A45,$C$1) -> Enero9 | F45: =VLOOKUP(B45,'Calendario Tributario'!$D$3:$K$122,6,0) -> 44610 | G45: =IF(E45-F45<0,0,E45-F45) -> 0 | H45: =IF(AND(EOMONTH(DATE($A$43,MONTH("1-"&A45&"-"&$A$43),1),0)>=Generales!$B$4,DATE($A$43,MONTH("1-"&A45&"-"&$A$43),1)<=Generales!$C$4),"","FUERA DE RANGO") -> FUERA DE RANGO
A46: Febrero | B46: =CONCATENATE(A46,$C$1) -> Febrero9 | F46: =VLOOKUP(B46,'Calendario Tributario'!$D$3:$K$122,6,0) -> 44638 | G46: =IF(E46-F46<0,0,E46-F46) -> 0 | H46: =IF(AND(EOMONTH(DATE($A$43,MONTH("1-"&A46&"-"&$A$43),1),0)>=Generales!$B$4,DATE($A$43,MONTH("1-"&A46&"-"&$A$43),1)<=Generales!$C$4),"","FUERA DE RANGO") -> FUERA DE RANGO
A47: Marzo | B47: =CONCATENATE(A47,$C$1) -> Marzo9 | F47: =VLOOKUP(B47,'Calendario Tributario'!$D$3:$K$122,6,0) -> 44672 | G47: =IF(E47-F47<0,0,E47-F47) -> 0 | H47: =IF(AND(EOMONTH(DATE($A$43,MONTH("1-"&A47&"-"&$A$43),1),0)>=Generales!$B$4,DATE($A$43,MONTH("1-"&A47&"-"&$A$43),1)<=Generales!$C$4),"","FUERA DE RANGO") -> FUERA DE RANGO
A48: Abril | B48: =CONCATENATE(A48,$C$1) -> Abril9 | F48: =VLOOKUP(B48,'Calendario Tributario'!$D$3:$K$122,6,0) -> 44701 | G48: =IF(E48-F48<0,0,E48-F48) -> 0 | H48: =IF(AND(EOMONTH(DATE($A$43,MONTH("1-"&A48&"-"&$A$43),1),0)>=Generales!$B$4,DATE($A$43,MONTH("1-"&A48&"-"&$A$43),1)<=Generales!$C$4),"","FUERA DE RANGO") -> FUERA DE RANGO
A49: Mayo | B49: =CONCATENATE(A49,$C$1) -> Mayo9 | F49: =VLOOKUP(B49,'Calendario Tributario'!$D$3:$K$122,6,0) -> 44729 | G49: =IF(E49-F49<0,0,E49-F49) -> 0 | H49: =IF(AND(EOMONTH(DATE($A$43,MONTH("1-"&A49&"-"&$A$43),1),0)>=Generales!$B$4,DATE($A$43,MONTH("1-"&A49&"-"&$A$43),1)<=Generales!$C$4),"","FUERA DE RANGO") -> FUERA DE RANGO
A50: Junio | B50: =CONCATENATE(A50,$C$1) -> Junio9 | F50: =VLOOKUP(B50,'Calendario Tributario'!$D$3:$K$122,6,0) -> 44763 | G50: =IF(E50-F50<0,0,E50-F50) -> 0 | H50: =IF(AND(EOMONTH(DATE($A$43,MONTH("1-"&A50&"-"&$A$43),1),0)>=Generales!$B$4,DATE($A$43,MONTH("1-"&A50&"-"&$A$43),1)<=Generales!$C$4),"","FUERA DE RANGO") -> FUERA DE RANGO
A51: Julio | B51: =CONCATENATE(A51,$C$1) -> Julio9 | F51: =VLOOKUP(B51,'Calendario Tributario'!$D$3:$K$122,6,0) -> 44795 | G51: =IF(E51-F51<0,0,E51-F51) -> 0 | H51: =IF(AND(EOMONTH(DATE($A$43,MONTH("1-"&A51&"-"&$A$43),1),0)>=Generales!$B$4,DATE($A$43,MONTH("1-"&A51&"-"&$A$43),1)<=Generales!$C$4),"","FUERA DE RANGO") -> FUERA DE RANGO
A52: Agosto | B52: =CONCATENATE(A52,$C$1) -> Agosto9 | F52: =VLOOKUP(B52,'Calendario Tributario'!$D$3:$K$122,6,0) -> 44823 | G52: =IF(E52-F52<0,0,E52-F52) -> 0 | H52: =IF(AND(EOMONTH(DATE($A$43,MONTH("1-"&A52&"-"&$A$43),1),0)>=Generales!$B$4,DATE($A$43,MONTH("1-"&A52&"-"&$A$43),1)<=Generales!$C$4),"","FUERA DE RANGO") -> FUERA DE RANGO
A53: Septiembre | B53: =CONCATENATE(A53,$C$1) -> Septiembre9 | F53: =VLOOKUP(B53,'Calendario Tributario'!$D$3:$K$122,6,0) -> 44854 | G53: =IF(E53-F53<0,0,E53-F53) -> 0 | H53: =IF(AND(EOMONTH(DATE($A$43,MONTH("1-"&A53&"-"&$A$43),1),0)>=Generales!$B$4,DATE($A$43,MONTH("1-"&A53&"-"&$A$43),1)<=Generales!$C$4),"","FUERA DE RANGO") -> FUERA DE RANGO
A54: Octubre | B54: =CONCATENATE(A54,$C$1) -> Octubre9 | F54: =VLOOKUP(B54,'Calendario Tributario'!$D$3:$K$122,6,0) -> 44887 | G54: =IF(E54-F54<0,0,E54-F54) -> 0
A55: Noviembre | B55: =CONCATENATE(A55,$C$1) -> Noviembre9 | F55: =VLOOKUP(B55,'Calendario Tributario'!$D$3:$K$122,6,0) -> 44917 | G55: =IF(E55-F55<0,0,E55-F55) -> 0
A56: Diciembre | B56: =CONCATENATE(A56,$C$1) -> Diciembre9 | F56: =VLOOKUP(B56,'Calendario Tributario'!$D$3:$K$122,6,0) -> 44949 | G56: =IF(E56-F56<0,0,E56-F56) -> 0
A58: 2023
A59: MES | C59: BANCO | D59: VALOR | E59: FECHA CONSIGNACION | F59: FECHA PAGO SEGÚN CALENDARIO TRIBUTARIO | G59: DIAS INCUMPLIDOS
A60: Enero | B60: =CONCATENATE(A60,$C$1) -> Enero9 | F60: =VLOOKUP(B60,'Calendario Tributario'!$D$3:$K$122,7,0) -> 44974 | G60: =IF(E60-F60<0,0,E60-F60) -> 0
A61: Febrero | B61: =CONCATENATE(A61,$C$1) -> Febrero9 | F61: =VLOOKUP(B61,'Calendario Tributario'!$D$3:$K$122,7,0) -> 45002 | G61: =IF(E61-F61<0,0,E61-F61) -> 0
A62: Marzo | B62: =CONCATENATE(A62,$C$1) -> Marzo9 | F62: =VLOOKUP(B62,'Calendario Tributario'!$D$3:$K$122,7,0) -> 45036 | G62: =IF(E62-F62<0,0,E62-F62) -> 0
A63: Abril | B63: =CONCATENATE(A63,$C$1) -> Abril9 | F63: =VLOOKUP(B63,'Calendario Tributario'!$D$3:$K$122,7,0) -> 45065 | G63: =IF(E63-F63<0,0,E63-F63) -> 0
A64: Mayo | B64: =CONCATENATE(A64,$C$1) -> Mayo9 | F64: =VLOOKUP(B64,'Calendario Tributario'!$D$3:$K$122,7,0) -> 45098 | G64: =IF(E64-F64<0,0,E64-F64) -> 0
A65: Junio | B65: =CONCATENATE(A65,$C$1) -> Junio9 | F65: =VLOOKUP(B65,'Calendario Tributario'!$D$3:$K$122,7,0) -> 45126 | G65: =IF(E65-F65<0,0,E65-F65) -> 0
A66: Julio | B66: =CONCATENATE(A66,$C$1) -> Julio9 | F66: =VLOOKUP(B66,'Calendario Tributario'!$D$3:$K$122,7,0) -> 45160 | G66: =IF(E66-F66<0,0,E66-F66) -> 0
A67: Agosto | B67: =CONCATENATE(A67,$C$1) -> Agosto9 | F67: =VLOOKUP(B67,'Calendario Tributario'!$D$3:$K$122,7,0) -> 45188 | G67: =IF(E67-F67<0,0,E67-F67) -> 0
A68: Septiembre | B68: =CONCATENATE(A68,$C$1) -> Septiembre9 | F68: =VLOOKUP(B68,'Calendario Tributario'!$D$3:$K$122,7,0) -> 45222 | G68: =IF(E68-F68<0,0,E68-F68) -> 0
A69: Octubre | B69: =CONCATENATE(A69,$C$1) -> Octubre9 | F69: =VLOOKUP(B69,'Calendario Tributario'!$D$3:$K$122,7,0) -> 45251 | G69: =IF(E69-F69<0,0,E69-F69) -> 0
A70: Noviembre | B70: =CONCATENATE(A70,$C$1) -> Noviembre9 | F70: =VLOOKUP(B70,'Calendario Tributario'!$D$3:$K$122,7,0) -> 45281 | G70: =IF(E70-F70<0,0,E70-F70) -> 0
A71: Diciembre | B71: =CONCATENATE(A71,$C$1) -> Diciembre9 | F71: =VLOOKUP(B71,'Calendario Tributario'!$D$3:$K$122,7,0) -> 45313 | G71: =IF(E71-F71<0,0,E71-F71) -> 0
A73: 2024
A74: MES | C74: BANCO | D74: VALOR | E74: FECHA CONSIGNACION | F74: FECHA PAGO SEGÚN CALENDARIO TRIBUTARIO | G74: DIAS INCUMPLIDOS
A75: Enero | B75: =CONCATENATE(A75,$C$1) -> Enero9 | F75: =VLOOKUP(B75,'Calendario Tributario'!$D$3:$K$122,8,0) -> 45343 | G75: =IF(E75-F75<0,0,E75-F75) -> 0
A76: Febrero | B76: =CONCATENATE(A76,$C$1) -> Febrero9 | F76: =VLOOKUP(B76,'Calendario Tributario'!$D$3:$K$122,8,0) -> 45372 | G76: =IF(E76-F76<0,0,E76-F76) -> 0 | H76: =IF(AND(EOMONTH(DATE($A$73,MONTH("1-"&A76&"-"&$A$73),1),0)>=Generales!$B$4,DATE($A$73,MONTH("1-"&A76&"-"&$A$73),1)<=Generales!$C$4),"","FUERA DE RANGO") -> FUERA DE RANGO
A77: Marzo | B77: =CONCATENATE(A77,$C$1) -> Marzo9 | F77: =VLOOKUP(B77,'Calendario Tributario'!$D$3:$K$122,8,0) -> 45401 | G77: =IF(E77-F77<0,0,E77-F77) -> 0 | H77: =IF(AND(EOMONTH(DATE($A$73,MONTH("1-"&A77&"-"&$A$73),1),0)>=Generales!$B$4,DATE($A$73,MONTH("1-"&A77&"-"&$A$73),1)<=Generales!$C$4),"","FUERA DE RANGO") -> FUERA DE RANGO
A78: Abril | B78: =CONCATENATE(A78,$C$1) -> Abril9 | F78: =VLOOKUP(B78,'Calendario Tributario'!$D$3:$K$122,8,0) -> 45435 | G78: =IF(E78-F78<0,0,E78-F78) -> 0 | H78: =IF(AND(EOMONTH(DATE($A$73,MONTH("1-"&A78&"-"&$A$73),1),0)>=Generales!$B$4,DATE($A$73,MONTH("1-"&A78&"-"&$A$73),1)<=Generales!$C$4),"","FUERA DE RANGO") -> FUERA DE RANGO
A79: Mayo | B79: =CONCATENATE(A79,$C$1) -> Mayo9 | F79: =VLOOKUP(B79,'Calendario Tributario'!$D$3:$K$122,8,0) -> 45468 | G79: =IF(E79-F79<0,0,E79-F79) -> 0
A80: Junio | B80: =CONCATENATE(A80,$C$1) -> Junio9 | F80: =VLOOKUP(B80,'Calendario Tributario'!$D$3:$K$122,8,0) -> 45495 | G80: =IF(E80-F80<0,0,E80-F80) -> 0 | H80: =IF(AND(EOMONTH(DATE($A$73,MONTH("1-"&A80&"-"&$A$73),1),0)>=Generales!$B$4,DATE($A$73,MONTH("1-"&A80&"-"&$A$73),1)<=Generales!$C$4),"","FUERA DE RANGO") -> FUERA DE RANGO
A81: Julio | B81: =CONCATENATE(A81,$C$1) -> Julio9 | F81: =VLOOKUP(B81,'Calendario Tributario'!$D$3:$K$122,8,0) -> 45527 | G81: =IF(E81-F81<0,0,E81-F81) -> 0 | H81: =IF(AND(EOMONTH(DATE($A$73,MONTH("1-"&A81&"-"&$A$73),1),0)>=Generales!$B$4,DATE($A$73,MONTH("1-"&A81&"-"&$A$73),1)<=Generales!$C$4),"","FUERA DE RANGO") -> FUERA DE RANGO
A82: Agosto | B82: =CONCATENATE(A82,$C$1) -> Agosto9 | F82: =VLOOKUP(B82,'Calendario Tributario'!$D$3:$K$122,8,0) -> 45555 | G82: =IF(E82-F82<0,0,E82-F82) -> 0 | H82: =IF(AND(EOMONTH(DATE($A$73,MONTH("1-"&A82&"-"&$A$73),1),0)>=Generales!$B$4,DATE($A$73,MONTH("1-"&A82&"-"&$A$73),1)<=Generales!$C$4),"","FUERA DE RANGO") -> FUERA DE RANGO
A83: Septiembre | B83: =CONCATENATE(A83,$C$1) -> Septiembre9 | F83: =VLOOKUP(B83,'Calendario Tributario'!$D$3:$K$122,8,0) -> 45587 | G83: =IF(E83-F83<0,0,E83-F83) -> 0
A84: Octubre | B84: =CONCATENATE(A84,$C$1) -> Octubre9 | F84: =VLOOKUP(B84,'Calendario Tributario'!$D$3:$K$122,8,0) -> 45621 | G84: =IF(E84-F84<0,0,E84-F84) -> 0 | H84: =IF(AND(EOMONTH(DATE($A$73,MONTH("1-"&A84&"-"&$A$73),1),0)>=Generales!$B$4,DATE($A$73,MONTH("1-"&A84&"-"&$A$73),1)<=Generales!$C$4),"","FUERA DE RANGO") -> FUERA DE RANGO
A85: Noviembre | B85: =CONCATENATE(A85,$C$1) -> Noviembre9 | F85: =VLOOKUP(B85,'Calendario Tributario'!$D$3:$K$122,8,0) -> 45646 | G85: =IF(E85-F85<0,0,E85-F85) -> 0 | H85: =IF(AND(EOMONTH(DATE($A$73,MONTH("1-"&A85&"-"&$A$73),1),0)>=Generales!$B$4,DATE($A$73,MONTH("1-"&A85&"-"&$A$73),1)<=Generales!$C$4),"","FUERA DE RANGO") -> FUERA DE RANGO
A86: Diciembre | B86: =CONCATENATE(A86,$C$1) -> Diciembre9 | F86: =VLOOKUP(B86,'Calendario Tributario'!$D$3:$K$122,8,0) -> 45680 | G86: =IF(E86-F86<0,0,E86-F86) -> 0 | H86: =IF(AND(EOMONTH(DATE($A$73,MONTH("1-"&A86&"-"&$A$73),1),0)>=Generales!$B$4,DATE($A$73,MONTH("1-"&A86&"-"&$A$73),1)<=Generales!$C$4),"","FUERA DE RANGO") -> FUERA DE RANGO
A88: 2025
A89: MES | C89: BANCO | D89: VALOR | E89: FECHA CONSIGNACION | F89: FECHA PAGO SEGÚN CALENDARIO TRIBUTARIO | G89: DIAS INCUMPLIDOS
A90: Enero | B90: =CONCATENATE(A90,$C$1) -> Enero9 | F90: =VLOOKUP(B90,'Calendario Tributario'!$D$3:$L$122,9,0) -> 45709 | G90: =IF(E90-F90<0,0,E90-F90) -> 0 | H90: =IF(AND(EOMONTH(DATE($A$88,MONTH("1-"&A90&"-"&$A$88),1),0)>=Generales!$B$4,DATE($A$88,MONTH("1-"&A90&"-"&$A$88),1)<=Generales!$C$4),"","FUERA DE RANGO") -> FUERA DE RANGO
A91: Febrero | B91: =CONCATENATE(A91,$C$1) -> Febrero9 | F91: =VLOOKUP(B91,'Calendario Tributario'!$D$3:$L$122,9,0) -> 45737 | G91: =IF(E91-F91<0,0,E91-F91) -> 0 | H91: =IF(AND(EOMONTH(DATE($A$88,MONTH("1-"&A91&"-"&$A$88),1),0)>=Generales!$B$4,DATE($A$88,MONTH("1-"&A91&"-"&$A$88),1)<=Generales!$C$4),"","FUERA DE RANGO") -> FUERA DE RANGO
A92: Marzo | B92: =CONCATENATE(A92,$C$1) -> Marzo9 | F92: =VLOOKUP(B92,'Calendario Tributario'!$D$3:$L$122,9,0) -> 45770 | G92: =IF(E92-F92<0,0,E92-F92) -> 0 | H92: =IF(AND(EOMONTH(DATE($A$88,MONTH("1-"&A92&"-"&$A$88),1),0)>=Generales!$B$4,DATE($A$88,MONTH("1-"&A92&"-"&$A$88),1)<=Generales!$C$4),"","FUERA DE RANGO") -> FUERA DE RANGO
A93: Abril | B93: =CONCATENATE(A93,$C$1) -> Abril9 | F93: =VLOOKUP(B93,'Calendario Tributario'!$D$3:$L$122,9,0) -> 45799 | G93: =IF(E93-F93<0,0,E93-F93) -> 0 | H93: =IF(AND(EOMONTH(DATE($A$88,MONTH("1-"&A93&"-"&$A$88),1),0)>=Generales!$B$4,DATE($A$88,MONTH("1-"&A93&"-"&$A$88),1)<=Generales!$C$4),"","FUERA DE RANGO") -> FUERA DE RANGO
A94: Mayo | B94: =CONCATENATE(A94,$C$1) -> Mayo9 | F94: =VLOOKUP(B94,'Calendario Tributario'!$D$3:$L$122,9,0) -> 45832 | G94: =IF(E94-F94<0,0,E94-F94) -> 0 | H94: =IF(AND(EOMONTH(DATE($A$88,MONTH("1-"&A94&"-"&$A$88),1),0)>=Generales!$B$4,DATE($A$88,MONTH("1-"&A94&"-"&$A$88),1)<=Generales!$C$4),"","FUERA DE RANGO") -> FUERA DE RANGO
A95: Junio | B95: =CONCATENATE(A95,$C$1) -> Junio9 | F95: =VLOOKUP(B95,'Calendario Tributario'!$D$3:$L$122,9,0) -> 45859 | G95: =IF(E95-F95<0,0,E95-F95) -> 0 | H95: =IF(AND(EOMONTH(DATE($A$88,MONTH("1-"&A95&"-"&$A$88),1),0)>=Generales!$B$4,DATE($A$88,MONTH("1-"&A95&"-"&$A$88),1)<=Generales!$C$4),"","FUERA DE RANGO") -> FUERA DE RANGO
A96: Julio | B96: =CONCATENATE(A96,$C$1) -> Julio9 | F96: =VLOOKUP(B96,'Calendario Tributario'!$D$3:$L$122,9,0) -> 45894 | G96: =IF(E96-F96<0,0,E96-F96) -> 0 | H96: =IF(AND(EOMONTH(DATE($A$88,MONTH("1-"&A96&"-"&$A$88),1),0)>=Generales!$B$4,DATE($A$88,MONTH("1-"&A96&"-"&$A$88),1)<=Generales!$C$4),"","FUERA DE RANGO") -> FUERA DE RANGO
A97: Agosto | B97: =CONCATENATE(A97,$C$1) -> Agosto9 | F97: =VLOOKUP(B97,'Calendario Tributario'!$D$3:$L$122,9,0) -> 45919 | G97: =IF(E97-F97<0,0,E97-F97) -> 0 | H97: =IF(AND(EOMONTH(DATE($A$88,MONTH("1-"&A97&"-"&$A$88),1),0)>=Generales!$B$4,DATE($A$88,MONTH("1-"&A97&"-"&$A$88),1)<=Generales!$C$4),"","FUERA DE RANGO") -> FUERA DE RANGO
A98: Septiembre | B98: =CONCATENATE(A98,$C$1) -> Septiembre9 | F98: =VLOOKUP(B98,'Calendario Tributario'!$D$3:$L$122,9,0) -> 45952 | G98: =IF(E98-F98<0,0,E98-F98) -> 0 | H98: =IF(AND(EOMONTH(DATE($A$88,MONTH("1-"&A98&"-"&$A$88),1),0)>=Generales!$B$4,DATE($A$88,MONTH("1-"&A98&"-"&$A$88),1)<=Generales!$C$4),"","FUERA DE RANGO")
A99: Octubre | B99: =CONCATENATE(A99,$C$1) -> Octubre9 | F99: =VLOOKUP(B99,'Calendario Tributario'!$D$3:$L$122,9,0) -> 45986 | G99: =IF(E99-F99<0,0,E99-F99) -> 0 | H99: =IF(AND(EOMONTH(DATE($A$88,MONTH("1-"&A99&"-"&$A$88),1),0)>=Generales!$B$4,DATE($A$88,MONTH("1-"&A99&"-"&$A$88),1)<=Generales!$C$4),"","FUERA DE RANGO")
A100: Noviembre | B100: =CONCATENATE(A100,$C$1) -> Noviembre9 | F100: =VLOOKUP(B100,'Calendario Tributario'!$D$3:$L$122,9,0) -> 46013 | G100: =IF(E100-F100<0,0,E100-F100) -> 0 | H100: =IF(AND(EOMONTH(DATE($A$88,MONTH("1-"&A100&"-"&$A$88),1),0)>=Generales!$B$4,DATE($A$88,MONTH("1-"&A100&"-"&$A$88),1)<=Generales!$C$4),"","FUERA DE RANGO")
A101: Diciembre | B101: =CONCATENATE(A101,$C$1) -> Diciembre9 | F101: =VLOOKUP(B101,'Calendario Tributario'!$D$3:$L$122,9,0) -> 46045 | G101: =IF(E101-F101<0,0,E101-F101) -> 0 | H101: =IF(AND(EOMONTH(DATE($A$88,MONTH("1-"&A101&"-"&$A$88),1),0)>=Generales!$B$4,DATE($A$88,MONTH("1-"&A101&"-"&$A$88),1)<=Generales!$C$4),"","FUERA DE RANGO")

Sheet APORTE ESPE
A1: BANCO | B1: VALOR | C1: FECHA PAGO | D1: FECHA FACTURA | E1: ESCRITURA Y FECHA | F1: ¿Extemporáneo?
C2: 43617 | D2: 43586 | F2: =IF((NETWORKDAYS(D2,C2))>5,"SÍ "&(NETWORKDAYS(D2,C2))&" días","NO") -> SÍ 23 días | H2: Tope entre Privados | I2: 28798900 | J2: Valor Derechos
F3: =IF((NETWORKDAYS(D3,C3))>5,"SÍ "&(NETWORKDAYS(D3,C3))&" días","NO") -> NO | H3: Tope entre Privado - Exento | I3: 4326500 | J3: Valor del Aporte Especial | K3: =K2-I3 -> -4326500
F4: =IF((NETWORKDAYS(D4,C4))>5,"SÍ "&(NETWORKDAYS(D4,C4))&" días","NO") -> NO
F5: =IF((NETWORKDAYS(D5,C5))>5,"SÍ "&(NETWORKDAYS(D5,C5))&" días","NO") -> NO
F6: =IF((NETWORKDAYS(D6,C6))>5,"SÍ "&(NETWORKDAYS(D6,C6))&" días","NO") -> NO
F7: =IF((NETWORKDAYS(D7,C7))>5,"SÍ "&(NETWORKDAYS(D7,C7))&" días","NO") -> NO
F8: =IF((NETWORKDAYS(D8,C8))>5,"SÍ "&(NETWORKDAYS(D8,C8))&" días","NO") -> NO
F9: =IF((NETWORKDAYS(D9,C9))>5,"SÍ "&(NETWORKDAYS(D9,C9))&" días","NO") -> NO
F10: =IF((NETWORKDAYS(D10,C10))>5,"SÍ "&(NETWORKDAYS(D10,C10))&" días","NO") -> NO
A12: AÑO 2020
A13: BANCO | B13: VALOR | C13: FECHA PAGO | D13: FECHA FACTURA | E13: ESCRITURA Y FECHA | F13: ¿Extemporáneo?
F14: =IF((NETWORKDAYS(D14,C14))>5,"SÍ "&(NETWORKDAYS(D14,C14))&" días","NO") -> NO | H14: Tope entre Privados | I14: 29893300 | J14: Valor del Derechos
F15: =IF((NETWORKDAYS(D15,C15))>5,"SÍ "&(NETWORKDAYS(D15,C15))&" días","NO") -> NO | H15: Tope entre Privado - Exento | I15: 4490900 | J15: Valor del Aporte Especial | K15: =K14-I15 -> -4490900
F16: =IF((NETWORKDAYS(D16,C16))>5,"SÍ "&(NETWORKDAYS(D16,C16))&" días","NO") -> NO
F17: =IF((NETWORKDAYS(D17,C17))>5,"SÍ "&(NETWORKDAYS(D17,C17))&" días","NO") -> NO
F18: =IF((NETWORKDAYS(D18,C18))>5,"SÍ "&(NETWORKDAYS(D18,C18))&" días","NO") -> NO
F19: =IF((NETWORKDAYS(D19,C19))>5,"SÍ "&(NETWORKDAYS(D19,C19))&" días","NO") -> NO
F20: =IF((NETWORKDAYS(D20,C20))>5,"SÍ "&(NETWORKDAYS(D20,C20))&" días","NO") -> NO
F21: =IF((NETWORKDAYS(D21,C21))>5,"SÍ "&(NETWORKDAYS(D21,C21))&" días","NO") -> NO
A23: AÑO 2021
A24: BANCO | B24: VALOR | C24: FECHA PAGO | D24: FECHA FACTURA | E24: ESCRITURA Y FECHA | F24: ¿Extemporáneo? | G24: Método | H24: Tope entre Privados | I24: 30374600 | J24: Valor Derechos
F25: =IF((NETWORKDAYS(D25,C25))>5,"SÍ "&(NETWORKDAYS(D25,C25))&" días","NO") -> NO | G25: Se verifica tipo de aporte especial generado (entre privados o privado - exento), se verifica el cálculo del aporte y se verifica la cuantía del acto. | H25: Tope entre Privado - Exento | I25: 4563200 | J25: Valor del Aporte Especial | K25: =K24-I24 -> -30374600
F26: =IF((NETWORKDAYS(D26,C26))>5,"SÍ "&(NETWORKDAYS(D26,C26))&" días","NO") -> NO | G26: *Ingresó el dinero en cartera el 6 de mayo de 2021
F27: =IF((NETWORKDAYS(D27,C27))>5,"SÍ "&(NETWORKDAYS(D27,C27))&" días","NO") -> NO
F28: =IF((NETWORKDAYS(D28,C28))>5,"SÍ "&(NETWORKDAYS(D28,C28))&" días","NO") -> NO
F29: =IF((NETWORKDAYS(D29,C29))>5,"SÍ "&(NETWORKDAYS(D29,C29))&" días","NO") -> NO
F30: =IF((NETWORKDAYS(D30,C30))>5,"SÍ "&(NETWORKDAYS(D30,C30))&" días","NO") -> NO
F31: =IF((NETWORKDAYS(D31,C31))>5,"SÍ "&(NETWORKDAYS(D31,C31))&" días","NO") -> NO
F32: =IF((NETWORKDAYS(D32,C32))>5,"SÍ "&(NETWORKDAYS(D32,C32))&" días","NO") -> NO
A35: AÑO 2022
A36: BANCO | B36: VALOR | C36: FECHA PAGO | D36: FECHA FACTURA | E36: ESCRITURA Y FECHA | F36: ¿Extemporáneo? | H36: Tope entre Privados | I36: 32081700 | J36: Valor Derechos
F37: =IF((NETWORKDAYS(D37,C37))>5,"SÍ "&(NETWORKDAYS(D37,C37))&" días","NO") -> NO | H37: Tope entre Privado - Exento | I37: 4819700 | J37: Valor del Aporte Especial | K37: =K36-I36 -> -32081700
F38: =IF((NETWORKDAYS(D38,C38))>5,"SÍ "&(NETWORKDAYS(D38,C38))&" días","NO") -> NO
F39: =IF((NETWORKDAYS(D39,C39))>5,"SÍ "&(NETWORKDAYS(D39,C39))&" días","NO") -> NO
F40: =IF((NETWORKDAYS(D40,C40))>5,"SÍ "&(NETWORKDAYS(D40,C40))&" días","NO") -> NO
F41: =IF((NETWORKDAYS(D41,C41))>5,"SÍ "&(NETWORKDAYS(D41,C41))&" días","NO") -> NO
F42: =IF((NETWORKDAYS(D42,C42))>5,"SÍ "&(NETWORKDAYS(D42,C42))&" días","NO") -> NO
F43: =IF((NETWORKDAYS(D43,C43))>5,"SÍ "&(NETWORKDAYS(D43,C43))&" días","NO") -> NO
A45: AÑO 2023
A46: BANCO | B46: VALOR | C46: FECHA PAGO | D46: FECHA FACTURA | E46: ESCRITURA Y FECHA | F46: ¿Extemporáneo? | H46: Tope entre Privados | I46: 36290800 | J46: Valor Derechos
F47: =IF((NETWORKDAYS(D47,C47))>5,"SÍ "&(NETWORKDAYS(D47,C47))&" días","NO") -> NO | H47: Tope entre Privado - Exento | I47: 5452000 | J47: Valor del Aporte Especial | K47: =K46-I47 -> -5452000
F48: =IF((NETWORKDAYS(D48,C48))>5,"SÍ "&(NETWORKDAYS(D48,C48))&" días","NO") -> NO
F49: =IF((NETWORKDAYS(D49,C49))>5,"SÍ "&(NETWORKDAYS(D49,C49))&" días","NO") -> NO
F50: =IF((NETWORKDAYS(D50,C50))>5,"SÍ "&(NETWORKDAYS(D50,C50))&" días","NO") -> NO | H50: Liquidación derechos notariales conforme avalúo de 83,662,882,000 y liquidación de impuesto de timbre conforme cuantía de la venta 70, 718,215,000.
F51: =IF((NETWORKDAYS(D51,C51))>5,"SÍ "&(NETWORKDAYS(D51,C51))&" días","NO") -> NO
F52: =IF((NETWORKDAYS(D52,C52))>5,"SÍ "&(NETWORKDAYS(D52,C52))&" días","NO") -> NO
F53: =IF((NETWORKDAYS(D53,C53))>5,"SÍ "&(NETWORKDAYS(D53,C53))&" días","NO") -> NO
A55: AÑO 2024
A56: BANCO | B56: VALOR | C56: FECHA PAGO | D56: FECHA FACTURA | E56: ESCRITURA Y FECHA | F56: ¿Extemporáneo? | H56: Tope entre Privados | I56: 39658600 | J56: Valor Derechos
F57: =IF((NETWORKDAYS(D57,C57))>5,"SÍ "&(NETWORKDAYS(D57,C57))&" días","NO") -> NO | H57: Tope entre Privado - Exento | I57: 5957900 | J57: Valor del Aporte Especial | K57: =K56-I56 -> -39658600
F58: =IF((NETWORKDAYS(D58,C58))>5,"SÍ "&(NETWORKDAYS(D58,C58))&" días","NO") -> NO
F59: =IF((NETWORKDAYS(D59,C59))>5,"SÍ "&(NETWORKDAYS(D59,C59))&" días","NO") -> NO
F60: =IF((NETWORKDAYS(D60,C60))>5,"SÍ "&(NETWORKDAYS(D60,C60))&" días","NO") -> NO
F61: =IF((NETWORKDAYS(D61,C61))>5,"SÍ "&(NETWORKDAYS(D61,C61))&" días","NO") -> NO
F62: =IF((NETWORKDAYS(D62,C62))>5,"SÍ "&(NETWORKDAYS(D62,C62))&" días","NO") -> NO
F63: =IF((NETWORKDAYS(D63,C63))>5,"SÍ "&(NETWORKDAYS(D63,C63))&" días","NO") -> NO
A65: AÑO 2025
A66: BANCO | B66: VALOR | C66: FECHA PAGO | D66: FECHA FACTURA | E66: ESCRITURA Y FECHA | F66: ¿Extemporáneo? | H66: Tope entre Privados | I66: 41720800 | J66: Valor Derechos
F67: =IF((NETWORKDAYS(D67,C67))>5,"SÍ "&(NETWORKDAYS(D67,C67))&" días","NO") -> NO | H67: Tope entre Privado - Exento | I67: 6267700 | J67: Valor del Aporte Especial | K67: =K66-I66 -> -41720800
F68: =IF((NETWORKDAYS(D68,C68))>5,"SÍ "&(NETWORKDAYS(D68,C68))&" días","NO") -> NO
F69: =IF((NETWORKDAYS(D69,C69))>5,"SÍ "&(NETWORKDAYS(D69,C69))&" días","NO") -> NO
F70: =IF((NETWORKDAYS(D70,C70))>5,"SÍ "&(NETWORKDAYS(D70,C70))&" días","NO") -> NO
F71: =IF((NETWORKDAYS(D71,C71))>5,"SÍ "&(NETWORKDAYS(D71,C71))&" días","NO") -> NO
F72: =IF((NETWORKDAYS(D72,C72))>5,"SÍ "&(NETWORKDAYS(D72,C72))&" días","NO") -> NO
F73: =IF((NETWORKDAYS(D73,C73))>5,"SÍ "&(NETWORKDAYS(D73,C73))&" días","NO") -> NO

Sheet IVA - Bimestral
A1: AÑO 2019
A2: BIMESTRAL | B2: BANCO | C2: VALOR | D2: FECHA CONSIGNACION | E2: FECHA DE PRESENTACION DIAN | F2: DIAS INCUMPLIDOS
A3: Enero - Febrero | F3: =IF(D3-E3>0,D3-E3,0) -> 0
A4: Marzo - Abril | F4: =IF(D4-E4>0,D4-E4,0) -> 0
A5: Mayo - Junio | F5: =IF(D5-E5>0,D5-E5,0) -> 0
A6: Julio .- Agosto | E6: =Retefuente!F7 -> 43719 | F6: =IF(D6-E6>0,D6-E6,0) -> 0
A7: Septiembre - Octubre | E7: =Retefuente!F9 -> 43782 | F7: =IF(D7-E7>0,D7-E7,0) -> 0
A8: Noviembre - Diciembre | E8: =Retefuente!F11 -> 43843 | F8: =IF(D8-E8>0,D8-E8,0) -> 0
A10: AÑO 2020
A11: BIMESTRAL | B11: BANCO | C11: VALOR | D11: FECHA CONSIGNACION | E11: FECHA DE PRESENTACION DIAN | F11: DIAS INCUMPLIDOS
A12: Enero - Febrero | E12: =Retefuente!F16 -> 43901 | F12: =IF(D12-E12>0,D12-E12,0) -> 0
A13: Marzo - Abril | E13: =Retefuente!F18 -> 43964 | F13: =IF(D13-E13>0,D13-E13,0) -> 0
A14: Mayo - Junio | E14: =Retefuente!F20 -> 44020 | F14: =IF(D14-E14>0,D14-E14,0) -> 0
A15: Julio .- Agosto | E15: =Retefuente!F22 -> 44083 | F15: =IF(D15-E15>0,D15-E15,0) -> 0
A16: Septiembre - Octubre | E16: =Retefuente!F24 -> 44146 | F16: =IF(D16-E16>0,D16-E16,0) -> 0
A17: Noviembre - Diciembre | E17: =Retefuente!F26 -> 44210 | F17: =IF(D17-E17>0,D17-E17,0) -> 0
A19: AÑO 2021
A20: BIMESTRAL | B20: BANCO | C20: VALOR | D20: FECHA CONSIGNACION | E20: FECHA DE PRESENTACION DIAN | F20: DIAS INCUMPLIDOS
A21: Enero - Febrero | E21: =Retefuente!F31 -> 44274 | F21: =IF(D21-E21>0,D21-E21,0) -> 0
A22: Marzo - Abril | E22: =Retefuente!F33 -> 44337 | F22: =IF(D22-E22>0,D22-E22,0) -> 0
A23: Mayo - Junio | E23: =Retefuente!F35 -> 44398 | F23: =IF(D23-E23>0,D23-E23,0) -> 0
A24: Julio .- Agosto | E24: =Retefuente!F37 -> 44459 | F24: =IF(D24-E24>0,D24-E24,0) -> 0
A25: Septiembre - Octubre | E25: =Retefuente!F39 -> 44522 | F25: =IF(D25-E25>0,D25-E25,0) -> 0
A26: Noviembre - Diciembre | E26: =Retefuente!F41 -> 44585 | F26: =IF(D26-E26>0,D26-E26,0) -> 0
A28: AÑO 2022
A29: BIMESTRAL | B29: BANCO | C29: VALOR | D29: FECHA CONSIGNACION | E29: FECHA DE PRESENTACION DIAN | F29: DIAS INCUMPLIDOS | G29: Impuesto generado
A30: Enero - Febrero | E30: =Retefuente!F46 -> 44638 | F30: =IF(D30-E30>0,D30-E30,0) -> 0 | G30: 70987000
A31: Marzo - Abril | E31: =Retefuente!F48 -> 44701 | F31: =IF(D31-E31>0,D31-E31,0) -> 0 | G31: 114819000
A32: Mayo - Junio | E32: =Retefuente!F50 -> 44763 | F32: =IF(D32-E32>0,D32-E32,0) -> 0 | G32: 111167000
A33: Julio .- Agosto | E33: =Retefuente!F52 -> 44823 | F33: =IF(D33-E33>0,D33-E33,0) -> 0 | G33: 105227000
A34: Septiembre - Octubre | E34: =Retefuente!F54 -> 44887 | F34: =IF(D34-E34>0,D34-E34,0) -> 0 | G34: 109419000
A35: Noviembre - Diciembre | E35: =Retefuente!F56 -> 44949 | F35: =IF(D35-E35>0,D35-E35,0) -> 0 | G35: 246413000
A37: AÑO 2023
A38: BIMESTRAL | B38: BANCO | C38: VALOR | D38: FECHA CONSIGNACION | E38: FECHA DE PRESENTACION DIAN | F38: DIAS INCUMPLIDOS
A39: Enero - Febrero | E39: =Retefuente!F61 -> 45002 | F39: =IF(D39-E39>0,D39-E39,0) -> 0 | G39: 74648000
A40: Marzo - Abril | E40: =Retefuente!F63 -> 45065 | F40: =IF(D40-E40>0,D40-E40,0) -> 0 | G40: 95414000
A41: Mayo - Junio | E41: =Retefuente!F65 -> 45126 | F41: =IF(D41-E41>0,D41-E41,0) -> 0 | G41: 90544000
A42: Julio .- Agosto | E42: =Retefuente!F67 -> 45188 | F42: =IF(D42-E42>0,D42-E42,0) -> 0 | G42: 90399000
A43: Septiembre - Octubre | E43: =Retefuente!F69 -> 45251 | F43: =IF(D43-E43>0,D43-E43,0) -> 0 | G43: 111340000
A44: Noviembre - Diciembre | E44: =Retefuente!F71 -> 45313 | F44: =IF(D44-E44>0,D44-E44,0) -> 0 | G44: 151485000
A46: AÑO 2024
A47: BIMESTRAL | B47: BANCO | C47: VALOR | D47: FECHA CONSIGNACION | E47: FECHA DE PRESENTACION DIAN | F47: DIAS INCUMPLIDOS
A48: Enero - Febrero | E48: =Retefuente!F76 -> 45372 | F48: =IF(D48-E48>0,D48-E48,0) -> 0
A49: Marzo - Abril | E49: =Retefuente!F78 -> 45435 | F49: =IF(D49-E49>0,D49-E49,0) -> 0
A50: Mayo - Junio | E50: =Retefuente!F80 -> 45495 | F50: =IF(D50-E50>0,D50-E50,0) -> 0
A51: Julio .- Agosto | E51: =Retefuente!F82 -> 45555 | F51: =IF(D51-E51>0,D51-E51,0) -> 0
A52: Septiembre - Octubre | E52: =Retefuente!F84 -> 45621 | F52: =IF(D52-E52>0,D52-E52,0) -> 0
A53: Noviembre - Diciembre | E53: =Retefuente!F86 -> 45680 | F53: =IF(D53-E53>0,D53-E53,0) -> 0
A55: AÑO 2025
A56: BIMESTRAL | B56: BANCO | C56: VALOR | D56: FECHA CONSIGNACION | E56: FECHA DE PRESENTACION DIAN | F56: DIAS INCUMPLIDOS
A57: Enero - Febrero | E57: =Retefuente!F91 -> 45737 | F57: =IF(D57-E57>0,D57-E57,0) -> 0
A58: Marzo - Abril | E58: =Retefuente!F93 -> 45799 | F58: =IF(D58-E58>0,D58-E58,0) -> 0
A59: Mayo - Junio | E59: =Retefuente!F95 -> 45859 | F59: =IF(D59-E59>0,D59-E59,0) -> 0
A60: Julio .- Agosto | E60: =Retefuente!F97 -> 45919 | F60: =IF(D60-E60>0,D60-E60,0) -> 0
A61: Septiembre - Octubre | E61: =Retefuente!F99 -> 45986 | F61: =IF(D61-E61>0,D61-E61,0) -> 0
A62: Noviembre - Diciembre | E62: =Retefuente!F101 -> 46045 | F62: =IF(D62-E62>0,D62-E62,0) -> 0

Sheet IVA - Cuatrimestral
A2: AÑO 2019
A3: CUATRIMESTRE | B3: BANCO | C3: VALOR | D3: FECHA CONSIGNACION | E3: FECHA DE PRESENTACION DIAN | F3: DIAS INCUMPLIDOS
A4: Enero - Abril | E4: =Retefuente!F3 -> 0 | F4: =IF(D4-E4>0,D4-E4,0) -> 0
A5: Mayo - Agosto | E5: =Retefuente!F7 -> 43719 | F5: =IF(D5-E5>0,D5-E5,0) -> 0
A6: Septiembre - Diciembre | E6: =Retefuente!F11 -> 43843 | F6: =IF(D6-E6>0,D6-E6,0) -> 0
A8: AÑO 2020 | B8: |
A9: CUATRIMESTRE | B9: BANCO | C9: VALOR | D9: FECHA CONSIGNACION | E9: FECHA DE PRESENTACION DIAN | F9: DIAS INCUMPLIDOS
A10: Enero - Abril | E10: =Retefuente!F18 -> 43964 | F10: =IF(D10-E10>0,D10-E10,0) -> 0
A11: Mayo - Agosto | E11: =Retefuente!F22 -> 44083 | F11: =IF(D11-E11>0,D11-E11,0) -> 0
A12: Septiembre - Diciembre | E12: =Retefuente!F26 -> 44210 | F12: =IF(D12-E12>0,D12-E12,0) -> 0
A15: AÑO 2021
A16: CUATRIMESTRE | B16: BANCO | C16: VALOR | D16: FECHA CONSIGNACION | E16: FECHA DE PRESENTACION DIAN | F16: DIAS INCUMPLIDOS | I16: Ingreso bruto | J16: Registro Civil
A17: Enero - Abril | E17: =Retefuente!F33 -> 44337 | F17: =IF(D17-E17>0,D17-E17,0) -> 0 | G17: 182679000
A18: Mayo - Agosto | E18: =Retefuente!F37 -> 44459 | F18: =IF(D18-E18>0,D18-E18,0) -> 0 | G18: 180773000
A19: Septiembre - Diciembre | E19: =Retefuente!F41 -> 44585 | F19: =IF(D19-E19>0,D19-E19,0) -> 0 | G19: 259066000 | I19: 668410264 | J19: 9173200 | K19: =I19-J19 -> 659237064
I20: 305326012 | J20: 12464000 | K20: =I20-J20 -> 292862012
A21: AÑO 2022 | I21: 209267803 | J21: 9918000 | K21: =I21-J21 -> 199349803
A22: CUATRIMESTRE | B22: BANCO | C22: VALOR | D22: FECHA CONSIGNACION | E22: FECHA DE PRESENTACION DIAN | F22: DIAS INCUMPLIDOS | I22: 222867861 | J22: 10898400 | K22: =I22-J22 -> 211969461
A23: Enero - Abril | E23: =Retefuente!F48 -> 44701 | F23: =IF(D23-E23>0,D29-E23,0) -> 0 | K23: =K19+K20+K21+K22 -> 1363418340
A24: Mayo - Agosto | E24: =Retefuente!F52 -> 44823 | F24: =IF(D24-E24>0,D24-E24,0) -> 0 | K24: =K23*0.19 -> 2.5904948e+08
A25: Septiembre - Diciembre | E25: =Retefuente!F56 -> 44949 | F25: =IF(D25-E25>0,D25-E25,0) -> 0
A27: AÑO 2023
A28: CUATRIMESTRE | B28: BANCO | C28: VALOR | D28: FECHA CONSIGNACION | E28: FECHA DE PRESENTACION DIAN | F28: DIAS INCUMPLIDOS
A29: Enero - Abril | E29: =Retefuente!F63 -> 45065 | F29: =IF(D29-E29>0,D29-E29,0) -> 0
A30: Mayo - Agosto | E30: =Retefuente!F67 -> 45188 | F30: =IF(D30-E30>0,D30-E30,0) -> 0
A31: Septiembre - Diciembre | E31: =Retefuente!F71 -> 45313 | F31: =IF(D31-E31>0,D31-E31,0) -> 0
A33: AÑO 2024
A34: CUATRIMESTRE | B34: BANCO | C34: VALOR | D34: FECHA CONSIGNACION | E34: FECHA DE PRESENTACION DIAN | F34: DIAS INCUMPLIDOS
A35: Enero - Abril | E35: =Retefuente!F78 -> 45435 | F35: =IF(D35-E35>0,D35-E35,0) -> 0
A36: Mayo - Agosto | E36: =Retefuente!F82 -> 45555 | F36: =IF(D36-E36>0,D36-E36,0) -> 0
A37: Septiembre - Diciembre | E37: =Retefuente!F86 -> 45680 | F37: =IF(D37-E37>0,D37-E37,0) -> 0
A39: AÑO 2025
A40: CUATRIMESTRE | B40: BANCO | C40: VALOR | D40: FECHA CONSIGNACION | E40: FECHA DE PRESENTACION DIAN | F40: DIAS INCUMPLIDOS
A41: Enero - Abril | E41: =Retefuente!F93 -> 45799 | F41: =IF(D41-E41>0,D41-E41,0) -> 0
A42: Mayo - Agosto | E42: =Retefuente!F97 -> 45919 | F42: =IF(D42-E42>0,D42-E42,0) -> 0
A43: Septiembre - Diciembre | E43: =Retefuente!F101 -> 46045 | F43: =IF(D43-E43>0,D43-E43,0) -> 0

Sheet EXOGENA
A1: Últimos 2 digitos Cédula de ciudadanía | C1: 39 | E1: Año 2019 | H1: Año 2020 | K1: Año 2021 | N1: Año 2022 | Q1: Año 2023 | T1: 2024
A2: PERIODO | B2: FECHA PRESENTACION | C2: FECHA VENCIMIENTO | D2: Extemporaneidad | E2: ÚLTIMOS DÍGITOS | F2: FECHA | H2: ÚLTIMOS DÍGITOS | I2: FECHA | K2: ÚLTIMOS DÍGITOS | L2: FECHA | N2: ÚLTIMOS DÍGITOS | O2: FECHA | Q2: ÚLTIMOS DÍGITOS | R2: FECHA | T2: Últimos digitos | U2: Fecha
A3: 2019 | E3: 91 a 00 | F3: 16 de junio de 2020 | H3: 1 | I3: 25 de Mayo de 2021 | K3: 1 | L3: 10 de Mayo de 2022 | N3: 1 | O3: 16 de Mayo de 2023 | Q3: 1 | R3: 08 de Mayo de 2024 | T3: 1 | U3: 14 de mayo de 2025
A4: 2020 | C4: =VLOOKUP(C1,H3:I17,2,TRUE) -> 02 de Junio de 2021 | E4: 81 a 90 | F4: 17 de junio de 2020 | H4: 7 | I4: 26 de Mayo de 2021 | K4: 6 | L4: 11 de Mayo de 2022 | N4: 6 | O4: 17 de Mayo de 2023 | Q4: 6 | R4: 09 de Mayo de 2024 | T4: 6 | U4: 15 de mayo de 2025
A5: 2021 | C5: =VLOOKUP(C1,K3:L17,2,TRUE) -> 19 de Mayo de 2022 | E5: 71 a 80 | F5: 18 de junio de 2020 | H5: 13 | I5: 27 de Mayo de 2021 | K5: 11 | L5: 12 de Mayo de 2022 | N5: 11 | O5: 18 de Mayo de 2023 | Q5: 11 | R5: 10 de Mayo de 2024 | T5: 11 | U5: 16 de mayo de 2025
A6: 2022 | C6: =VLOOKUP($C$1,N3:O17,2,TRUE) -> 26 de Mayo de 2023 | E6: 61 a 70 | F6: 19 de junio de 2020 | H6: 19 | I6: 28 de Mayo de 2021 | K6: 16 | L6: 13 de Mayo de 2022 | N6: 16 | O6: 19 de Mayo de 2023 | Q6: 16 | R6: 14 de Mayo de 2024 | T6: 16 | U6: 19 de mayo de 2025
A7: 2023 | C7: =VLOOKUP($C$1,Q3:R17,2,TRUE) -> 20 de Mayo de 2024 | E7: 51 a 60 | F7: 23 de junio de 2020 | H7: 25 | I7: 31 de Mayo de 2021 | K7: 21 | L7: 16 de Mayo de 2022 | N7: 21 | O7: 23 de Mayo de 2023 | Q7: 21 | R7: 15 de Mayo de 2024 | T7: 21 | U7: 20 de mayo de 2025
A8: 2024 | C8: =VLOOKUP($C$1,T3:U17,2,TRUE) -> 23 de mayo de 2025 | E8: 41 a 50 | F8: 24 de junio de 2020 | H8: 31 | I8: 01 de Junio de 2021 | K8: 26 | L8: 17 de Mayo de 2022 | N8: 26 | O8: 24 de Mayo de 2023 | Q8: 26 | R8: 16 de Mayo de 2024 | T8: 26 | U8: 21 de mayo de 2025
E9: 31 a 40 | F9: 25 de junio de 2020 | H9: 38 | I9: 02 de Junio de 2021 | K9: 31 | L9: 18 de Mayo de 2022 | N9: 31 | O9: 25 de Mayo de 2023 | Q9: 31 | R9: 17 de Mayo de 2024 | T9: 31 | U9: 22 de mayo de 2025
E10: 21 a 30 | F10: 26 de junio de 2020 | H10: 45 | I10: 03 de Junio de 2021 | K10: 36 | L10: 19 de Mayo de 2022 | N10: 36 | O10: 26 de Mayo de 2023 | Q10: 36 | R10: 20 de Mayo de 2024 | T10: 36 | U10: 23 de mayo de 2025
E11: 11 a 20 | F11: 30 de junio de 2020 | H11: 52 | I11: 04 de Junio de 2021 | K11: 41 | L11: 20 de Mayo de 2022 | N11: 41 | O11: 29 de Mayo de 2023 | Q11: 41 | R11: 21 de Mayo de 2024 | T11: 41 | U11: 26 de mayo de 2025
E12: 01 a 10 | F12: 01 de julio de 2020 | H12: 59 | I12: 08 de Junio de 2021 | K12: 46 | L12: 23 de Mayo de 2022 | N12: 46 | O12: 30 de Mayo de 2023 | Q12: 46 | R12: 22 de Mayo de 2024 | T12: 46 | U12: 27 de mayo de 2025
H13: 66 | I13: 09 de Junio de 2021 | K13: 51 | L13: 24 de Mayo de 2022 | N13: 51 | O13: 31 de Mayo de 2023 | Q13: 51 | R13: 23 de Mayo de 2024 | T13: 51 | U13: 28 de mayo de 2025
H14: 72 | I14: 10 de Junio de 2021 | K14: 56 | L14: 25 de Mayo de 2022 | N14: 56 | O14: 01 de Junio de 2023 | Q14: 56 | R14: 24 de Mayo de 2024 | T14: 56 | U14: 03 de junio de 2025
H15: 80 | I15: 11 de Junio de 2021 | K15: 61 | L15: 26 de Mayo de 2022 | N15: 61 | O15: 02 de Junio de 2023 | Q15: 61 | R15: 27 de Mayo de 2024 | T15: 61 | U15: 04 de junio de 2025
H16: 87 | I16: 15 de Junio de 2021 | K16: 66 | L16: 27 de Mayo de 2022 | N16: 66 | O16: 05 de Junio de 2023 | Q16: 66 | R16: 28 de Mayo de 2024 | T16: 66 | U16: 05 de junio de 2025
H17: 94 | I17: 16 de Junio de 2021 | K17: 71 | L17: 31 de Mayo de 2022 | N17: 71 | O17: 06 de Junio de 2023 | Q17: 71 | R17: 29 de Mayo de 2024 | T17: 71 | U17: 06 de junio de 2025
K18: 76 | L18: 01 de Junio de 2022 | N18: 76 | O18: 07 de Junio de 2023 | Q18: 76 | R18: 30 de Mayo de 2024 | T18: 76 | U18: 09 de junio de 2025
K19: 81 | L19: 02 de Junio de 2022 | N19: 81 | O19: 08 de Junio de 2023 | Q19: 81 | R19: 31 de Mayo de 2024 | T19: 81 | U19: 10 de junio de 2025
K20: 86 | L20: 03 de Junio de 2022 | N20: 86 | O20: 09 de Junio de 2023 | Q20: 86 | R20: 04 de Junio de 2024 | T20: 86 | U20: 11 de junio de 2025
K21: 91 | L21: 06 de Junio de 2022 | N21: 91 | O21: 13 de Junio de 2023 | Q21: 91 | R21: 05 de Junio de 2024 | T21: 91 | U21: 12 de junio de 2025
K22: 96 | L22: 07 de Junio de 2022 | N22: 96 | O22: 14 de Junio de 2023 | Q22: 96 | R22: 06 de Junio de 2024 | T22: 96 | U22: 13 de junio de 2025

Sheet Ind. Comercio
A1: AÑO 2021
A2: MES | B2: BANCO | C2: VALOR | D2: FECHA CONSIGNACION
A3: Enero - Febrero
A4: Marzo - Abril
A5: Mayo - Junio
A6: Julio - Agosto
A7: Septiembre - Octubre
A8: Noviembre - Diciembre
A9: ANUAL
A11: AÑO 2022
A12: MES | B12: BANCO | C12: VALOR | D12: FECHA CONSIGNACION
A13: Enero - Febrero
A14: Marzo - Abril
A15: Mayo - Junio
A16: Julio - Agosto
A17: Septiembre - Octubre
A18: Noviembre - Diciembre
A19: ANUAL
A21: AÑO 2023
A22: MES | B22: BANCO | C22: VALOR | D22: FECHA CONSIGNACION
A23: Enero - Febrero
A24: Marzo - Abril
A25: Mayo - Junio
A26: Julio - Agosto
A27: Septiembre - Octubre
A28: Noviembre - Diciembre
A29: ANUAL
A31: AÑO 2024
A32: MES | B32: BANCO | C32: VALOR | D32: FECHA CONSIGNACION
A33: Enero - Febrero
A34: Marzo - Abril
A35: Mayo - Junio
A36: Julio - Agosto
A37: Septiembre - Octubre
A38: Noviembre - Diciembre
A39: ANUAL
A41: AÑO 2025
A42: MES | B42: BANCO | C42: VALOR | D42: FECHA CONSIGNACION
A43: Enero - Febrero
A44: Marzo - Abril
A45: Mayo - Junio
A46: Julio - Agosto
A47: Septiembre - Octubre
A48: Noviembre - Diciembre
A49: ANUAL

Sheet Impuesto Timbre
A1: pesos | B1: IMPUESTO DE TIMBRE | G1: AÑO | H1: VALOR UVT | I1: EN PESOS
B2: VIGENTE DESDE 2023 POR LEY 2277 DE 2022 | I2: 20000 | J2: 50000
B3: RANGOS UVT | D3: TARIFA MARGINAL | E3: IMPUESTO | G3: 2023 | H3: 42412 | I3: =I2*H3 -> 848240000 | J3: =J2*H3 -> 2120600000
B4: DESDE | C4: HASTA | G4: 2024 | H4: 47065 | I4: =I2*H4 -> 941300000 | J4: =J2*H4 -> 2353250000
B5: 0 | C5: 20000 | D5: 0 | E5: 0 | G5: 2025 | H5: 49799 | I5: =I2*H5 -> 995980000 | J5: =J2*H5 -> 2489950000
B6: > 20.000 | C6: 50000 | D6: 0.015 | E6: (VALOR DE LA ENAJENACIÓN EN UVT MENOS 20.000 UVT) * 1,5% | G6: 2026 | H6: 52374 | I6: =I2*H6 -> 1047480000 | J6: =J2*H6 -> 2618700000
B7: > 50.000 | C7: En Adelante | D7: 0.03 | E7: ((VALOR DE LA ENAJENACIÓN EN UVT MENOS 50.000 UVT) * 3%) + 450 UVT
B9: CALCULADORA UNIFICADA DE IMPUESTO DE TIMBRE | F9: AÑO
B10: 1 | C10: Valor enajenación | D10: 1200000000 | E10: =IF(D11>50000,(((D11-50000)*3%+450)*VLOOKUP(F10,G3:J6,2,FALSE)),IF(D11>20000,((D11-20000)*1.5%)*(VLOOKUP(F10,G3:J6,2,FALSE)),0)) -> 3880500 | F10: 2024 | G10: Instrucciones de Empleo: 1. Una vez determinado el valor de los inmuebles enajenados escriba el valor en el cuadro naranja al frente de "Valor de enajenación". 2. Verifique el año en que se generó la enajenación. 3. Disfrute 4. No modifique las casillas adicionales, son meramente informativas.
B11: 2 | C11: valor en UVT | D11: =D10/(VLOOKUP(F10,G3:J6,2,FALSE)) -> 25496.654 | E11: UVT
B12: 2. | C12: valor enajenación - UVT correspondientes. | D12: =D11-I2 -> 5496.6536 | E12: =D11-J2 -> -24503.346
B13: 3. | C13: Aplicación Tarifa | D13: =D12*D6 -> 82.449803 | E13: =(E12*D7)+450 -> -285.10039
B14: 4. | C14: Valor a Pagar | D14: Impuesto de Timbre | E14: =D13*((VLOOKUP(F10,G3:J5,2,FALSE))) -> 3880500 | G14: =E13*((VLOOKUP(F10,G3:J5,2,FALSE))) -> -13418250
B16: 50.000 UVT | F16: AÑO
B17: 50.000 UVT | C17: Valor Inmueble | D17: 5000000000 | E17: pesos | F17: 2025
B18: 1. | C18: Valor en UVT | D18: =D17/(VLOOKUP(F17,G3:J5,2,FALSE)) -> 100403.62 | E18: UVT | I18: 1988
B19: 2. | C19: Valor Enajenación - UVT correspondientes. | D19: =D18-50000 -> 50403.623 | E19: UVT | I19: 50
B20: 3. | C20: Aplicación Tarifa | D20: =D19*D7 -> 1512.1087 | E20: UVT
B21: 4. | C21: Suma UVT | D21: =D20+450 -> 1962.1087 | E21: UVT
B22: 5. | C22: Valor a Pagar | D22: Impuesto de Timbre | E22: =D21*((VLOOKUP(F17,G3:J5,2,FALSE))) -> 97711050 | F22: =IF(E22<0,"NO APLICA","APLICA") -> APLICA | G22: =E22/2 -> 48855525 | H22: =G22/2 -> 24427762
B24: MODIFICACIÓN TRANSITORIA POR DECRETO 175 DE 2025
B25: Vigencia | C25: 45709 | D25: Cuantía del acto | E25: 4
B26: Hecho gravado | C26: sobre los instrumentos públicos y documentos privados, incluidos los títulos valores, que se otorguen o acepten en el país, o que se otorguen fuera del país pero que se ejecuten en el territorio nacional o generen obligaciones en el mismo, en los que se haga constar la constitución, existencia, modificación o extinción de obligaciones, al igual que su prórroga o cesión
B27: Sujeto gravado | C27: en los cuales intervenga como otorgante, aceptante o suscriptor una entidad pública, una persona jurídica o asimilada, o una persona natural que tenga la calidad de comerciante, que en el año inmediatamente anterior tuviere unos ingresos brutos o un patrimonio bruto superior a treinta mil (30.000) Unidades de Valor Tributario, UVT.
B28: 600 UVT | C28: =6000*D28 -> 282390000 | D28: =(VLOOKUP(F10,G3:J5,2,FALSE)) -> 47065 | E28: =IF(E25/C28>1,E25/C28,"NO APLICA") -> NO APLICA
B29: Tarifa | C29: 0.01
B30: Valor a pagar | C30: =IF(E28="NO APLICA", "0",C29*E25) -> 0

Sheet Liquidador
B2: LIQUIDADOR UNIFICADO. VR PRELIMINAR 2.
B3: DERECHOS NOTARIALES | G3: APORTES ESPECIALES
G4: Límite de la remuneración notarial
B6: AUTORIZACIÓN DE ACTOS | F6: AÑO | G6: Art. 39 Concurrencia de los particulares con entidades exentas y límite de la remuneración notarial. | H6: Literal b | J6: =IF(E13>=VLOOKUP($F$7,'Hoja de control'!A2:BH7,31,FALSE),E13-VLOOKUP($F$7,'Hoja de control'!A2:BH7,31,FALSE),"No genera aporte especial") -> #NAME?
B7: Art. 2 Lit. a) | C7: Actos SIN Cuantía | F7: 2024 | H7: Literal c | J7: =IF(E18>=VLOOKUP($F$7,'Hoja de control'!A2:BH7,31,FALSE),E18-VLOOKUP($F$7,'Hoja de control'!A2:BH7,31,FALSE),"No genera aporte especial") -> #NAME?
C8: VALOR A PAGAR | D8: =VLOOKUP($F$7,'Hoja de control'!A2:BH7,2,FALSE) -> 5000 | G8: Art. 40 Actos entre particulares o entre entidades no exentas y límite de la remuneración notarial. | H8: Literal b | J8: =IF(E13>=VLOOKUP($F$7,'Hoja de control'!A2:BH7,32,FALSE),E13-VLOOKUP($F$7,'Hoja de control'!A2:BH7,32,FALSE),"No genera aporte especial") -> #NAME?
B9: Actos CON Cuantía | H9: Literal c | J9: =IF(E18>=VLOOKUP($F$7,'Hoja de control'!A2:BH7,32,FALSE),E18-VLOOKUP($F$7,'Hoja de control'!A2:BH7,32,FALSE),"No genera aporte especial") -> #NAME?
B10: Art. 2 Lit. b) | C10: Igual o Inferior a | D10: =VLOOKUP($F$7,'Hoja de control'!A2:BH7,3,FALSE) -> 3800 | E10: =VLOOKUP($F$7,'Hoja de control'!A2:BH7,4,FALSE) -> 2300
C11: Cuantía | D11: 15000000
C12: Superior a X | D12: =D11-D10 -> 14996200 | E12: =(D12*3/1000)+E10 -> 47288.6 | G12: RETENCIÓN EN LA FUENTE | H12: 0.01 | I12: =D11 -> 15000000 | J12: =H12*I12 -> 150000 | K12: =SUM(K8:K10) -> 0
C13: VALOR A PAGAR | E13: =_xlfn.IFS(D11=D10,E10,D11<D10,E10,D11>D10,E12) -> #NAME?
B14: Liquidación de herencias y sociedades conyugales | G14: IMPUESTO DE TIMBRE LEY 2277 DE 2022
B15: Art. 2 Lit. c) | C15: Inferior a | D15: =VLOOKUP($F$7,'Hoja de control'!A2:BH7,7,FALSE) -> 4700 | E15: =D8 -> 5000
C16: Cuantía | D16: 60000000 | G16: CONSIDERACIONES | I16: Valor en UVT | J16: Impuesto a pagar
C17: Superior a X | D17: =D16-D15 -> 59995300 | E17: =(D17*3.5/1000)+E15 -> 214983.55
C18: VALOR A PAGAR | E18: =_xlfn.IFS(D16=D15,E15,D16<D15,E15,D16>D15,E17) -> #NAME? | G18: Valor de inmuebles enajenados - Valor de muebles enajenados | H18: Art. 2 Lit. b) Resol. Tarf | I18: =(D11-H20)/VLOOKUP($F$7,'Hoja de control'!A2:BH7,37,FALSE) -> #DIV/0! | J18: =IF(I22>500000,(((I22-50000)*3%+450)*VLOOKUP($F$7,'Hoja de control'!A2:BH7,37,FALSE)),IF(I22>20000,((I22-20000)*1.5%)*(VLOOKUP($F$7,'Hoja de control'!A2:BH7,37,FALSE)),0)) -> #NAME?
B19: Art. 2 Pr. | C19: Valor hoja del instrumento público utilizado por ambas caras. | E19: =VLOOKUP($F$7,'Hoja de control'!A2:BH7,9,FALSE) -> 2600 | H19: Art. 2 Lit. c) Resol. Tarf | I19: =(D16-H21)/VLOOKUP($F$7,'Hoja de control'!A2:BH7,37,FALSE) -> #DIV/0! | J19: =IF(I23>500000,(((I23-50000)*3%+450)*VLOOKUP($F$7,'Hoja de control'!A2:BH7,37,FALSE)),IF(I23>20000,((I23-20000)*1.5%)*(VLOOKUP($F$7,'Hoja de control'!A2:BH7,37,FALSE)),0)) -> #NAME?
G20: Valor de muebles enajenados Lit b | H20: 0
G21: Valor de muebles enajenados Lit c | H21: 0
B22: PROTOCOLIZACIÓN | G22: TRUE | I22: =(_xlfn.IFS(G22&G23=TRUE,I18/4,OR(G22,G23)=TRUE,I18/2,G22=FALSE&G23=FALSE,I18)) -> #NAME?
B23: Art. 3 Pr. 1 | C23: Protocolización por cada documento NO esencial del acto, por decisión voluntaria de otorgante. | E23: =D8 -> 5000 | G23: TRUE | I23: =(_xlfn.IFS(G22&G23=TRUE,I19/4,OR(G22,G23)=TRUE,I19/2,G22=FALSE&G23=FALSE,I19)) -> #NAME? | K23: Genera Aporte Especial
K24: No Genera Aporte Especial
B25: CERTIFICACIONES
B26: Art. 4 Lit. a) | C26: Por cada certificación de actos o hechos que consten en instrumentos públicos o en documentos protocolizados. | E26: =VLOOKUP($F$7,'Hoja de control'!A2:BH7,10,FALSE) -> 2600
B27: Art. 4 Lit. b) | C27: Por cada nota de referencia en la escritura pública afectada por nuevas declaraciones de voluntad. | E27: =VLOOKUP($F$7,'Hoja de control'!A2:BH7,11,FALSE) -> 2600 | K27: Genera Aporte Especial
K28: NO Genera Aporte Especial
B29: COPIAS
B30: Art. 5 | C30: Copias auténticas que según la Ley debe expedir el Notario de los instrumentos, y demás documentos que reposen en el protocolo de la Notaría, causarán derechos por cada hoja utilizada por ambas caras. | E30: =VLOOKUP($F$7,'Hoja de control'!A2:BH7,12,FALSE) -> 2600
C31: Por cada cara de una copia simple física expedida por notarios de documentos que reposan en el protocolo, se expedirán en papel común y no podrán contar con ningún sello, firma ni rúbrica adicional a aquellos que se encuentran plasmados en el documento reproducido. | E31: =VLOOKUP($F$7,'Hoja de control'!A2:BH7,13,FALSE) -> 2600
B32: Art. 5 Pr. | C32: Si el usuario requiere impresión de certificados tomados de páginas web de diferentes entidades estatales, tal impresión causará derechos. | E32: =VLOOKUP($F$7,'Hoja de control'!A2:BH7,14,FALSE) -> 4400
B34: TESTIMONIO NOTARIAL
B35: Art. 6 | C35: Testimonio escrito, en la presentación personal y el reconocimiento de documento privado, autenticidad de firmas puestas en documentos previa confrontación de su correspondencia, autenticidad de firmas y huellas dactilares puestas en su presencia, autenticidad de fotografías de personas. | E35: =VLOOKUP($F$7,'Hoja de control'!A2:BH7,15,FALSE) -> 9400
C36: Identificación personal del usuario mediante verificación de huella dactilar, por medios electrónicos y cotejo con la base de datos de la Registraduría. | E36: =VLOOKUP($F$7,'Hoja de control'!A2:BH7,16,FALSE) -> 9400
B37: Art. 6 Pr. 1 | C37: Reconocimiento de firma y contenido, si está conformado por más de un folio, cada hoja que forme parte del mismo, rubricada y sellada, costará el 10% adicional de la tarifa establecida para la autenticación de la firma. | E37: =VLOOKUP($F$7,'Hoja de control'!A2:BH7,17,FALSE) -> 18000
B38: Art. 6 Pr. 2 | C38: Imposición de la firma digital. | E38: =VLOOKUP($F$7,'Hoja de control'!A2:BH7,18,FALSE) -> 135500
C39: Tránsito o transferencia cibernético. | E39: =VLOOKUP($F$7,'Hoja de control'!A2:BH7,18,FALSE) -> 135500
C40: Si el documento consta de varios folios, el valor adicional será del 10% por folio enviado. | E40: =VLOOKUP($F$7,'Hoja de control'!A2:BH7,19,FALSE) -> 18000
B41: Art. 6 Pr. 3 | C41: Impresión de huella dactilar y su certificación en los eventos en que la ley lo exija o cuando solicite el usuario.
C42: Hechos relacionados con el ejercicio de sus funciones ocurridos en su presencia / Actas de Comparecencia. | E42: =VLOOKUP($F$7,'Hoja de control'!A2:BH7,20,FALSE) -> 9300
C43: Hechos/testimonios relacionados con el ejercicio de sus funciones, que implique el desplazamiento del Notario dentro de la cabecera del círculo. | E43: =VLOOKUP($F$7,'Hoja de control'!A2:BH7,21,FALSE) -> 58600
B45: DECLARACIÓN EXTRAPROCESO
B46: Art. 7 | C46: Declaración Extraproceso. | E46: =VLOOKUP($F$7,'Hoja de control'!A2:BH7,22,FALSE) -> 158100
B48: CONSTANCIAS EN ESCRITURAS PÚBLICAS
B49: Art. 8 | C49: Constancia consignada en la matriz de escrituras pública por afectación a vivienda familiar, imperativo legal o acto voluntario de las partes. | E49: =VLOOKUP($F$7,'Hoja de control'!A2:BH7,23,FALSE) -> 18000
B51: INVENTARIO DE BIENES DE MENORES
B52: Art. 9 | C52: Escritura pública del inventario solemne de bienes del menor, causará derechos calculados sobre el valor de los bienes inventariados.
B54: CAPITULACIONES MATRIMONIALES
B55: Art. 10 | C55: Se tomará como base de liquidación, el valor de los bienes objeto de la misma, el cual no podrá ser inferior del avalúo catastral.
B57: MATRIMONIO CIVIL
B58: Art. 11 | C58: Celebrado en la sede (Notaría), incluida extensión, otorgamiento y autorización de escritura. | E58: =VLOOKUP($F$7,'Hoja de control'!A2:BH7,24,FALSE) -> 0
C59: Celebrado por fuera del despacho notarial. | E59: =VLOOKUP($F$7,'Hoja de control'!A2:BH7,25,FALSE) -> 0
B61: DISOLUCIÓN Y LIQUIDACIÓN DE SOCIEDAD CONYUGAL Y UNIÓN MARITAL DE HECHO
B62: Art. 12 | C62: Se tomará como base de liquidación el patrimonio líquido. | E62: A Pagar
B63: Literal C Art. 2
B65: TESTAMENTO CERRADO
B66: Art. 13 | C66: Apertura y publicación de testamento cerrado y protocolización de lo actuado, causará los derechos establecidos para los actos sin cuantía. | E66: =D8 -> 5000
B68: PROTOCOLIZACIÓN DEL PROCESO JUDICIAL DE SUCESIÓN
B69: Art. 14 | C69: Se tomará como base el patrimonio líquido, y en todo caso, se aplicará lo dispuesto en el literal c) del artículo 2.
B71: ACTAS DE ADMISIÓN O DEVOLUCIÓN EN TRTÁMITES SUCESORALES
B72: Art. 15 | C72: Actas de admisión o devolución en trámites sucesorales. | E72: =VLOOKUP($F$7,'Hoja de control'!A2:BH7,26,FALSE) -> 0
B74: SOCIEDADES
B75: Art. 16 | C75: Se toma como base el capital social suscrito, excepto en las escrituras de constitución de sociedades por acciones, en las cuales la liquidación de se hará con base en el capital autorizado.
B76: Art. 16 Lit. a) | C76: Reforma Estatutaria | E76: A Pagar
C77: Se liquidará sobre el incremento respectivo; en los demás casos en las sociedades por acciones, entiéndase como capital social. el suscrito
B78: Art. 16 Lit. b) | C78: Reforma Estatutaria con Disminución de Capital | E78: A Pagar
C79: Cuando la reforma implique disminución del capital, la liquidación se efectuará como acto sin cuantía. | E79: =E8 -> 0
B80: Art. 16 Lit. c) | C80: Fusión de Sociedades | E80: A Pagar
C81: Se tomará como base el capital de la nueva sociedad o de la absorbente. En la transformación de una sociedad, será con base en el capital social. Siendo el capital suscrito el de las sociedades por acciones.
B82: Art. 16 Lit. d) | C82: Escisión de Sociedades | E82: A Pagar
C83: Se liquidarán como acto sin cuantía. | E83: =E8 -> 0
B84: Art. 16 Lit. e) | C84: Cambio de Razón Social | E84: A Pagar
C85: Cambio de razón social y prórroga del término de duración de una sociedad, se efectuará como acto sin cuantía. | E85: =E8 -> 0
B86: Art. 16 Lit. f) | C86: Liquidación de Sociedades | E86: A Pagar
C87: Se tomará como base el activo líquido, pero en todo caso será necesario protocolizar el balance debidamente firmado por contador en el cual se señale el pasivo declarado.
B89: Constitución y Reformas estatutarias de Empresas Industriales y Comerciales del Estado
B90: Art. 17 | C90: Se liquidará sobre la base de los aportes de las entidades no exentas que intervengan en el acto, las cuales pagarán en proporción a sus aportes.
C91: Referente a reformas estatutarias con incremento de capital, los respectivos derechos estarán a cargo de las Empresas Industriales y Comerciales del Estado, tomando como base el incremento dado.
B93: Constitución y reformas estatutarias de sociedades de economía mixta
B94: Art. 18 | C94: Se liquidarán sobre la base de los aportes de los particulares y de las entidades no exentas que intervengan en el acto, los cuales pagarán en proporción a los mismos.
C95: Referente a reformas estatutarias con incremento de capital, los respectivos derechos estarán a cargo de tales organismos, tomando como base el incremento dado.
B97: Fiducia Mercantil
B98: Art. 19 | C98: Se tendrán como acto con cuantía, y se cobrará de conformidad con lo dispuesto en el literal b) del artículo 2.
B100: Fiducia en Garantía
B101: Art. 20 | C101: Causará por derechos notariales los ordenados para las hipotecas.
B103: Fiducia de Administración
B104: Art. 21 | C104: Se tendrá como cuantía del acto el valor estipulado como remuneración para el fiduciario.
B106: Leasing
B107: Art. 22 | C107: Los derechos notariales se liquidarán teniendo en cuenta la cuantía total de tales prestaciones. Si el plazo fuere indeterminado la base de la liquidación será el monto de la misma en cinco años.
B109: Contrato de leasing sin escritura pública.
B110: Art. 23 | C110: Cuando la cuantía del acto sea inferior a la del avalúo catastral, al autoavalúo o al valor del remate, los derechos se liquidarán con base en el concepto de los mencionados que presente el mayor valor.
B112: Hipotecas abiertas con límite de cuantía
B113: Art. 24 | C113: Hipotecas abiertas en donde se fijen las cuantías máximas de la obligación, los derechos notariales se liquidarán con base en dicha cuantía.
B115: Hipotecas abiertas sin límite de cuantía
B116: Art. 25 | C116: Los derechos notariales se liquidarán con base en la constancia, documento o carta que para tal efecto deberá presentar la persona o entidad acreedora, en la que se fijará de manera clara y precisa el cupo o monto del crédito aprobado que garantiza la respectiva hipoteca.
B118: Venta con hipoteca abierta sin límite de cuantía
B119: Art. 26 | C119: Los derechos notariales correspondientes a la hipoteca se liquidarán con base en el precio de la venta, cuando en el instrumento no se señale la parte del precio garantizado con la hipoteca.
B121: Cancelación de hipotecas abiertas
B122: Art. 27 | C122: Se liquidarán con base en el mismo monto que se tuvo en cuenta para su constitución.
B124: Cancelaciones parciales de hipotecas
B125: Art. 28 | C125: Se liquidarán con base en el coeficiente que tenga el inmueble hipotecado en el respectivo régimen de propiedad horizontal.
...

Sheet Hoja de control
A1: AÑO | B1: PAPEL ORIGINAL | C1: CERTIFICACIÓN | D1: NOTAS DE REFERENCIA | E1: COPIA AUTÉNTICA | F1: COPIA SIMPLE | G1: CERTIFICADO WEB | H1: ACTO SIN CUANTÍA | I1: AUTENTICIDAD DE FOTOGRAFÍA | J1: PRESENTACIÓN PERSONAL | K1: RECONOCIMIENTO DE DOCUMENTO PRIVADO | L1: AUTENTICIDAD DE FIRMAS REGISTRADAS | M1: AUTENTICIDAD DE FIRMA | N1: IDENTIFICACIÓN BIOMÉTRICA | O1: FIRMA DIGITAL | P1: TRANSFERENCIA CIBERNÉTICA | Q1: ACTA DE COMPARECENCIA | R1: TESTIMONIO QUE IMPLIQUE DESPLAZAMIENTO DENTRO DEL CÍRCULO | S1: DECLARACIÓN EXTRAPROCESO | T1: CONSTANCIA DE AFECTACIÓN A VIVIENDA FAMILIAR | U1: MATRIMONIO EN DESPACHO | V1: MATRIMONIO FUERA DEL DESPACHO | W1: ACTA DE ADMISIÓN O DEVOLUCIÓN EN TRÁMITES SUCESORALES
A2: 2026
A3: 2025 | B3: 5300 | C3: 4000 | D3: 2400 | E3: 5300 | F3: 700 | G3: 4900 | H3: 86200 | I3: 2700 | J3: 2700 | K3: 2700 | L3: 2700 | M3: 2700 | N3: 4600 | O3: 9900 | P3: 9900 | Q3: 18900 | R3: 142500 | S3: 18900 | T3: 9800 | U3: 61600 | V3: 166300 | W3: 18900
A4: 2024 | B4: 5000 | C4: 3800 | D4: 2300 | E4: 5000 | F4: 900 | G4: 4700 | H4: 81900 | I4: 2600 | J4: 2600 | K4: 2600 | L4: 2600 | M4: 2600 | N4: 4400 | O4: 9400 | P4: 9400 | Q4: 18000 | R4: 135500 | S4: 18000 | T4: 9300 | U4: 58600 | V4: 158100 | W4: 18000
A5: 2023 | B5: 4600 | C5: 3500 | D5: 2100 | E5: 4600 | F5: 900 | G5: 4300 | H5: 74900 | I5: 2400 | J5: 2400 | K5: 2400 | L5: 2400 | M5: 2400 | N5: 4000 | O5: 8600 | P5: 8600 | Q5: 16500 | R5: 124000 | S5: 16500 | T5: 8500 | U5: 53600 | V5: 144700 | W5: 16500
A6: 2022 | B6: 4100 | C6: 3100 | D6: 1900 | E6: 4100 | F6: 900 | G6: 3800 | H6: 66200 | I6: 2100 | J6: 2100 | K6: 2100 | L6: 2100 | M6: 2100 | N6: 3500 | O6: 7600 | P6: 7600 | Q6: 14600 | R6: 109600 | S6: 14600 | T6: 7500 | U6: 47400 | V6: 127900 | W6: 14600
A7: 2021 | B7: 3900 | C7: 2900 | D7: 1800 | E7: 3900 | F7: 900 | G7: 3600 | H7: 62700 | I7: 2000 | J7: 2000 | K7: 2000 | L7: 2000 | M7: 2000 | N7: 3300 | O7: 7200 | P7: 7200 | Q7: 13800 | R7: 103800 | S7: 13800 | T7: 7100 | U7: 44900 | V7: 121100 | W7: 13800

Sheet Servicios por cuantia
A1: SERVICIO | B1: TIPO_REGLA | C1: UMBRAL | D1: TARIFA_BASE | E1: PORCENTAJE_EXCEDENTE | F1: MIN | G1: MAX | H1: AÑO_DESDE | I1: AÑO_HASTA | J1: TOPE_PARTICULARES | K1: TOPE_EXENTOS | L1: REQUIERE_TIPO_COMPARECIENTE
A2: Acto con cuantía lit B | B2: UMBRAL_MAS_EXCEDENTE | H2: 2026 | I2: 2026
A3: Acto con cuantía lit B | B3: UMBRAL_MAS_EXCEDENTE | C3: 246700 | D3: 29400 | E3: 0.003 | H3: 2025 | I3: 2025 | J3: 41720800 | K3: 6267700
A4: Acto con cuantía lit B | B4: UMBRAL_MAS_EXCEDENTE | C4: 234500 | D4: 27900 | E4: 0.003 | H4: 2024 | I4: 2024 | J4: 39658600 | K4: 5957900
A5: Acto con cuantía lit B | B5: UMBRAL_MAS_EXCEDENTE | C5: 214600 | D5: 25500 | E5: 0.003 | H5: 2023 | I5: 2023 | J5: 36290800 | K5: 5452000
A6: Acto con cuantía lit B | B6: UMBRAL_MAS_EXCEDENTE | C6: 189700 | D6: 22500 | E6: 0.003 | H6: 2022 | I6: 2022 | J6: 32081700 | K6: 4819700
A7: Acto con cuantía lit B | B7: UMBRAL_MAS_EXCEDENTE | C7: 179600 | D7: 21300 | E7: 0.003 | H7: 2021 | I7: 2021 | J7: 30374600 | K7: 4563200
A8: Acto con cuantía lit C | B8: UMBRAL_MAS_EXCEDENTE | H8: 2026 | I8: 2026
A9: Acto con cuantía lit C | B9: UMBRAL_MAS_EXCEDENTE | C9: 18389629 | D9: 86200 | E9: 0.0035 | H9: 2025 | I9: 2025 | J9: 41720800 | K9: 6267700
A10: Acto con cuantía lit C | B10: UMBRAL_MAS_EXCEDENTE | C10: 17432897 | D10: 81900 | E10: 0.0035 | H10: 2024 | I10: 2024 | J10: 39658600 | K10: 5957900
A11: Acto con cuantía lit C | B11: UMBRAL_MAS_EXCEDENTE | C11: 15918973 | D11: 74900 | E11: 0.0035 | H11: 2023 | I11: 2023 | J11: 36290800 | K11: 5452000
A12: Acto con cuantía lit C | B12: UMBRAL_MAS_EXCEDENTE | C12: 14264469 | D12: 66200 | E12: 0.0035 | H12: 2022 | I12: 2022 | J12: 32081700 | K12: 4819700
A13: Acto con cuantía lit C | B13: UMBRAL_MAS_EXCEDENTE | C13: 13627890 | D13: 62700 | E13: 0.0035 | H13: 2021 | I13: 2021 | J13: 30374600 | K13: 4563200

Sheet Hoja1
A1: LITERAL B. ACTO CON CUANTÍA | D1: LITERAL C. LIQUIDACIÓN DE HERENCIAS Y SOCIEDADES CONYUGALES | G1: PARÁGRAFO 1. EN RECONOCIMIENTO DE FIRMA Y CONTENIDO 10% ADCIONAL POR CADA HOJA RUBRICADA Y SELLADA | H1: 10% ADICIONAL POR CADA FOLIO ENVIADO | I1: LITERAL A. FUERA DE LA CABECERA DEL CÍRCULO | J1: LITERAL B. EN LA CABECERA DEL CÍRCULO | K1: LITERAL C. SUSCRIPCIÓN DE REPRESENTANTES ENTIDADES OFICIALES Y PARTICULARES CON FIRMA REGISTRADA. | L1: Las fundaciones de asistencia o beneficencia pública reconocidas por el Estado, pagarán como suma máxima el valor de XXXXXXX por concepto de derechos notariales, en todos aquellos casos cuya cuantía fuere determinable. | M1: Concurrencia de los Particulares con Entidades Exentas | N1: Actos entre particulares o entre entidades no exentas | O1: Cuando se cumpla lo establecido en el Decreto 2158 de 1995 y 371 de 1996. Como tarifa única sin importar la cantidad de actos | P1: LA ESCRITURA PÚBLICA DE CAMBIO DE NOMBRE | Q1: LA CORRECCIÓN DE ERRORES U OMISIONES EN REGISTRO CIVIL | S1: UVT | T1: (VALOR DE LA ENAJENACIÓN EN UVT - 20000 UVT)*1.5% | U1: ((VALOR DE LA ENAJENACIÓN EN UVT - 50000 UVT) *3.5%) + 450 UVT | V1: LAS QUE DEBAN PRACTICARSE A SOLICITUD DEL USUARIO EN EL DOMICILIO | W1: LAS QUE DEBAN PRACTICARSE EN CLÍNICAS Y HOSPITALES
S2: 52374 | T2: =20000*S2 -> 1047480000 | U2: =50000*S2 -> 2618700000
A3: 246700 | B3: 29400 | C3: 3X1000 | D3: 375.341247 UVT | E3: 18389629 | F3: 3.5X1000 | G3: =#REF!*10% -> #REF! | H3: ='Hoja de control'!P3*10% -> 990 | I3: 18900 | J3: 9400 | K3: 3400 | L3: 285400 | M3: 6267700 | N3: 41720800 | O3: 12900 | P3: 61600 | Q3: 11500 | R3: 10300 | S3: 49799 | T3: =20000*S3 -> 995980000 | U3: =50000*S3 -> 2489950000 | V3: 9800 | W3: 2400
A4: 234500 | B4: 27900 | C4: 3X1000 | D4: 375.341247 UVT | E4: 17432897 | F4: 3.5X1000 | G4: =#REF!*10% -> #REF! | H4: ='Hoja de control'!P4*10% -> 940 | I4: 18000 | J4: 8900 | K4: 3200 | L4: 271300 | M4: 5957900 | N4: 39658600 | O4: 12300 | P4: 58600 | Q4: 10900 | S4: 47065 | T4: =20000*S4 -> 941300000 | U4: =50000*S4 -> 2353250000 | V4: 9300 | W4: 2300
A5: 214600 | B5: 25500 | C5: 3X1000 | D5: 375.341247 UVT | E5: 15918973 | F5: 3.5X1000 | G5: =#REF!*10% -> #REF! | H5: ='Hoja de control'!P5*10% -> 860 | I5: 16500 | J5: 8100 | K5: 2900 | L5: 248300 | M5: 5452000 | N5: 36290800 | O5: 11300 | P5: 53600 | Q5: 10000 | S5: 42412 | T5: =20000*S5 -> 848240000 | U5: =50000*S5 -> 2120600000 | V5: 8500 | W5: 2100
A6: 189700 | B6: 22500 | C6: 3X1000 | D6: 375.341247 UVT | E6: 14264469 | F6: 3.5X1000 | G6: =#REF!*10% -> #REF! | H6: ='Hoja de control'!P6*10% -> 760 | I6: 14600 | J6: 7200 | K6: 2600 | L6: 219500 | M6: 4819700 | N6: 32081700 | O6: 10000 | P6: 47400 | Q6: 8800 | S6: 38004 | T6: 0 | U6: 0 | V6: 7500 | W6: 1900
A7: 179600 | B7: 21300 | C7: 3X1000 | D7: 15 SMLMV | E7: =15*908526 -> 13627890 | F7: 3.5X1000 | G7: =#REF!*10% -> #REF! | H7: ='Hoja de control'!P7*10% -> 720 | I7: 13800 | J7: 6800 | K7: 2500 | L7: 207800 | M7: 4563200 | N7: 30374600 | O7: 9500 | P7: 44900 | Q7: 8300 | S7: 36308 | T7: 0 | U7: 0 | V7: 7100 | W7: 1800

Sheet 2024
G1: FACTURACIÓN
B2: AÑO 2024 | G2: Concepto | H2: Cant | I2: Valor Unitario | J2: Subtotal
B3: DERECHOS NOTARIALES | G3: Derechos Notariales | H3: 1 | I3: =E13 -> 27900 | J3: =H3*I3 -> 27900 | K3: =IF(J3>J28,K28,K29) -> NO Genera Aporte Especial
B4: Resolución No 00773 del 26 de enero de 2024 | G4: Copias | H4: 9 | I4: =E31 -> 5000 | J4: =H4*I4 -> 45000
H5: 1 | I5: =E32 -> 0 | J5: =H5*I5 -> 0
B6: AUTORIZACIÓN DE ACTOS | G6: Concepto | H6: 0 | I6: 0 | J6: =H6*I6 -> 0
B7: Art. 2 Lit. a) | C7: Actos SIN Cuantía | G7: SUBTOTAL | J7: =SUM(J3:J6) -> 72900 | K7: 2
C8: Actos SIN Cuantía | D8: Valor a Pagar | E8: 81900 | G8: IVA | J8: =J7*19% -> 13851 | K8: 3
B9: Actos CON Cuantía | G9: TOTAL | J9: =SUM(J7:J8) -> 86751 | K9: 4
B10: Art. 2 Lit. b) | C10: Igual o Inferior a | D10: 234500 | E10: 27900 | G10: RETENCIÓN EN LA FUENTE | H10: 0.01 | I10: =D11 -> 0 | J10: =H10*I10 -> 0
C11: Cuantía | D11: 0 | G11: RETENCIÓN EN LA FUENTE | H11: 0.01 | I11: =D11 -> 0 | J11: =H11*I11 -> 0 | K11: =SUM(K7:K9) -> 9
C12: Superior a $234.500 | D12: =D11-D10 -> -234500 | E12: =(D12*3/1000)+E10 -> 27196.5
C13: VALOR A PAGAR | E13: {=_xlfn.IFS(D11=D10,E10,D11<D10,E10,D11>D10,E12)} -> 27900
B14: Liquidación de herencias y sociedades conyugales
B15: Art. 2 Lit. c) | C15: Inferior a 1591,90 UVB | D15: 1591.9 | E15: Valor a Pagar
C16: Valor UVB | D16: 10951
C17: Inferior a | D17: =D15*D16 -> 17432897 | E17: =E8 -> 81900
C18: Cuantía | D18: 12170695612
C19: Superior a $17.432.896,90 | D19: =D18-D17 -> 1.2153263e+10 | E19: =(D19*3.5/1000)+E17 -> 42618320
C20: VALOR A PAGAR | E20: =_xlfn.IFS(D18=D17,E17,D18<D17,E17,D18>D17,E19) -> 42618320 | G20: APORTES ESPECIALES
B21: Art. 2 Pr. | C21: Valor hoja del instrumento público utilizado por ambas caras. | E21: 5000 | G21: Límite de la remuneración notarial
G22: Art. 39 Concurrencia de los particulares con entidades exentas y límite de la remuneración notarial.
B23: PROTOCOLIZACIÓN
B24: Art. 3 Pr. 1 | C24: Protocolización por cada documento NO esencial del acto, por decisión voluntaria de otorgante. | E24: =E8 -> 81900 | G24: De los derechos que se causen por este concepto, el notario solo podrá percibir como remuneración por sus servicios hasta cinco millones cuatrocientos cincuenta y dos mil pesos. | J24: 5957900 | K24: NO Genera Aporte Especial | L24: =E13-J24 -> -5930000 | M24: 3344987 | N24: =M24-L24 -> 9274987
J25: =IF(J3-J24>0,(J3-J24),K24) -> NO Genera Aporte Especial | K25: No Genera Aporte Especial
B26: CERTIFICACIONES | G26: Art. 40 Actos entre particulares o entre entidades no exentas y límite de la remuneración notarial.
B27: Art. 4 Lit. a) | C27: Por cada certificación de actos o hechos que consten en instrumentos públicos o en documentos protocolizados. | E27: 3800
B28: Art. 4 Lit. b) | C28: Por cada nota de referencia en la escritura pública afectada por nuevas declaraciones de voluntad. | E28: 2300 | G28: De los derechos notariales que se causen en los actos o contratos entre particulares o entre entidades no exentas, el notario solo podrá percibir como remuneración por sus servicios hasta treinta y seis millones doscientos noventa mil ochocientos pesos. | J28: 39658600 | K28: Genera Aporte Especial
J29: =_xlfn.IFS(K3=K28,(J3-J28),K3=K29,K29) -> NO Genera Aporte Especial | K29: NO Genera Aporte Especial
B30: COPIAS
B31: Art. 5 | C31: Copias auténticas que según la Ley debe expedir el Notario de los instrumentos, y demás documentos que reposen en el protocolo de la Notaría, causarán derechos por cada hoja utilizada por ambas caras. | E31: 5000
C32: Por cada cara de una copia simple física expedida por notarios de documentos que reposan en el protocolo, se expedirán en papel común y no podrán contar con ningún sello, firma ni rúbrica adicional a aquellos que se encuentran plasmados en el documento reproducido.
B33: Art. 5 Pr. | C33: Si el usuario requiere impresión de certificados tomados de páginas web de diferentes entidades estatales, tal impresión causará derechos. | E33: 4700
B35: TESTIMONIO NOTARIAL
B36: Art. 6 | C36: Testimonio escrito, en la presentación personal y el reconocimiento de documento privado, autenticidad de firmas puestas en documentos previa confrontación de su correspondencia, autenticidad de firmas y huellas dactilares puestas en su presencia, autenticidad de fotografías de personas. | E36: 2600
C37: Identificación personal del usuario mediante verificación de huella dactilar, por medios electrónicos y cotejo con la base de datos de la Registraduría. | E37: 4400
B38: Art. 6 Pr. 1 | C38: Reconocimiento de firma y contenido, si está conformado por más de un folio, cada hoja que forme parte del mismo, rubricada y sellada, costará el 10% adicional de la tarifa establecida para la autenticación de la firma. | E38: 0.1
B39: Art. 6 Pr. 2 | C39: Imposición de la firma digital. | E39: 9400
C40: Tránsito o transferencia cibernético. | E40: 9400
C41: Si el documento consta de varios folios, el valor adicional será del 10% por folio enviado. | E41: 0.1
B42: Art. 6 Pr. 3 | C42: Impresión de huella dactilar y su certificación en los eventos en que la ley lo exija o cuando solicite el usuario.
C43: Hechos relacionados con el ejercicio de sus funciones ocurridos en su presencia / Actas de Comparecencia. | E43: 18000
C44: Hechos/testimonios relacionados con el ejercicio de sus funciones, que implique el desplazamiento del Notario dentro de la cabecera del círculo. | E44: 135500
B46: DECLARACIÓN EXTRAPROCESO
B47: Art. 7 | C47: Declaración Extraproceso. | E47: 18000
B49: CONSTANCIAS EN ESCRITURAS PÚBLICAS
B50: Art. 8 | C50: Constancia consignada en la matriz de escrituras pública por afectación a vivienda familiar, imperativo legal o acto voluntario de las partes. | E50: 9300
B52: INVENTARIO DE BIENES DE MENORES
B53: Art. 9 | C53: Escritura pública del inventario solemne de bienes del menor, causará derechos calculados sobre el valor de los bienes inventariados.
B55: CAPITULACIONES MATRIMONIALES
B56: Art. 10 | C56: Se tomará como base de liquidación, el valor de los bienes objeto de la misma, el cual no podrá ser inferior del avalúo catastral.
B58: MATRIMONIO CIVIL
B59: Art. 11 | C59: Celebrado en la sede (Notaría), incluida extensión, otorgamiento y autorización de escritura. | E59: 58600
C60: Celebrado por fuera del despacho notarial. | E60: 158100
B62: DISOLUCIÓN Y LIQUIDACIÓN DE SOCIEDAD CONYUGAL Y UNIÓN MARITAL DE HECHO
B63: Art. 12 | C63: Se tomará como base de liquidación el patrimonio líquido. | E63: A Pagar
B64: Literal C Art. 2
B66: TESTAMENTO CERRADO
B67: Art. 13 | C67: Apertura y publicación de testamento cerrado y protocolización de lo actuado, causará los derechos establecidos para los actos sin cuantía. | E67: =E8 -> 81900
B69: PROTOCOLIZACIÓN DEL PROCESO JUDICIAL DE SUCESIÓN
B70: Art. 14 | C70: Se tomará como base el patrimonio líquido, y en todo caso, se aplicará lo dispuesto en el literal c) del artículo 2.
B72: ACTAS DE ADMISIÓN O DEVOLUCIÓN EN TRTÁMITES SUCESORALES
B73: Art. 15 | C73: Actas de admisión o devolución en trámites sucesorales. | E73: 18000
B75: SOCIEDADES
B76: Art. 16 | C76: Se toma como base el capital social suscrito, excepto en las escrituras de constitución de sociedades por acciones, en las cuales la liquidación de se hará con base en el capital autorizado.
B77: Art. 16 Lit. a) | C77: Reforma Estatutaria | E77: A Pagar
C78: Se liquidará sobre el incremento respectivo; en los demás casos en las sociedades por acciones, entiéndase como capital social. el suscrito
B79: Art. 16 Lit. b) | C79: Reforma Estatutaria con Disminución de Capital | E79: A Pagar
C80: Cuando la reforma implique disminución del capital, la liquidación se efectuará como acto sin cuantía. | E80: =E8 -> 81900
B81: Art. 16 Lit. c) | C81: Fusión de Sociedades | E81: A Pagar
C82: Se tomará como base el capital de la nueva sociedad o de la absorbente. En la transformación de una sociedad, será con base en el capital social. Siendo el capital suscrito el de las sociedades por acciones.
B83: Art. 16 Lit. d) | C83: Escisión de Sociedades | E83: A Pagar
C84: Se liquidarán como acto sin cuantía. | E84: =E8 -> 81900
B85: Art. 16 Lit. e) | C85: Cambio de Razón Social | E85: A Pagar
C86: Cambio de razón social y prórroga del término de duración de una sociedad, se efectuará como acto sin cuantía. | E86: =E8 -> 81900
B87: Art. 16 Lit. f) | C87: Liquidación de Sociedades | E87: A Pagar
C88: Se tomará como base el activo líquido, pero en todo caso será necesario protocolizar el balance debidamente firmado por contador en el cual se señale el pasivo declarado.
B90: Constitución y Reformas estatutarias de Empresas Industriales y Comerciales del Estado
B91: Art. 17 | C91: Se liquidará sobre la base de los aportes de las entidades no exentas que intervengan en el acto, las cuales pagarán en proporción a sus aportes.
C92: Referente a reformas estatutarias con incremento de capital, los respectivos derechos estarán a cargo de las Empresas Industriales y Comerciales del Estado, tomando como base el incremento dado.
B94: Constitución y reformas estatutarias de sociedades de economía mixta
B95: Art. 18 | C95: Se liquidarán sobre la base de los aportes de los particulares y de las entidades no exentas que intervengan en el acto, los cuales pagarán en proporción a los mismos.
C96: Referente a reformas estatutarias con incremento de capital, los respectivos derechos estarán a cargo de tales organismos, tomando como base el incremento dado.
B98: Fiducia Mercantil
B99: Art. 19 | C99: Se tendrán como acto con cuantía, y se cobrará de conformidad con lo dispuesto en el literal b) del artículo 2.
B101: Fiducia en Garantía
B102: Art. 20 | C102: Causará por derechos notariales los ordenados para las hipotecas.
B104: Fiducia de Administración
B105: Art. 21 | C105: Se tendrá como cuantía del acto el valor estipulado como remuneración para el fiduciario.
B107: Leasing
B108: Art. 22 | C108: Los derechos notariales se liquidarán teniendo en cuenta la cuantía total de tales prestaciones. Si el plazo fuere indeterminado la base de la liquidación será el monto de la misma en cinco años.
B110: Contrato de leasing sin escritura pública.
B111: Art. 23 | C111: Cuando la cuantía del acto sea inferior a la del avalúo catastral, al autoavalúo o al valor del remate, los derechos se liquidarán con base en el concepto de los mencionados que presente el mayor valor.
B113: Hipotecas abiertas con límite de cuantía
B114: Art. 24 | C114: Hipotecas abiertas en donde se fijen las cuantías máximas de la obligación, los derechos notariales se liquidarán con base en dicha cuantía.
B116: Hipotecas abiertas sin límite de cuantía
B117: Art. 25 | C117: Los derechos notariales se liquidarán con base en la constancia, documento o carta que para tal efecto deberá presentar la persona o entidad acreedora, en la que se fijará de manera clara y precisa el cupo o monto del crédito aprobado que garantiza la respectiva hipoteca.
B119: Venta con hipoteca abierta sin límite de cuantía
B120: Art. 26 | C120: Los derechos notariales correspondientes a la hipoteca se liquidarán con base en el precio de la venta, cuando en el instrumento no se señale la parte del precio garantizado con la hipoteca.
B122: Cancelación de hipotecas abiertas
...

Sheet Formato 2B RC
A2: AÑO 2018
A3: MES | B3: FECHA DE ENVIO | C3: OBSERVACIONES
A4: Agosto | B4: 43350 | C4: Niguna
A5: Septiembre | B5: 43381 | C5: Niguna
A6: Octubre | B6: 43412 | C6: Niguna
A7: Noviembre | B7: 43441 | C7: Niguna
A8: Diciembre | B8: 43473 | C8: Niguna
A10: AÑO 2019
A11: MES | B11: FECHA DE ENVIO | C11: OBSERVACIONES
A12: Enero | B12: 43502 | C12: Ninguna
A13: Febrero | B13: 43531 | C13: Ninguna
A14: Marzo | B14: 5/0$/2019 | C14: Ninguna
A15: Abril | B15: 43594 | C15: Ninguna
A16: Mayo | B16: 7/0/2019 | C16: Ninguna
A17: Junio | B17: 43654 | C17: Ninguna
A18: Julio | B18: 43685 | C18: Ninguna
A19: Agosto | B19: 43714 | C19: Ninguna
A20: Septiembre | B20: 43745 | C20: Ninguna
A21: Octubre | B21: 43777 | C21: Ninguna
A22: Noviembre | B22: 43808 | C22: Ninguna
A23: Diciembre | B23: 43839 | C23: Ninguna
A25: AÑO 2020
A26: MES | B26: FECHA DE ENVIO | C26: OBSERVACIONES
A27: Enero | B27: 43865 | C27: Ninguna
A28: Febrero | B28: 43895 | C28: Ninguna
A29: Marzo | B29: 44083 | C29: Por pandemia se envia en una misma fecha
A30: Abril | B30: 44083
A31: Mayo | B31: 44083
A32: Junio | B32: 44083
A33: Julio | B33: 44083
A34: Agosto | B34: 44083
A35: Septiembre | B35: 44112 | C35: Ninguna
A36: Octubre | B36: 44144 | C36: Ninguna
A37: Noviembre | B37: 44174 | C37: Ninguna
A38: Diciembre | B38: 44204 | C38: Ninguna
A40: AÑO 2021
A41: MES | B41: FECHA DE ENVIO | C41: OBSERVACIONES
A42: Enero | B42: 44232 | C42: Niguna
A43: Febrero | B43: 44260 | C43: Niguna
A44: Marzo | B44: 44295 | C44: Niguna
A45: Abril | B45: 44326 | C45: Niguna
A46: Mayo | B46: 44351 | C46: Niguna
A47: Junio | B47: 44386 | C47: Niguna
A48: Julio | B48: 44413 | C48: Niguna
A49: Agosto | B49: 44445 | C49: Niguna
A50: Septiembre | B50: 44481 | C50: Niguna
A51: Octubre | B51: 44511 | C51: Niguna
A52: Noviembre | B52: 10/12/1021 | C52: Niguna
A53: Diciembre | B53: 44566 | C53: Niguna
A55: AÑO 2022
A56: MES | B56: FECHA DE ENVIO | C56: OBSERVACIONES
A57: Enero | B57: 44596 | C57: Ninguna
A58: Febrero | B58: 44627 | C58: Ninguna
A59: Marzo | B59: 44658 | C59: Ninguna
A60: Abril | B60: 44690 | C60: Ninguna
A61: Mayo | B61: 44718 | C61: Ninguna
A62: Junio | B62: 44750 | C62: Ninguna
A63: Julio | B63: 44778 | C63: Ninguna
A64: Agosto | B64: 44811 | C64: Ninguna
A65: Septiembre | B65: 44844 | C65: Ninguna
A66: Octubre | B66: 44876 | C66: Ninguna
A67: Noviembre | B67: 44910 | C67: Ninguna
A68: Diciembre | B68: 44932 | C68: Ninguna

Sheet Reporte ICBF-Otros
A1: REPORTE AL I.C.B.F RELACIONES DE HIJOS EXTRAMATRIMONIALES-DEFENSOR DE FAMILIA. DEFENSOR DE FAMILIA-COMISARIO DE FAMILIA-ACTAS COMPLEMENTARIAS.
A3: AÑO 2018
A4: MES | B4: FECHA DE ENVIO | C4: OBSERVACIONES
A5: Agosto - Diciembre | B5: No hubo | C5: No hubo
A7: AÑO 2019
A8: MES | B8: FECHA DE ENVIO | C8: OBSERVACIONES
A9: Enero - Marzo | B9: No hubo | C9: No hubo
A10: Abril | B10: 43592 | C10: Ninguna
A11: Mayo - Julio | B11: No hubo | C11: No hubo
A12: Agosto | B12: 43714 | C12: Ninguna
A13: Septiembre | B13: 43742 | C13: Ninguna
A14: Octubre | B14: No hubo | C14: No hubo
A15: Noviembre | B15: 43803 | C15: Ninguna
A16: Diciembre | B16: No hubo | C16: No hubo
A18: AÑO 2020
A19: MES | B19: FECHA DE ENVIO | C19: OBSERVACIONES
A20: Noviembre | B20: 44169 | C20: Ninguna
A23: AÑO 2021
A24: MES | B24: FECHA DE ENVIO | C24: OBSERVACIONES
A25: Enero - Diciembre | B25: Ninguna | C25: Ninguna
A27: AÑO 2022
A28: MES | B28: FECHA DE ENVIO | C28: OBSERVACIONES
A29: Enero - Diciembre | B29: Ninguna | C29: Ninguna
